Workbook
Name Себестоимость: [1]Справочник!$C$3:$C$6
Name Себестоимость: Справочник!$C$3:$C$6
Name Capex_группы_СПП: [1]Справочник!$A$3:$A$26
Name Capex_группы_СПП: Справочник!$A$3:$A$25
Name Language: [2]Outputs!$AU$1
Name OPEX_группы_СПП: [1]Справочник!$B$3:$B$15
Name OPEX_группы_СПП: Справочник!$B$3:$B$15
Name OPEX_PL: Справочник!$D$3:$D$15
Name SAPCrosstab1: #REF!
Name SAPFdd1: #REF!
Name SAPFdd10: #REF!
Name SAPFdd11: #REF!
Name SAPFdd12: #REF!
Name SAPFdd13: #REF!
Name SAPFdd14: #REF!
Name SAPFdd15: #REF!
Name SAPFdd16: #REF!
Name SAPFdd17: #REF!
Name SAPFdd18: #REF!
Name SAPFdd2: #REF!
Name SAPFdd29: #REF!
Name SAPFdd3: #REF!
Name SAPFdd30: #REF!
Name SAPFdd31: #REF!
Name SAPFdd32: #REF!
Name SAPFdd33: #REF!
Name SAPFdd34: #REF!
Name SAPFdd35: #REF!
Name SAPFdd36: #REF!
Name SAPFdd37: #REF!
Name SAPFdd38: #REF!
Name SAPFdd39: #REF!
Name SAPFdd4: #REF!
Name SAPFdd40: #REF!
Name SAPFdd41: #REF!
Name SAPFdd5: #REF!
Name SAPFdd6: #REF!
Name SAPFdd7: #REF!
Name SAPFdd8: #REF!
Name SAPFdd9: #REF!
Name WORKBOOK_SAPBEXq0001: "DP_4"

Sheet Инструкция
B1: ЛЕГЕНДА
C2: Ячейки к заполнению значений / показателей
C3: Расчетные поля (не исправлять)
B5: ПРАВИЛА ДЛЯ КОРРЕКТНОЙ ЗАГРУЗКИ ШАБЛОНА НА ФИНАНСОВЫЙ ПОРТАЛ
B7: Финансовый портал для расчета показателей забирает данные только из вкладок "Как есть" и "Как будет". Поэтому правила корректной загрузки ТЭО на Финансовый портал применимы только к указанным вкладкам.
B8: 1. | C8: Нельзя добавлять новые строки, так как калькулятор Финансового портала настроен на определенный диапазон.
B9: 2. | C9: Нельзя вносить во всех голубых блоках отрицательные суммы (со знаком "-"), при сохранении шаблона калькулятор Финансового портала проигнорирует эти суммы. Рекомендуется учитывать отрицательные суммы в положительных суммах других месяцев в пределах одного года (например, при наличии суммы сторно в январе -100, ее следует "внести" в общую сумму в феврале: если в феврале было без сторно 500, с учетом сторно января станет 400)
B10: 3. | C10: Все значения в голубых полях на вкладках "Как есть" и "Как будет" заполняются строго БЕЗ ссылок на вспомогательные расчеты - Hard-значения (эффекты и затраты). Все необходимые детали по расчетам эффектов и затратам можно привести на дополнительной/вспомогательной вкладке.
B11: 4. | C11: Постпроектные расходы должны начинаться строго после даты Окончания проекта (ячейка D1).
B12: 5. | C12: Проектные расходы должны учитываться в диапазоне указанных Даты начала проекта (ячейка С1) и Даты окончания проекта (ячейка D1).
B13: 6. | C13: ВЕСЬ САРЕХ и ОРЕХ НА РЕАЛИЗАЦИЮ ПРОЕКТА должен "сидеть" в Проектных расходах, все что идет на тех поддержку после - в Постпроектных расходах, и ТОЛЬКО ЕСЛИ проект предполагает экономию на САРЕХ - это отражается в блоке с Экономическим эффектом. Блок "Экономический эффект" на Листе "Как есть" используется только для заполнения сумм эффекта по проекту/продукту, при условии, что ТЭО для проекта/продукта построен по принципу сравнения объема затрат или суммы дохода "До реализации проекта" (Как есть) и "После реализации проекта" (Как будет). Если эффект посчитан исключительно на дельте (уже посчитанная разница между Как есть и Как будет), то Лист "Как есть" не заполняется. ВАЖНО! После внесения данных на вкладки "Как есть" и "Как будет", обязательно проверить, что период начала инвестиций в проект (САРЕХ, ОРЕХ) наступает/закладывается ДО получения экономического эффекта от инициативы. Т.е. эффект от инициативы может быть получен только после момента старта проекта/продукта и вложения инвестиций.
B14: 7. | C14: Горизонт планирования определяется количеством месяцев, указанных в Сроке полезного использования (ячейка С7). Суммы, проставленные после последнего месяца горизонта планирования, калькулятор Финансового портала проигнорирует.
B15: 8. | C15: Привлечение дополнительной прибыли для Компании рассчитывается либо через ВАЛОВЫЙ ДОХОД, либо через КОММЕРЧЕСКУЮ МАРЖУ. Нельзя заполнять ОДНОВРЕМЕННО значения в строке Выручка/Себестоимость и Коммерческая маржа, т.к. Фин портал тогда рассматривает это как несколько доходных потоков и завышает IRR при сохранении на Финансовом портале.
B18: ПЕРВЫЕ ОБЯЗАТЕЛЬНЫЕ ШАГИ:
B20: 1. | C20: Указываем дату начала проекта/продукта на Листе "Как есть" в ячейке C1, в ячейке D1 - дату окончания проекта/продукта. Дата окончания проекта/продукта: окончание срока реализации внедряемого в рамках инициативы функционала = дата закрытия СПП (совпадает с датой завершения инвестиций в проект/продукт)
B22: 2. | C22: На Листе "Как есть" в ячейке C7 указываем в месяцах срок полезного использования оборудования (СПИ) или капитализируемого нематериалого актива (НМА), закупаемого/реализуемого в рамках проекта/продукта, на который будут рассчитываться показатели эффективности на вкладке "Свод"
B24: ! | C24: ИНФОРМАЦИЯ !
B25: Блок "Экономический эффект" на Листе "Как есть" используется только для заполнения сумм эффекта по проекту/продукту, при условии, что ТЭО для проекта/продукта построен по принципу сравнения объема затрат или суммы дохода "До реализации проекта" (Как есть) и "После реализации проекта" (Как будет). Если эффект посчитан исключительно на дельте (уже посчитанная разница между Как есть и Как будет), то Лист "Как есть" не заполняется.
B27: НАПОЛНЕНИЕ ТЭО ДАННЫМИ:
C29: Лист "Как есть"
B31: 3. | C31: Выбираем необходимые статьи в столбце A в зависимости от монетарного эффекта проекта/продукта:
C32: ● Экономия/снижение затрат
C33: → СAPEX или OPEX
C34: → СЕБЕСТОИМОСТЬ
C35: ● Привлечение дополнительной прибыли для Комании
C36: → ВЫРУЧКА помним, что Выручка - это РТО очищенный от НДС
C37: → ВАЛОВЫЙ ДОХОД помним, что Валовый доход - это Выручка за минусом Себестоимости товара
C38: → КОММЕРЧЕСКАЯ МАРЖА помним, что Коммерческая маржа - это сумма Front Margin и Back Margin
B40: 4. | C40: Наполняем диапазон ячеек C55:GT81 данными, в соответствии с выбранными статьями (столбец A) и периодами (строка 14) САРЕХ/ОРЕХ значения в голубых полях заполняются без знака "-" (положительное значение инвестиций/затрат), а также БЕЗ ссылок на вспомогательные расчеты
C41: Ячейки с серой заливкой в столбце B заполняются информационно для детализации данных.
C43: Лист "Как будет"
C45: Проектные расходы
B47: 5. | C47: Выбираем необходимые статьи затрат в столбце A в зависимости от вида затрат (CAPEX или OPEX)
B49: 6. | C49: Наполняем диапазон ячеек C17:GT33 данными, в соответствии с выбранными статьями (столбец A) и периодами (строка 14) САРЕХ/ОРЕХ значения в голубых полях заполняются без знака "-" (положительное значение инвестиций/затрат),а также без ссылок на вспомогательные расчеты
C50: Ячейки с серой заливкой в столбце B заполняются информационно для детализации данных.
C52: Постпроектные расходы Пост-проектные расходы - это затраты на тех. поддержку (после передачи проекта/продукта на тех. поддержку), последующие доработки действующих внедренных в рамках проекта/продукта систем и т.п. Постпроектные затраты начинаются не раньше даты окончания проекта/продукта/завершения основной фазы финансирования проекта/продукта (Лист "Как будет" ячейка D1). Постпроектные расходы (при их наличии) закладываются до конца горизонта планирования.
B54: 7. | C54: Выбираем необходимые статьи затрат в столбце A в зависимости от вида затрат (CAPEX или OPEX)
B56: 8. | C56: Наполняем диапазон ячеек C36:GT52 данными, в соответствии с выбранными статьями (столбец A) и периодами (строка 14) САРЕХ/ОРЕХ значения в голубых полях заполняются без знака "-" (положительное значение инвестиций/затрат),а также без ссылок на вспомогательные расчеты
C57: Ячейки с серой заливкой в столбце B заполняются информационно для детализации данных.
B58: ! | C58: Помним, что Постпроектные затраты начинаются не раньше даты окончания проекта/продукта (Лист "Как будет" ячейка D1) !
C60: Экономический эффект
B62: 9. | C62: Статьи для эффекта на Листе "Как будет" идентичны статьям для эффекта указанным на Листе "Как есть" столбец A. Для замены указанных значений на листе "Как будет", необходимо поменять статьи эффекта на Листе "Как есть".
B64: 10. | C64: Наполняем диапазон ячеек C55:GT81 с голубой заливкой данными, в соответствии с выбранными статьями (столбец A) и периодами (строка 14) - САРЕХ/ОРЕХ значения в голубых полях заполняются без знака "-" (положительное значение инвестиций/затрат), а также без ссылок на вспомогательные расчеты
C65: Ячейки с серой заливкой в столбце B заполняются информационно для детализации данных.
B67: Полученный результат расчета показателей экономичекой эффективности можно увидеть на Листе "Свод" диапазон ячеек B212:C216

Sheet Свод
C1: =IF(C7<>0,1,0) -> 1 | D1: =IF(D7<>0,1,0) -> 1 | E1: =IF(E7<>0,1,0) -> 1 | F1: =IF(F7<>0,1,0) -> 1 | G1: =IF(G7<>0,1,0) -> 1 | H1: =IF(H7<>0,1,0) -> 0 | I1: =IF(I7<>0,1,0) -> 0
B2: Технико-экономическое обоснование | E2: Актуальный шаблон от 10.2025
B4: тыс. руб. | C4: ='Как есть'!C12 -> 2026 | D4: =C4+1 -> 2027 | E4: =D4+1 -> 2028 | F4: =E4+1 -> 2029 | G4: =F4+1 -> 2030 | H4: =G4+1 -> 2031 | I4: =H4+1 -> 2032 | J4: =I4+1 -> 2033 | K4: =J4+1 -> 2034 | ... M4: =L4+1 -> 2036
B5: Инфляция | C5: =HLOOKUP(C4,'Как есть'!$C$3:$S$5,2) -> 0.07 | D5: =HLOOKUP(D4,'Как есть'!$C$3:$S$5,2) -> 0.07 | E5: =HLOOKUP(E4,'Как есть'!$C$3:$S$5,2) -> 0.05 | F5: =HLOOKUP(F4,'Как есть'!$C$3:$S$5,2) -> 0.05 | G5: =HLOOKUP(G4,'Как есть'!$C$3:$S$5,2) -> 0.05 | H5: =HLOOKUP(H4,'Как есть'!$C$3:$S$5,2) -> 0.05 | I5: =HLOOKUP(I4,'Как есть'!$C$3:$S$5,2) -> 0.05 | J5: =HLOOKUP(J4,'Как есть'!$C$3:$S$5,2) -> 0.05 | ... M5: =HLOOKUP(M4,'Как есть'!$C$3:$S$5,2) -> 0.05
B6: Ставка дисконтирования (avg monthly WACC) | C6: =IFERROR(SUMIFS('Как будет'!5:5,'Как будет'!9:9,Свод!C4)/COUNTIFS('Как будет'!9:9,Свод!C4),Свод!B6) -> 0.16 | D6: =IFERROR(SUMIFS('Как будет'!5:5,'Как будет'!9:9,Свод!D4)/COUNTIFS('Как будет'!9:9,Свод!D4),Свод!C6) -> 0.16 | E6: =IFERROR(SUMIFS('Как будет'!5:5,'Как будет'!9:9,Свод!E4)/COUNTIFS('Как будет'!9:9,Свод!E4),Свод!D6) -> 0.16 | F6: =IFERROR(SUMIFS('Как будет'!5:5,'Как будет'!9:9,Свод!F4)/COUNTIFS('Как будет'!9:9,Свод!F4),Свод!E6) -> 0.16 | G6: =IFERROR(SUMIFS('Как будет'!5:5,'Как будет'!9:9,Свод!G4)/COUNTIFS('Как будет'!9:9,Свод!G4),Свод!F6) -> 0.16 | H6: =IFERROR(SUMIFS('Как будет'!5:5,'Как будет'!9:9,Свод!H4)/COUNTIFS('Как будет'!9:9,Свод!H4),Свод!G6) -> 0.16 | I6: =IFERROR(SUMIFS('Как будет'!5:5,'Как будет'!9:9,Свод!I4)/COUNTIFS('Как будет'!9:9,Свод!I4),Свод!H6) -> 0.16 | J6: =IFERROR(SUMIFS('Как будет'!5:5,'Как будет'!9:9,Свод!J4)/COUNTIFS('Как будет'!9:9,Свод!J4),Свод!I6) -> 0.16 | ... M6: =IFERROR(SUMIFS('Как будет'!5:5,'Как будет'!9:9,Свод!M4)/COUNTIFS('Как будет'!9:9,Свод!M4),Свод!L6) -> 0.16
A7: =SUM(C7:M7) -> 60 | B7: Кол-во месяцев | C7: =COUNTIF('Как есть'!12:12,Свод!C4) -> 12 | D7: =COUNTIF('Как есть'!12:12,Свод!D4) -> 12 | E7: =COUNTIF('Как есть'!12:12,Свод!E4) -> 12 | F7: =COUNTIF('Как есть'!12:12,Свод!F4) -> 12 | G7: =COUNTIF('Как есть'!12:12,Свод!G4) -> 12 | H7: =COUNTIF('Как есть'!12:12,Свод!H4) -> 0 | I7: =COUNTIF('Как есть'!12:12,Свод!I4) -> 0 | J7: =COUNTIF('Как есть'!12:12,Свод!J4) -> 0 | ... M7: =COUNTIF('Как есть'!12:12,Свод!M4) -> 0
B8: AS IS
B9: Проектные расходы
B10: Инвестиционная деятельность | C10: =SUMIF('Как есть'!$12:$12,Свод!C4,'Как есть'!$16:$16) -> 0 | D10: =SUMIF('Как есть'!$12:$12,Свод!D4,'Как есть'!$16:$16) -> 0 | E10: =SUMIF('Как есть'!$12:$12,Свод!E4,'Как есть'!$16:$16) -> 0 | F10: =SUMIF('Как есть'!$12:$12,Свод!F4,'Как есть'!$16:$16) -> 0 | G10: =SUMIF('Как есть'!$12:$12,Свод!G4,'Как есть'!$16:$16) -> 0 | H10: =SUMIF('Как есть'!$12:$12,Свод!H4,'Как есть'!$16:$16) -> 0 | I10: =SUMIF('Как есть'!$12:$12,Свод!I4,'Как есть'!$16:$16) -> 0 | J10: =SUMIF('Как есть'!$12:$12,Свод!J4,'Как есть'!$16:$16) -> 0 | ... M10: =SUMIF('Как есть'!$12:$12,Свод!M4,'Как есть'!$16:$16) -> 0
B11: Земельные участки | C11: =-SUMIF(Доп.расчеты!$3:$3,Свод!C$4,Доп.расчеты!110:110) -> 0 | D11: =-SUMIF(Доп.расчеты!$3:$3,Свод!D$4,Доп.расчеты!110:110) -> 0 | E11: =-SUMIF(Доп.расчеты!$3:$3,Свод!E$4,Доп.расчеты!110:110) -> 0 | F11: =-SUMIF(Доп.расчеты!$3:$3,Свод!F$4,Доп.расчеты!110:110) -> 0 | G11: =-SUMIF(Доп.расчеты!$3:$3,Свод!G$4,Доп.расчеты!110:110) -> 0 | H11: =-SUMIF(Доп.расчеты!$3:$3,Свод!H$4,Доп.расчеты!110:110) -> 0 | I11: =-SUMIF(Доп.расчеты!$3:$3,Свод!I$4,Доп.расчеты!110:110) -> 0 | J11: =-SUMIF(Доп.расчеты!$3:$3,Свод!J$4,Доп.расчеты!110:110) -> 0 | ... M11: =-SUMIF(Доп.расчеты!$3:$3,Свод!M$4,Доп.расчеты!110:110) -> 0
B12: Здания и сооружения | C12: =-SUMIF(Доп.расчеты!$3:$3,Свод!C$4,Доп.расчеты!111:111) -> 0 | D12: =-SUMIF(Доп.расчеты!$3:$3,Свод!D$4,Доп.расчеты!111:111) -> 0 | E12: =-SUMIF(Доп.расчеты!$3:$3,Свод!E$4,Доп.расчеты!111:111) -> 0 | F12: =-SUMIF(Доп.расчеты!$3:$3,Свод!F$4,Доп.расчеты!111:111) -> 0 | G12: =-SUMIF(Доп.расчеты!$3:$3,Свод!G$4,Доп.расчеты!111:111) -> 0 | H12: =-SUMIF(Доп.расчеты!$3:$3,Свод!H$4,Доп.расчеты!111:111) -> 0 | I12: =-SUMIF(Доп.расчеты!$3:$3,Свод!I$4,Доп.расчеты!111:111) -> 0 | J12: =-SUMIF(Доп.расчеты!$3:$3,Свод!J$4,Доп.расчеты!111:111) -> 0 | ... M12: =-SUMIF(Доп.расчеты!$3:$3,Свод!M$4,Доп.расчеты!111:111) -> 0
B13: Помещения в составе зданий и сооружений | C13: =-SUMIF(Доп.расчеты!$3:$3,Свод!C$4,Доп.расчеты!112:112) -> 0 | D13: =-SUMIF(Доп.расчеты!$3:$3,Свод!D$4,Доп.расчеты!112:112) -> 0 | E13: =-SUMIF(Доп.расчеты!$3:$3,Свод!E$4,Доп.расчеты!112:112) -> 0 | F13: =-SUMIF(Доп.расчеты!$3:$3,Свод!F$4,Доп.расчеты!112:112) -> 0 | G13: =-SUMIF(Доп.расчеты!$3:$3,Свод!G$4,Доп.расчеты!112:112) -> 0 | H13: =-SUMIF(Доп.расчеты!$3:$3,Свод!H$4,Доп.расчеты!112:112) -> 0 | I13: =-SUMIF(Доп.расчеты!$3:$3,Свод!I$4,Доп.расчеты!112:112) -> 0 | J13: =-SUMIF(Доп.расчеты!$3:$3,Свод!J$4,Доп.расчеты!112:112) -> 0 | ... M13: =-SUMIF(Доп.расчеты!$3:$3,Свод!M$4,Доп.расчеты!112:112) -> 0
B14: Строительство и ремонты | C14: =-SUMIF(Доп.расчеты!$3:$3,Свод!C$4,Доп.расчеты!113:113) -> 0 | D14: =-SUMIF(Доп.расчеты!$3:$3,Свод!D$4,Доп.расчеты!113:113) -> 0 | E14: =-SUMIF(Доп.расчеты!$3:$3,Свод!E$4,Доп.расчеты!113:113) -> 0 | F14: =-SUMIF(Доп.расчеты!$3:$3,Свод!F$4,Доп.расчеты!113:113) -> 0 | G14: =-SUMIF(Доп.расчеты!$3:$3,Свод!G$4,Доп.расчеты!113:113) -> 0 | H14: =-SUMIF(Доп.расчеты!$3:$3,Свод!H$4,Доп.расчеты!113:113) -> 0 | I14: =-SUMIF(Доп.расчеты!$3:$3,Свод!I$4,Доп.расчеты!113:113) -> 0 | J14: =-SUMIF(Доп.расчеты!$3:$3,Свод!J$4,Доп.расчеты!113:113) -> 0 | ... M14: =-SUMIF(Доп.расчеты!$3:$3,Свод!M$4,Доп.расчеты!113:113) -> 0
B15: Холодильное оборудование | C15: =-SUMIF(Доп.расчеты!$3:$3,Свод!C$4,Доп.расчеты!114:114) -> 0 | D15: =-SUMIF(Доп.расчеты!$3:$3,Свод!D$4,Доп.расчеты!114:114) -> 0 | E15: =-SUMIF(Доп.расчеты!$3:$3,Свод!E$4,Доп.расчеты!114:114) -> 0 | F15: =-SUMIF(Доп.расчеты!$3:$3,Свод!F$4,Доп.расчеты!114:114) -> 0 | G15: =-SUMIF(Доп.расчеты!$3:$3,Свод!G$4,Доп.расчеты!114:114) -> 0 | H15: =-SUMIF(Доп.расчеты!$3:$3,Свод!H$4,Доп.расчеты!114:114) -> 0 | I15: =-SUMIF(Доп.расчеты!$3:$3,Свод!I$4,Доп.расчеты!114:114) -> 0 | J15: =-SUMIF(Доп.расчеты!$3:$3,Свод!J$4,Доп.расчеты!114:114) -> 0 | ... M15: =-SUMIF(Доп.расчеты!$3:$3,Свод!M$4,Доп.расчеты!114:114) -> 0
B16: Стеллажное оборудование | C16: =-SUMIF(Доп.расчеты!$3:$3,Свод!C$4,Доп.расчеты!115:115) -> 0 | D16: =-SUMIF(Доп.расчеты!$3:$3,Свод!D$4,Доп.расчеты!115:115) -> 0 | E16: =-SUMIF(Доп.расчеты!$3:$3,Свод!E$4,Доп.расчеты!115:115) -> 0 | F16: =-SUMIF(Доп.расчеты!$3:$3,Свод!F$4,Доп.расчеты!115:115) -> 0 | G16: =-SUMIF(Доп.расчеты!$3:$3,Свод!G$4,Доп.расчеты!115:115) -> 0 | H16: =-SUMIF(Доп.расчеты!$3:$3,Свод!H$4,Доп.расчеты!115:115) -> 0 | I16: =-SUMIF(Доп.расчеты!$3:$3,Свод!I$4,Доп.расчеты!115:115) -> 0 | J16: =-SUMIF(Доп.расчеты!$3:$3,Свод!J$4,Доп.расчеты!115:115) -> 0 | ... M16: =-SUMIF(Доп.расчеты!$3:$3,Свод!M$4,Доп.расчеты!115:115) -> 0
B17: Производственное оборудование | C17: =-SUMIF(Доп.расчеты!$3:$3,Свод!C$4,Доп.расчеты!116:116) -> 0 | D17: =-SUMIF(Доп.расчеты!$3:$3,Свод!D$4,Доп.расчеты!116:116) -> 0 | E17: =-SUMIF(Доп.расчеты!$3:$3,Свод!E$4,Доп.расчеты!116:116) -> 0 | F17: =-SUMIF(Доп.расчеты!$3:$3,Свод!F$4,Доп.расчеты!116:116) -> 0 | G17: =-SUMIF(Доп.расчеты!$3:$3,Свод!G$4,Доп.расчеты!116:116) -> 0 | H17: =-SUMIF(Доп.расчеты!$3:$3,Свод!H$4,Доп.расчеты!116:116) -> 0 | I17: =-SUMIF(Доп.расчеты!$3:$3,Свод!I$4,Доп.расчеты!116:116) -> 0 | J17: =-SUMIF(Доп.расчеты!$3:$3,Свод!J$4,Доп.расчеты!116:116) -> 0 | ... M17: =-SUMIF(Доп.расчеты!$3:$3,Свод!M$4,Доп.расчеты!116:116) -> 0
B18: Торговое оборудование | C18: =-SUMIF(Доп.расчеты!$3:$3,Свод!C$4,Доп.расчеты!117:117) -> 0 | D18: =-SUMIF(Доп.расчеты!$3:$3,Свод!D$4,Доп.расчеты!117:117) -> 0 | E18: =-SUMIF(Доп.расчеты!$3:$3,Свод!E$4,Доп.расчеты!117:117) -> 0 | F18: =-SUMIF(Доп.расчеты!$3:$3,Свод!F$4,Доп.расчеты!117:117) -> 0 | G18: =-SUMIF(Доп.расчеты!$3:$3,Свод!G$4,Доп.расчеты!117:117) -> 0 | H18: =-SUMIF(Доп.расчеты!$3:$3,Свод!H$4,Доп.расчеты!117:117) -> 0 | I18: =-SUMIF(Доп.расчеты!$3:$3,Свод!I$4,Доп.расчеты!117:117) -> 0 | J18: =-SUMIF(Доп.расчеты!$3:$3,Свод!J$4,Доп.расчеты!117:117) -> 0 | ... M18: =-SUMIF(Доп.расчеты!$3:$3,Свод!M$4,Доп.расчеты!117:117) -> 0
B19: Складское оборудование | C19: =-SUMIF(Доп.расчеты!$3:$3,Свод!C$4,Доп.расчеты!118:118) -> 0 | D19: =-SUMIF(Доп.расчеты!$3:$3,Свод!D$4,Доп.расчеты!118:118) -> 0 | E19: =-SUMIF(Доп.расчеты!$3:$3,Свод!E$4,Доп.расчеты!118:118) -> 0 | F19: =-SUMIF(Доп.расчеты!$3:$3,Свод!F$4,Доп.расчеты!118:118) -> 0 | G19: =-SUMIF(Доп.расчеты!$3:$3,Свод!G$4,Доп.расчеты!118:118) -> 0 | H19: =-SUMIF(Доп.расчеты!$3:$3,Свод!H$4,Доп.расчеты!118:118) -> 0 | I19: =-SUMIF(Доп.расчеты!$3:$3,Свод!I$4,Доп.расчеты!118:118) -> 0 | J19: =-SUMIF(Доп.расчеты!$3:$3,Свод!J$4,Доп.расчеты!118:118) -> 0 | ... M19: =-SUMIF(Доп.расчеты!$3:$3,Свод!M$4,Доп.расчеты!118:118) -> 0
B20: Вертикальный транспорт | C20: =-SUMIF(Доп.расчеты!$3:$3,Свод!C$4,Доп.расчеты!119:119) -> 0 | D20: =-SUMIF(Доп.расчеты!$3:$3,Свод!D$4,Доп.расчеты!119:119) -> 0 | E20: =-SUMIF(Доп.расчеты!$3:$3,Свод!E$4,Доп.расчеты!119:119) -> 0 | F20: =-SUMIF(Доп.расчеты!$3:$3,Свод!F$4,Доп.расчеты!119:119) -> 0 | G20: =-SUMIF(Доп.расчеты!$3:$3,Свод!G$4,Доп.расчеты!119:119) -> 0 | H20: =-SUMIF(Доп.расчеты!$3:$3,Свод!H$4,Доп.расчеты!119:119) -> 0 | I20: =-SUMIF(Доп.расчеты!$3:$3,Свод!I$4,Доп.расчеты!119:119) -> 0 | J20: =-SUMIF(Доп.расчеты!$3:$3,Свод!J$4,Доп.расчеты!119:119) -> 0 | ... M20: =-SUMIF(Доп.расчеты!$3:$3,Свод!M$4,Доп.расчеты!119:119) -> 0
B21: Клининговое оборудование | C21: =-SUMIF(Доп.расчеты!$3:$3,Свод!C$4,Доп.расчеты!120:120) -> 0 | D21: =-SUMIF(Доп.расчеты!$3:$3,Свод!D$4,Доп.расчеты!120:120) -> 0 | E21: =-SUMIF(Доп.расчеты!$3:$3,Свод!E$4,Доп.расчеты!120:120) -> 0 | F21: =-SUMIF(Доп.расчеты!$3:$3,Свод!F$4,Доп.расчеты!120:120) -> 0 | G21: =-SUMIF(Доп.расчеты!$3:$3,Свод!G$4,Доп.расчеты!120:120) -> 0 | H21: =-SUMIF(Доп.расчеты!$3:$3,Свод!H$4,Доп.расчеты!120:120) -> 0 | I21: =-SUMIF(Доп.расчеты!$3:$3,Свод!I$4,Доп.расчеты!120:120) -> 0 | J21: =-SUMIF(Доп.расчеты!$3:$3,Свод!J$4,Доп.расчеты!120:120) -> 0 | ... M21: =-SUMIF(Доп.расчеты!$3:$3,Свод!M$4,Доп.расчеты!120:120) -> 0
B22: Офисное оборудование | C22: =-SUMIF(Доп.расчеты!$3:$3,Свод!C$4,Доп.расчеты!121:121) -> 0 | D22: =-SUMIF(Доп.расчеты!$3:$3,Свод!D$4,Доп.расчеты!121:121) -> 0 | E22: =-SUMIF(Доп.расчеты!$3:$3,Свод!E$4,Доп.расчеты!121:121) -> 0 | F22: =-SUMIF(Доп.расчеты!$3:$3,Свод!F$4,Доп.расчеты!121:121) -> 0 | G22: =-SUMIF(Доп.расчеты!$3:$3,Свод!G$4,Доп.расчеты!121:121) -> 0 | H22: =-SUMIF(Доп.расчеты!$3:$3,Свод!H$4,Доп.расчеты!121:121) -> 0 | I22: =-SUMIF(Доп.расчеты!$3:$3,Свод!I$4,Доп.расчеты!121:121) -> 0 | J22: =-SUMIF(Доп.расчеты!$3:$3,Свод!J$4,Доп.расчеты!121:121) -> 0 | ... M22: =-SUMIF(Доп.расчеты!$3:$3,Свод!M$4,Доп.расчеты!121:121) -> 0
B23: Рекламное оборудование | C23: =-SUMIF(Доп.расчеты!$3:$3,Свод!C$4,Доп.расчеты!122:122) -> 0 | D23: =-SUMIF(Доп.расчеты!$3:$3,Свод!D$4,Доп.расчеты!122:122) -> 0 | E23: =-SUMIF(Доп.расчеты!$3:$3,Свод!E$4,Доп.расчеты!122:122) -> 0 | F23: =-SUMIF(Доп.расчеты!$3:$3,Свод!F$4,Доп.расчеты!122:122) -> 0 | G23: =-SUMIF(Доп.расчеты!$3:$3,Свод!G$4,Доп.расчеты!122:122) -> 0 | H23: =-SUMIF(Доп.расчеты!$3:$3,Свод!H$4,Доп.расчеты!122:122) -> 0 | I23: =-SUMIF(Доп.расчеты!$3:$3,Свод!I$4,Доп.расчеты!122:122) -> 0 | J23: =-SUMIF(Доп.расчеты!$3:$3,Свод!J$4,Доп.расчеты!122:122) -> 0 | ... M23: =-SUMIF(Доп.расчеты!$3:$3,Свод!M$4,Доп.расчеты!122:122) -> 0
B24: ИТ оборудование | C24: =-SUMIF(Доп.расчеты!$3:$3,Свод!C$4,Доп.расчеты!123:123) -> 0 | D24: =-SUMIF(Доп.расчеты!$3:$3,Свод!D$4,Доп.расчеты!123:123) -> 0 | E24: =-SUMIF(Доп.расчеты!$3:$3,Свод!E$4,Доп.расчеты!123:123) -> 0 | F24: =-SUMIF(Доп.расчеты!$3:$3,Свод!F$4,Доп.расчеты!123:123) -> 0 | G24: =-SUMIF(Доп.расчеты!$3:$3,Свод!G$4,Доп.расчеты!123:123) -> 0 | H24: =-SUMIF(Доп.расчеты!$3:$3,Свод!H$4,Доп.расчеты!123:123) -> 0 | I24: =-SUMIF(Доп.расчеты!$3:$3,Свод!I$4,Доп.расчеты!123:123) -> 0 | J24: =-SUMIF(Доп.расчеты!$3:$3,Свод!J$4,Доп.расчеты!123:123) -> 0 | ... M24: =-SUMIF(Доп.расчеты!$3:$3,Свод!M$4,Доп.расчеты!123:123) -> 0
B25: СБ оборудование | C25: =-SUMIF(Доп.расчеты!$3:$3,Свод!C$4,Доп.расчеты!124:124) -> 0 | D25: =-SUMIF(Доп.расчеты!$3:$3,Свод!D$4,Доп.расчеты!124:124) -> 0 | E25: =-SUMIF(Доп.расчеты!$3:$3,Свод!E$4,Доп.расчеты!124:124) -> 0 | F25: =-SUMIF(Доп.расчеты!$3:$3,Свод!F$4,Доп.расчеты!124:124) -> 0 | G25: =-SUMIF(Доп.расчеты!$3:$3,Свод!G$4,Доп.расчеты!124:124) -> 0 | H25: =-SUMIF(Доп.расчеты!$3:$3,Свод!H$4,Доп.расчеты!124:124) -> 0 | I25: =-SUMIF(Доп.расчеты!$3:$3,Свод!I$4,Доп.расчеты!124:124) -> 0 | J25: =-SUMIF(Доп.расчеты!$3:$3,Свод!J$4,Доп.расчеты!124:124) -> 0 | ... M25: =-SUMIF(Доп.расчеты!$3:$3,Свод!M$4,Доп.расчеты!124:124) -> 0
B26: Прочее оборудование | C26: =-SUMIF(Доп.расчеты!$3:$3,Свод!C$4,Доп.расчеты!125:125) -> 0 | D26: =-SUMIF(Доп.расчеты!$3:$3,Свод!D$4,Доп.расчеты!125:125) -> 0 | E26: =-SUMIF(Доп.расчеты!$3:$3,Свод!E$4,Доп.расчеты!125:125) -> 0 | F26: =-SUMIF(Доп.расчеты!$3:$3,Свод!F$4,Доп.расчеты!125:125) -> 0 | G26: =-SUMIF(Доп.расчеты!$3:$3,Свод!G$4,Доп.расчеты!125:125) -> 0 | H26: =-SUMIF(Доп.расчеты!$3:$3,Свод!H$4,Доп.расчеты!125:125) -> 0 | I26: =-SUMIF(Доп.расчеты!$3:$3,Свод!I$4,Доп.расчеты!125:125) -> 0 | J26: =-SUMIF(Доп.расчеты!$3:$3,Свод!J$4,Доп.расчеты!125:125) -> 0 | ... M26: =-SUMIF(Доп.расчеты!$3:$3,Свод!M$4,Доп.расчеты!125:125) -> 0
B27: Транспорт | C27: =-SUMIF(Доп.расчеты!$3:$3,Свод!C$4,Доп.расчеты!126:126) -> 0 | D27: =-SUMIF(Доп.расчеты!$3:$3,Свод!D$4,Доп.расчеты!126:126) -> 0 | E27: =-SUMIF(Доп.расчеты!$3:$3,Свод!E$4,Доп.расчеты!126:126) -> 0 | F27: =-SUMIF(Доп.расчеты!$3:$3,Свод!F$4,Доп.расчеты!126:126) -> 0 | G27: =-SUMIF(Доп.расчеты!$3:$3,Свод!G$4,Доп.расчеты!126:126) -> 0 | H27: =-SUMIF(Доп.расчеты!$3:$3,Свод!H$4,Доп.расчеты!126:126) -> 0 | I27: =-SUMIF(Доп.расчеты!$3:$3,Свод!I$4,Доп.расчеты!126:126) -> 0 | J27: =-SUMIF(Доп.расчеты!$3:$3,Свод!J$4,Доп.расчеты!126:126) -> 0 | ... M27: =-SUMIF(Доп.расчеты!$3:$3,Свод!M$4,Доп.расчеты!126:126) -> 0
B28: Нематериальные активы | C28: =-SUMIF(Доп.расчеты!$3:$3,Свод!C$4,Доп.расчеты!127:127) -> 0 | D28: =-SUMIF(Доп.расчеты!$3:$3,Свод!D$4,Доп.расчеты!127:127) -> 0 | E28: =-SUMIF(Доп.расчеты!$3:$3,Свод!E$4,Доп.расчеты!127:127) -> 0 | F28: =-SUMIF(Доп.расчеты!$3:$3,Свод!F$4,Доп.расчеты!127:127) -> 0 | G28: =-SUMIF(Доп.расчеты!$3:$3,Свод!G$4,Доп.расчеты!127:127) -> 0 | H28: =-SUMIF(Доп.расчеты!$3:$3,Свод!H$4,Доп.расчеты!127:127) -> 0 | I28: =-SUMIF(Доп.расчеты!$3:$3,Свод!I$4,Доп.расчеты!127:127) -> 0 | J28: =-SUMIF(Доп.расчеты!$3:$3,Свод!J$4,Доп.расчеты!127:127) -> 0 | ... M28: =-SUMIF(Доп.расчеты!$3:$3,Свод!M$4,Доп.расчеты!127:127) -> 0
B29: Приобретение долей в бизнесе | C29: =-SUMIF(Доп.расчеты!$3:$3,Свод!C$4,Доп.расчеты!128:128) -> 0 | D29: =-SUMIF(Доп.расчеты!$3:$3,Свод!D$4,Доп.расчеты!128:128) -> 0 | E29: =-SUMIF(Доп.расчеты!$3:$3,Свод!E$4,Доп.расчеты!128:128) -> 0 | F29: =-SUMIF(Доп.расчеты!$3:$3,Свод!F$4,Доп.расчеты!128:128) -> 0 | G29: =-SUMIF(Доп.расчеты!$3:$3,Свод!G$4,Доп.расчеты!128:128) -> 0 | H29: =-SUMIF(Доп.расчеты!$3:$3,Свод!H$4,Доп.расчеты!128:128) -> 0 | I29: =-SUMIF(Доп.расчеты!$3:$3,Свод!I$4,Доп.расчеты!128:128) -> 0 | J29: =-SUMIF(Доп.расчеты!$3:$3,Свод!J$4,Доп.расчеты!128:128) -> 0 | ... M29: =-SUMIF(Доп.расчеты!$3:$3,Свод!M$4,Доп.расчеты!128:128) -> 0
B30: Капитализируемый ФОТ | C30: =-SUMIF(Доп.расчеты!$3:$3,Свод!C$4,Доп.расчеты!129:129) -> 0 | D30: =-SUMIF(Доп.расчеты!$3:$3,Свод!D$4,Доп.расчеты!129:129) -> 0 | E30: =-SUMIF(Доп.расчеты!$3:$3,Свод!E$4,Доп.расчеты!129:129) -> 0 | F30: =-SUMIF(Доп.расчеты!$3:$3,Свод!F$4,Доп.расчеты!129:129) -> 0 | G30: =-SUMIF(Доп.расчеты!$3:$3,Свод!G$4,Доп.расчеты!129:129) -> 0 | H30: =-SUMIF(Доп.расчеты!$3:$3,Свод!H$4,Доп.расчеты!129:129) -> 0 | I30: =-SUMIF(Доп.расчеты!$3:$3,Свод!I$4,Доп.расчеты!129:129) -> 0 | J30: =-SUMIF(Доп.расчеты!$3:$3,Свод!J$4,Доп.расчеты!129:129) -> 0 | ... M30: =-SUMIF(Доп.расчеты!$3:$3,Свод!M$4,Доп.расчеты!129:129) -> 0
B31: Консультационные услуги IT | C31: =-SUMIF(Доп.расчеты!$3:$3,Свод!C$4,Доп.расчеты!130:130) -> 0 | D31: =-SUMIF(Доп.расчеты!$3:$3,Свод!D$4,Доп.расчеты!130:130) -> 0 | E31: =-SUMIF(Доп.расчеты!$3:$3,Свод!E$4,Доп.расчеты!130:130) -> 0 | F31: =-SUMIF(Доп.расчеты!$3:$3,Свод!F$4,Доп.расчеты!130:130) -> 0 | G31: =-SUMIF(Доп.расчеты!$3:$3,Свод!G$4,Доп.расчеты!130:130) -> 0 | H31: =-SUMIF(Доп.расчеты!$3:$3,Свод!H$4,Доп.расчеты!130:130) -> 0 | I31: =-SUMIF(Доп.расчеты!$3:$3,Свод!I$4,Доп.расчеты!130:130) -> 0 | J31: =-SUMIF(Доп.расчеты!$3:$3,Свод!J$4,Доп.расчеты!130:130) -> 0 | ... M31: =-SUMIF(Доп.расчеты!$3:$3,Свод!M$4,Доп.расчеты!130:130) -> 0
B32: Тепловые завесы | C32: =-SUMIF(Доп.расчеты!$3:$3,Свод!C$4,Доп.расчеты!131:131) -> 0 | D32: =-SUMIF(Доп.расчеты!$3:$3,Свод!D$4,Доп.расчеты!131:131) -> 0 | E32: =-SUMIF(Доп.расчеты!$3:$3,Свод!E$4,Доп.расчеты!131:131) -> 0 | F32: =-SUMIF(Доп.расчеты!$3:$3,Свод!F$4,Доп.расчеты!131:131) -> 0 | G32: =-SUMIF(Доп.расчеты!$3:$3,Свод!G$4,Доп.расчеты!131:131) -> 0 | H32: =-SUMIF(Доп.расчеты!$3:$3,Свод!H$4,Доп.расчеты!131:131) -> 0 | I32: =-SUMIF(Доп.расчеты!$3:$3,Свод!I$4,Доп.расчеты!131:131) -> 0 | J32: =-SUMIF(Доп.расчеты!$3:$3,Свод!J$4,Доп.расчеты!131:131) -> 0 | ... M32: =-SUMIF(Доп.расчеты!$3:$3,Свод!M$4,Доп.расчеты!131:131) -> 0
B33: Кондиционеры и сплит-системы | C33: =-SUMIF(Доп.расчеты!$3:$3,Свод!C$4,Доп.расчеты!132:132) -> 0 | D33: =-SUMIF(Доп.расчеты!$3:$3,Свод!D$4,Доп.расчеты!132:132) -> 0 | E33: =-SUMIF(Доп.расчеты!$3:$3,Свод!E$4,Доп.расчеты!132:132) -> 0 | F33: =-SUMIF(Доп.расчеты!$3:$3,Свод!F$4,Доп.расчеты!132:132) -> 0 | G33: =-SUMIF(Доп.расчеты!$3:$3,Свод!G$4,Доп.расчеты!132:132) -> 0 | H33: =-SUMIF(Доп.расчеты!$3:$3,Свод!H$4,Доп.расчеты!132:132) -> 0 | I33: =-SUMIF(Доп.расчеты!$3:$3,Свод!I$4,Доп.расчеты!132:132) -> 0 | J33: =-SUMIF(Доп.расчеты!$3:$3,Свод!J$4,Доп.расчеты!132:132) -> 0 | ... M33: =-SUMIF(Доп.расчеты!$3:$3,Свод!M$4,Доп.расчеты!132:132) -> 0
B34: Автоматические двери и ворота | C34: =-SUMIF(Доп.расчеты!$3:$3,Свод!C$4,Доп.расчеты!133:133) -> 0 | D34: =-SUMIF(Доп.расчеты!$3:$3,Свод!D$4,Доп.расчеты!133:133) -> 0 | E34: =-SUMIF(Доп.расчеты!$3:$3,Свод!E$4,Доп.расчеты!133:133) -> 0 | F34: =-SUMIF(Доп.расчеты!$3:$3,Свод!F$4,Доп.расчеты!133:133) -> 0 | G34: =-SUMIF(Доп.расчеты!$3:$3,Свод!G$4,Доп.расчеты!133:133) -> 0 | H34: =-SUMIF(Доп.расчеты!$3:$3,Свод!H$4,Доп.расчеты!133:133) -> 0 | I34: =-SUMIF(Доп.расчеты!$3:$3,Свод!I$4,Доп.расчеты!133:133) -> 0 | J34: =-SUMIF(Доп.расчеты!$3:$3,Свод!J$4,Доп.расчеты!133:133) -> 0 | ... M34: =-SUMIF(Доп.расчеты!$3:$3,Свод!M$4,Доп.расчеты!133:133) -> 0
B35: Основная деятельность | C35: =SUM(C36:C48) -> 0 | D35: =SUM(D36:D48) -> 0 | E35: =SUM(E36:E48) -> 0 | F35: =SUM(F36:F48) -> 0 | G35: =SUM(G36:G48) -> 0 | H35: =SUM(H36:H48) -> 0 | I35: =SUM(I36:I48) -> 0 | J35: =SUM(J36:J48) -> 0 | ... M35: =SUM(M36:M48) -> 0
B36: Расходы на персонал | C36: =-SUMIF(Доп.расчеты!$3:$3,Свод!C$4,Доп.расчеты!135:135) -> 0 | D36: =-SUMIF(Доп.расчеты!$3:$3,Свод!D$4,Доп.расчеты!135:135) -> 0 | E36: =-SUMIF(Доп.расчеты!$3:$3,Свод!E$4,Доп.расчеты!135:135) -> 0 | F36: =-SUMIF(Доп.расчеты!$3:$3,Свод!F$4,Доп.расчеты!135:135) -> 0 | G36: =-SUMIF(Доп.расчеты!$3:$3,Свод!G$4,Доп.расчеты!135:135) -> 0 | H36: =-SUMIF(Доп.расчеты!$3:$3,Свод!H$4,Доп.расчеты!135:135) -> 0 | I36: =-SUMIF(Доп.расчеты!$3:$3,Свод!I$4,Доп.расчеты!135:135) -> 0 | J36: =-SUMIF(Доп.расчеты!$3:$3,Свод!J$4,Доп.расчеты!135:135) -> 0 | ... M36: =-SUMIF(Доп.расчеты!$3:$3,Свод!M$4,Доп.расчеты!135:135) -> 0
B37: Ремонт и обслуживание | C37: =-SUMIF(Доп.расчеты!$3:$3,Свод!C$4,Доп.расчеты!136:136) -> 0 | D37: =-SUMIF(Доп.расчеты!$3:$3,Свод!D$4,Доп.расчеты!136:136) -> 0 | E37: =-SUMIF(Доп.расчеты!$3:$3,Свод!E$4,Доп.расчеты!136:136) -> 0 | F37: =-SUMIF(Доп.расчеты!$3:$3,Свод!F$4,Доп.расчеты!136:136) -> 0 | G37: =-SUMIF(Доп.расчеты!$3:$3,Свод!G$4,Доп.расчеты!136:136) -> 0 | H37: =-SUMIF(Доп.расчеты!$3:$3,Свод!H$4,Доп.расчеты!136:136) -> 0 | I37: =-SUMIF(Доп.расчеты!$3:$3,Свод!I$4,Доп.расчеты!136:136) -> 0 | J37: =-SUMIF(Доп.расчеты!$3:$3,Свод!J$4,Доп.расчеты!136:136) -> 0 | ... M37: =-SUMIF(Доп.расчеты!$3:$3,Свод!M$4,Доп.расчеты!136:136) -> 0
B38: Коммунальные расходы и связь | C38: =-SUMIF(Доп.расчеты!$3:$3,Свод!C$4,Доп.расчеты!137:137) -> 0 | D38: =-SUMIF(Доп.расчеты!$3:$3,Свод!D$4,Доп.расчеты!137:137) -> 0 | E38: =-SUMIF(Доп.расчеты!$3:$3,Свод!E$4,Доп.расчеты!137:137) -> 0 | F38: =-SUMIF(Доп.расчеты!$3:$3,Свод!F$4,Доп.расчеты!137:137) -> 0 | G38: =-SUMIF(Доп.расчеты!$3:$3,Свод!G$4,Доп.расчеты!137:137) -> 0 | H38: =-SUMIF(Доп.расчеты!$3:$3,Свод!H$4,Доп.расчеты!137:137) -> 0 | I38: =-SUMIF(Доп.расчеты!$3:$3,Свод!I$4,Доп.расчеты!137:137) -> 0 | J38: =-SUMIF(Доп.расчеты!$3:$3,Свод!J$4,Доп.расчеты!137:137) -> 0 | ... M38: =-SUMIF(Доп.расчеты!$3:$3,Свод!M$4,Доп.расчеты!137:137) -> 0
B39: Расходы на охрану | C39: =-SUMIF(Доп.расчеты!$3:$3,Свод!C$4,Доп.расчеты!138:138) -> 0 | D39: =-SUMIF(Доп.расчеты!$3:$3,Свод!D$4,Доп.расчеты!138:138) -> 0 | E39: =-SUMIF(Доп.расчеты!$3:$3,Свод!E$4,Доп.расчеты!138:138) -> 0 | F39: =-SUMIF(Доп.расчеты!$3:$3,Свод!F$4,Доп.расчеты!138:138) -> 0 | G39: =-SUMIF(Доп.расчеты!$3:$3,Свод!G$4,Доп.расчеты!138:138) -> 0 | H39: =-SUMIF(Доп.расчеты!$3:$3,Свод!H$4,Доп.расчеты!138:138) -> 0 | I39: =-SUMIF(Доп.расчеты!$3:$3,Свод!I$4,Доп.расчеты!138:138) -> 0 | J39: =-SUMIF(Доп.расчеты!$3:$3,Свод!J$4,Доп.расчеты!138:138) -> 0 | ... M39: =-SUMIF(Доп.расчеты!$3:$3,Свод!M$4,Доп.расчеты!138:138) -> 0
B40: Расх материалы и хоз расходы | C40: =-SUMIF(Доп.расчеты!$3:$3,Свод!C$4,Доп.расчеты!139:139) -> 0 | D40: =-SUMIF(Доп.расчеты!$3:$3,Свод!D$4,Доп.расчеты!139:139) -> 0 | E40: =-SUMIF(Доп.расчеты!$3:$3,Свод!E$4,Доп.расчеты!139:139) -> 0 | F40: =-SUMIF(Доп.расчеты!$3:$3,Свод!F$4,Доп.расчеты!139:139) -> 0 | G40: =-SUMIF(Доп.расчеты!$3:$3,Свод!G$4,Доп.расчеты!139:139) -> 0 | H40: =-SUMIF(Доп.расчеты!$3:$3,Свод!H$4,Доп.расчеты!139:139) -> 0 | I40: =-SUMIF(Доп.расчеты!$3:$3,Свод!I$4,Доп.расчеты!139:139) -> 0 | J40: =-SUMIF(Доп.расчеты!$3:$3,Свод!J$4,Доп.расчеты!139:139) -> 0 | ... M40: =-SUMIF(Доп.расчеты!$3:$3,Свод!M$4,Доп.расчеты!139:139) -> 0
B41: Консультационные, информационные услуги и страхование | C41: =-SUMIF(Доп.расчеты!$3:$3,Свод!C$4,Доп.расчеты!140:140) -> 0 | D41: =-SUMIF(Доп.расчеты!$3:$3,Свод!D$4,Доп.расчеты!140:140) -> 0 | E41: =-SUMIF(Доп.расчеты!$3:$3,Свод!E$4,Доп.расчеты!140:140) -> 0 | F41: =-SUMIF(Доп.расчеты!$3:$3,Свод!F$4,Доп.расчеты!140:140) -> 0 | G41: =-SUMIF(Доп.расчеты!$3:$3,Свод!G$4,Доп.расчеты!140:140) -> 0 | H41: =-SUMIF(Доп.расчеты!$3:$3,Свод!H$4,Доп.расчеты!140:140) -> 0 | I41: =-SUMIF(Доп.расчеты!$3:$3,Свод!I$4,Доп.расчеты!140:140) -> 0 | J41: =-SUMIF(Доп.расчеты!$3:$3,Свод!J$4,Доп.расчеты!140:140) -> 0 | ... M41: =-SUMIF(Доп.расчеты!$3:$3,Свод!M$4,Доп.расчеты!140:140) -> 0
B42: Расходы на аренду | C42: =-SUMIF(Доп.расчеты!$3:$3,Свод!C$4,Доп.расчеты!141:141) -> 0 | D42: =-SUMIF(Доп.расчеты!$3:$3,Свод!D$4,Доп.расчеты!141:141) -> 0 | E42: =-SUMIF(Доп.расчеты!$3:$3,Свод!E$4,Доп.расчеты!141:141) -> 0 | F42: =-SUMIF(Доп.расчеты!$3:$3,Свод!F$4,Доп.расчеты!141:141) -> 0 | G42: =-SUMIF(Доп.расчеты!$3:$3,Свод!G$4,Доп.расчеты!141:141) -> 0 | H42: =-SUMIF(Доп.расчеты!$3:$3,Свод!H$4,Доп.расчеты!141:141) -> 0 | I42: =-SUMIF(Доп.расчеты!$3:$3,Свод!I$4,Доп.расчеты!141:141) -> 0 | J42: =-SUMIF(Доп.расчеты!$3:$3,Свод!J$4,Доп.расчеты!141:141) -> 0 | ... M42: =-SUMIF(Доп.расчеты!$3:$3,Свод!M$4,Доп.расчеты!141:141) -> 0
B43: Реклама, маркетинг и pr | C43: =-SUMIF(Доп.расчеты!$3:$3,Свод!C$4,Доп.расчеты!142:142) -> 0 | D43: =-SUMIF(Доп.расчеты!$3:$3,Свод!D$4,Доп.расчеты!142:142) -> 0 | E43: =-SUMIF(Доп.расчеты!$3:$3,Свод!E$4,Доп.расчеты!142:142) -> 0 | F43: =-SUMIF(Доп.расчеты!$3:$3,Свод!F$4,Доп.расчеты!142:142) -> 0 | G43: =-SUMIF(Доп.расчеты!$3:$3,Свод!G$4,Доп.расчеты!142:142) -> 0 | H43: =-SUMIF(Доп.расчеты!$3:$3,Свод!H$4,Доп.расчеты!142:142) -> 0 | I43: =-SUMIF(Доп.расчеты!$3:$3,Свод!I$4,Доп.расчеты!142:142) -> 0 | J43: =-SUMIF(Доп.расчеты!$3:$3,Свод!J$4,Доп.расчеты!142:142) -> 0 | ... M43: =-SUMIF(Доп.расчеты!$3:$3,Свод!M$4,Доп.расчеты!142:142) -> 0
B44: Транспортные расходы | C44: =-SUMIF(Доп.расчеты!$3:$3,Свод!C$4,Доп.расчеты!143:143) -> 0 | D44: =-SUMIF(Доп.расчеты!$3:$3,Свод!D$4,Доп.расчеты!143:143) -> 0 | E44: =-SUMIF(Доп.расчеты!$3:$3,Свод!E$4,Доп.расчеты!143:143) -> 0 | F44: =-SUMIF(Доп.расчеты!$3:$3,Свод!F$4,Доп.расчеты!143:143) -> 0 | G44: =-SUMIF(Доп.расчеты!$3:$3,Свод!G$4,Доп.расчеты!143:143) -> 0 | H44: =-SUMIF(Доп.расчеты!$3:$3,Свод!H$4,Доп.расчеты!143:143) -> 0 | I44: =-SUMIF(Доп.расчеты!$3:$3,Свод!I$4,Доп.расчеты!143:143) -> 0 | J44: =-SUMIF(Доп.расчеты!$3:$3,Свод!J$4,Доп.расчеты!143:143) -> 0 | ... M44: =-SUMIF(Доп.расчеты!$3:$3,Свод!M$4,Доп.расчеты!143:143) -> 0
B45: Услуги сторонних логистических операторов | C45: =-SUMIF(Доп.расчеты!$3:$3,Свод!C$4,Доп.расчеты!144:144) -> 0 | D45: =-SUMIF(Доп.расчеты!$3:$3,Свод!D$4,Доп.расчеты!144:144) -> 0 | E45: =-SUMIF(Доп.расчеты!$3:$3,Свод!E$4,Доп.расчеты!144:144) -> 0 | F45: =-SUMIF(Доп.расчеты!$3:$3,Свод!F$4,Доп.расчеты!144:144) -> 0 | G45: =-SUMIF(Доп.расчеты!$3:$3,Свод!G$4,Доп.расчеты!144:144) -> 0 | H45: =-SUMIF(Доп.расчеты!$3:$3,Свод!H$4,Доп.расчеты!144:144) -> 0 | I45: =-SUMIF(Доп.расчеты!$3:$3,Свод!I$4,Доп.расчеты!144:144) -> 0 | J45: =-SUMIF(Доп.расчеты!$3:$3,Свод!J$4,Доп.расчеты!144:144) -> 0 | ... M45: =-SUMIF(Доп.расчеты!$3:$3,Свод!M$4,Доп.расчеты!144:144) -> 0
B46: Налоги | C46: =-SUMIF(Доп.расчеты!$3:$3,Свод!C$4,Доп.расчеты!145:145) -> 0 | D46: =-SUMIF(Доп.расчеты!$3:$3,Свод!D$4,Доп.расчеты!145:145) -> 0 | E46: =-SUMIF(Доп.расчеты!$3:$3,Свод!E$4,Доп.расчеты!145:145) -> 0 | F46: =-SUMIF(Доп.расчеты!$3:$3,Свод!F$4,Доп.расчеты!145:145) -> 0 | G46: =-SUMIF(Доп.расчеты!$3:$3,Свод!G$4,Доп.расчеты!145:145) -> 0 | H46: =-SUMIF(Доп.расчеты!$3:$3,Свод!H$4,Доп.расчеты!145:145) -> 0 | I46: =-SUMIF(Доп.расчеты!$3:$3,Свод!I$4,Доп.расчеты!145:145) -> 0 | J46: =-SUMIF(Доп.расчеты!$3:$3,Свод!J$4,Доп.расчеты!145:145) -> 0 | ... M46: =-SUMIF(Доп.расчеты!$3:$3,Свод!M$4,Доп.расчеты!145:145) -> 0
B47: Прочие расходы | C47: =-SUMIF(Доп.расчеты!$3:$3,Свод!C$4,Доп.расчеты!146:146) -> 0 | D47: =-SUMIF(Доп.расчеты!$3:$3,Свод!D$4,Доп.расчеты!146:146) -> 0 | E47: =-SUMIF(Доп.расчеты!$3:$3,Свод!E$4,Доп.расчеты!146:146) -> 0 | F47: =-SUMIF(Доп.расчеты!$3:$3,Свод!F$4,Доп.расчеты!146:146) -> 0 | G47: =-SUMIF(Доп.расчеты!$3:$3,Свод!G$4,Доп.расчеты!146:146) -> 0 | H47: =-SUMIF(Доп.расчеты!$3:$3,Свод!H$4,Доп.расчеты!146:146) -> 0 | I47: =-SUMIF(Доп.расчеты!$3:$3,Свод!I$4,Доп.расчеты!146:146) -> 0 | J47: =-SUMIF(Доп.расчеты!$3:$3,Свод!J$4,Доп.расчеты!146:146) -> 0 | ... M47: =-SUMIF(Доп.расчеты!$3:$3,Свод!M$4,Доп.расчеты!146:146) -> 0
B48: Командировочные расходы | C48: =-SUMIF(Доп.расчеты!$3:$3,Свод!C$4,Доп.расчеты!147:147) -> 0 | D48: =-SUMIF(Доп.расчеты!$3:$3,Свод!D$4,Доп.расчеты!147:147) -> 0 | E48: =-SUMIF(Доп.расчеты!$3:$3,Свод!E$4,Доп.расчеты!147:147) -> 0 | F48: =-SUMIF(Доп.расчеты!$3:$3,Свод!F$4,Доп.расчеты!147:147) -> 0 | G48: =-SUMIF(Доп.расчеты!$3:$3,Свод!G$4,Доп.расчеты!147:147) -> 0 | H48: =-SUMIF(Доп.расчеты!$3:$3,Свод!H$4,Доп.расчеты!147:147) -> 0 | I48: =-SUMIF(Доп.расчеты!$3:$3,Свод!I$4,Доп.расчеты!147:147) -> 0 | J48: =-SUMIF(Доп.расчеты!$3:$3,Свод!J$4,Доп.расчеты!147:147) -> 0 | ... M48: =-SUMIF(Доп.расчеты!$3:$3,Свод!M$4,Доп.расчеты!147:147) -> 0
B49: Постпроектные расходы
B50: Инвестиционная деятельность | C50: =SUMIF('Как есть'!$12:$12,Свод!C4,'Как есть'!$44:$44) -> 0 | D50: =SUMIF('Как есть'!$12:$12,Свод!D4,'Как есть'!$44:$44) -> 0 | E50: =SUMIF('Как есть'!$12:$12,Свод!E4,'Как есть'!$44:$44) -> 0 | F50: =SUMIF('Как есть'!$12:$12,Свод!F4,'Как есть'!$44:$44) -> 0 | G50: =SUMIF('Как есть'!$12:$12,Свод!G4,'Как есть'!$44:$44) -> 0 | H50: =SUMIF('Как есть'!$12:$12,Свод!H4,'Как есть'!$44:$44) -> 0 | I50: =SUMIF('Как есть'!$12:$12,Свод!I4,'Как есть'!$44:$44) -> 0 | J50: =SUMIF('Как есть'!$12:$12,Свод!J4,'Как есть'!$44:$44) -> 0 | ... M50: =SUMIF('Как есть'!$12:$12,Свод!M4,'Как есть'!$44:$44) -> 0
B51: Земельные участки | C51: =-SUMIF(Доп.расчеты!$3:$3,Свод!C$4,Доп.расчеты!152:152) -> 0 | D51: =-SUMIF(Доп.расчеты!$3:$3,Свод!D$4,Доп.расчеты!152:152) -> 0 | E51: =-SUMIF(Доп.расчеты!$3:$3,Свод!E$4,Доп.расчеты!152:152) -> 0 | F51: =-SUMIF(Доп.расчеты!$3:$3,Свод!F$4,Доп.расчеты!152:152) -> 0 | G51: =-SUMIF(Доп.расчеты!$3:$3,Свод!G$4,Доп.расчеты!152:152) -> 0 | H51: =-SUMIF(Доп.расчеты!$3:$3,Свод!H$4,Доп.расчеты!152:152) -> 0 | I51: =-SUMIF(Доп.расчеты!$3:$3,Свод!I$4,Доп.расчеты!152:152) -> 0 | J51: =-SUMIF(Доп.расчеты!$3:$3,Свод!J$4,Доп.расчеты!152:152) -> 0 | ... M51: =-SUMIF(Доп.расчеты!$3:$3,Свод!M$4,Доп.расчеты!152:152) -> 0
B52: Здания и сооружения | C52: =-SUMIF(Доп.расчеты!$3:$3,Свод!C$4,Доп.расчеты!153:153) -> 0 | D52: =-SUMIF(Доп.расчеты!$3:$3,Свод!D$4,Доп.расчеты!153:153) -> 0 | E52: =-SUMIF(Доп.расчеты!$3:$3,Свод!E$4,Доп.расчеты!153:153) -> 0 | F52: =-SUMIF(Доп.расчеты!$3:$3,Свод!F$4,Доп.расчеты!153:153) -> 0 | G52: =-SUMIF(Доп.расчеты!$3:$3,Свод!G$4,Доп.расчеты!153:153) -> 0 | H52: =-SUMIF(Доп.расчеты!$3:$3,Свод!H$4,Доп.расчеты!153:153) -> 0 | I52: =-SUMIF(Доп.расчеты!$3:$3,Свод!I$4,Доп.расчеты!153:153) -> 0 | J52: =-SUMIF(Доп.расчеты!$3:$3,Свод!J$4,Доп.расчеты!153:153) -> 0 | ... M52: =-SUMIF(Доп.расчеты!$3:$3,Свод!M$4,Доп.расчеты!153:153) -> 0
B53: Помещения в составе зданий и сооружений | C53: =-SUMIF(Доп.расчеты!$3:$3,Свод!C$4,Доп.расчеты!154:154) -> 0 | D53: =-SUMIF(Доп.расчеты!$3:$3,Свод!D$4,Доп.расчеты!154:154) -> 0 | E53: =-SUMIF(Доп.расчеты!$3:$3,Свод!E$4,Доп.расчеты!154:154) -> 0 | F53: =-SUMIF(Доп.расчеты!$3:$3,Свод!F$4,Доп.расчеты!154:154) -> 0 | G53: =-SUMIF(Доп.расчеты!$3:$3,Свод!G$4,Доп.расчеты!154:154) -> 0 | H53: =-SUMIF(Доп.расчеты!$3:$3,Свод!H$4,Доп.расчеты!154:154) -> 0 | I53: =-SUMIF(Доп.расчеты!$3:$3,Свод!I$4,Доп.расчеты!154:154) -> 0 | J53: =-SUMIF(Доп.расчеты!$3:$3,Свод!J$4,Доп.расчеты!154:154) -> 0 | ... M53: =-SUMIF(Доп.расчеты!$3:$3,Свод!M$4,Доп.расчеты!154:154) -> 0
B54: Строительство и ремонты | C54: =-SUMIF(Доп.расчеты!$3:$3,Свод!C$4,Доп.расчеты!155:155) -> 0 | D54: =-SUMIF(Доп.расчеты!$3:$3,Свод!D$4,Доп.расчеты!155:155) -> 0 | E54: =-SUMIF(Доп.расчеты!$3:$3,Свод!E$4,Доп.расчеты!155:155) -> 0 | F54: =-SUMIF(Доп.расчеты!$3:$3,Свод!F$4,Доп.расчеты!155:155) -> 0 | G54: =-SUMIF(Доп.расчеты!$3:$3,Свод!G$4,Доп.расчеты!155:155) -> 0 | H54: =-SUMIF(Доп.расчеты!$3:$3,Свод!H$4,Доп.расчеты!155:155) -> 0 | I54: =-SUMIF(Доп.расчеты!$3:$3,Свод!I$4,Доп.расчеты!155:155) -> 0 | J54: =-SUMIF(Доп.расчеты!$3:$3,Свод!J$4,Доп.расчеты!155:155) -> 0 | ... M54: =-SUMIF(Доп.расчеты!$3:$3,Свод!M$4,Доп.расчеты!155:155) -> 0
B55: Холодильное оборудование | C55: =-SUMIF(Доп.расчеты!$3:$3,Свод!C$4,Доп.расчеты!156:156) -> 0 | D55: =-SUMIF(Доп.расчеты!$3:$3,Свод!D$4,Доп.расчеты!156:156) -> 0 | E55: =-SUMIF(Доп.расчеты!$3:$3,Свод!E$4,Доп.расчеты!156:156) -> 0 | F55: =-SUMIF(Доп.расчеты!$3:$3,Свод!F$4,Доп.расчеты!156:156) -> 0 | G55: =-SUMIF(Доп.расчеты!$3:$3,Свод!G$4,Доп.расчеты!156:156) -> 0 | H55: =-SUMIF(Доп.расчеты!$3:$3,Свод!H$4,Доп.расчеты!156:156) -> 0 | I55: =-SUMIF(Доп.расчеты!$3:$3,Свод!I$4,Доп.расчеты!156:156) -> 0 | J55: =-SUMIF(Доп.расчеты!$3:$3,Свод!J$4,Доп.расчеты!156:156) -> 0 | ... M55: =-SUMIF(Доп.расчеты!$3:$3,Свод!M$4,Доп.расчеты!156:156) -> 0
B56: Стеллажное оборудование | C56: =-SUMIF(Доп.расчеты!$3:$3,Свод!C$4,Доп.расчеты!157:157) -> 0 | D56: =-SUMIF(Доп.расчеты!$3:$3,Свод!D$4,Доп.расчеты!157:157) -> 0 | E56: =-SUMIF(Доп.расчеты!$3:$3,Свод!E$4,Доп.расчеты!157:157) -> 0 | F56: =-SUMIF(Доп.расчеты!$3:$3,Свод!F$4,Доп.расчеты!157:157) -> 0 | G56: =-SUMIF(Доп.расчеты!$3:$3,Свод!G$4,Доп.расчеты!157:157) -> 0 | H56: =-SUMIF(Доп.расчеты!$3:$3,Свод!H$4,Доп.расчеты!157:157) -> 0 | I56: =-SUMIF(Доп.расчеты!$3:$3,Свод!I$4,Доп.расчеты!157:157) -> 0 | J56: =-SUMIF(Доп.расчеты!$3:$3,Свод!J$4,Доп.расчеты!157:157) -> 0 | ... M56: =-SUMIF(Доп.расчеты!$3:$3,Свод!M$4,Доп.расчеты!157:157) -> 0
B57: Производственное оборудование | C57: =-SUMIF(Доп.расчеты!$3:$3,Свод!C$4,Доп.расчеты!158:158) -> 0 | D57: =-SUMIF(Доп.расчеты!$3:$3,Свод!D$4,Доп.расчеты!158:158) -> 0 | E57: =-SUMIF(Доп.расчеты!$3:$3,Свод!E$4,Доп.расчеты!158:158) -> 0 | F57: =-SUMIF(Доп.расчеты!$3:$3,Свод!F$4,Доп.расчеты!158:158) -> 0 | G57: =-SUMIF(Доп.расчеты!$3:$3,Свод!G$4,Доп.расчеты!158:158) -> 0 | H57: =-SUMIF(Доп.расчеты!$3:$3,Свод!H$4,Доп.расчеты!158:158) -> 0 | I57: =-SUMIF(Доп.расчеты!$3:$3,Свод!I$4,Доп.расчеты!158:158) -> 0 | J57: =-SUMIF(Доп.расчеты!$3:$3,Свод!J$4,Доп.расчеты!158:158) -> 0 | ... M57: =-SUMIF(Доп.расчеты!$3:$3,Свод!M$4,Доп.расчеты!158:158) -> 0
B58: Торговое оборудование | C58: =-SUMIF(Доп.расчеты!$3:$3,Свод!C$4,Доп.расчеты!159:159) -> 0 | D58: =-SUMIF(Доп.расчеты!$3:$3,Свод!D$4,Доп.расчеты!159:159) -> 0 | E58: =-SUMIF(Доп.расчеты!$3:$3,Свод!E$4,Доп.расчеты!159:159) -> 0 | F58: =-SUMIF(Доп.расчеты!$3:$3,Свод!F$4,Доп.расчеты!159:159) -> 0 | G58: =-SUMIF(Доп.расчеты!$3:$3,Свод!G$4,Доп.расчеты!159:159) -> 0 | H58: =-SUMIF(Доп.расчеты!$3:$3,Свод!H$4,Доп.расчеты!159:159) -> 0 | I58: =-SUMIF(Доп.расчеты!$3:$3,Свод!I$4,Доп.расчеты!159:159) -> 0 | J58: =-SUMIF(Доп.расчеты!$3:$3,Свод!J$4,Доп.расчеты!159:159) -> 0 | ... M58: =-SUMIF(Доп.расчеты!$3:$3,Свод!M$4,Доп.расчеты!159:159) -> 0
B59: Складское оборудование | C59: =-SUMIF(Доп.расчеты!$3:$3,Свод!C$4,Доп.расчеты!160:160) -> 0 | D59: =-SUMIF(Доп.расчеты!$3:$3,Свод!D$4,Доп.расчеты!160:160) -> 0 | E59: =-SUMIF(Доп.расчеты!$3:$3,Свод!E$4,Доп.расчеты!160:160) -> 0 | F59: =-SUMIF(Доп.расчеты!$3:$3,Свод!F$4,Доп.расчеты!160:160) -> 0 | G59: =-SUMIF(Доп.расчеты!$3:$3,Свод!G$4,Доп.расчеты!160:160) -> 0 | H59: =-SUMIF(Доп.расчеты!$3:$3,Свод!H$4,Доп.расчеты!160:160) -> 0 | I59: =-SUMIF(Доп.расчеты!$3:$3,Свод!I$4,Доп.расчеты!160:160) -> 0 | J59: =-SUMIF(Доп.расчеты!$3:$3,Свод!J$4,Доп.расчеты!160:160) -> 0 | ... M59: =-SUMIF(Доп.расчеты!$3:$3,Свод!M$4,Доп.расчеты!160:160) -> 0
B60: Вертикальный транспорт | C60: =-SUMIF(Доп.расчеты!$3:$3,Свод!C$4,Доп.расчеты!161:161) -> 0 | D60: =-SUMIF(Доп.расчеты!$3:$3,Свод!D$4,Доп.расчеты!161:161) -> 0 | E60: =-SUMIF(Доп.расчеты!$3:$3,Свод!E$4,Доп.расчеты!161:161) -> 0 | F60: =-SUMIF(Доп.расчеты!$3:$3,Свод!F$4,Доп.расчеты!161:161) -> 0 | G60: =-SUMIF(Доп.расчеты!$3:$3,Свод!G$4,Доп.расчеты!161:161) -> 0 | H60: =-SUMIF(Доп.расчеты!$3:$3,Свод!H$4,Доп.расчеты!161:161) -> 0 | I60: =-SUMIF(Доп.расчеты!$3:$3,Свод!I$4,Доп.расчеты!161:161) -> 0 | J60: =-SUMIF(Доп.расчеты!$3:$3,Свод!J$4,Доп.расчеты!161:161) -> 0 | ... M60: =-SUMIF(Доп.расчеты!$3:$3,Свод!M$4,Доп.расчеты!161:161) -> 0
B61: Клининговое оборудование | C61: =-SUMIF(Доп.расчеты!$3:$3,Свод!C$4,Доп.расчеты!162:162) -> 0 | D61: =-SUMIF(Доп.расчеты!$3:$3,Свод!D$4,Доп.расчеты!162:162) -> 0 | E61: =-SUMIF(Доп.расчеты!$3:$3,Свод!E$4,Доп.расчеты!162:162) -> 0 | F61: =-SUMIF(Доп.расчеты!$3:$3,Свод!F$4,Доп.расчеты!162:162) -> 0 | G61: =-SUMIF(Доп.расчеты!$3:$3,Свод!G$4,Доп.расчеты!162:162) -> 0 | H61: =-SUMIF(Доп.расчеты!$3:$3,Свод!H$4,Доп.расчеты!162:162) -> 0 | I61: =-SUMIF(Доп.расчеты!$3:$3,Свод!I$4,Доп.расчеты!162:162) -> 0 | J61: =-SUMIF(Доп.расчеты!$3:$3,Свод!J$4,Доп.расчеты!162:162) -> 0 | ... M61: =-SUMIF(Доп.расчеты!$3:$3,Свод!M$4,Доп.расчеты!162:162) -> 0
B62: Офисное оборудование | C62: =-SUMIF(Доп.расчеты!$3:$3,Свод!C$4,Доп.расчеты!163:163) -> 0 | D62: =-SUMIF(Доп.расчеты!$3:$3,Свод!D$4,Доп.расчеты!163:163) -> 0 | E62: =-SUMIF(Доп.расчеты!$3:$3,Свод!E$4,Доп.расчеты!163:163) -> 0 | F62: =-SUMIF(Доп.расчеты!$3:$3,Свод!F$4,Доп.расчеты!163:163) -> 0 | G62: =-SUMIF(Доп.расчеты!$3:$3,Свод!G$4,Доп.расчеты!163:163) -> 0 | H62: =-SUMIF(Доп.расчеты!$3:$3,Свод!H$4,Доп.расчеты!163:163) -> 0 | I62: =-SUMIF(Доп.расчеты!$3:$3,Свод!I$4,Доп.расчеты!163:163) -> 0 | J62: =-SUMIF(Доп.расчеты!$3:$3,Свод!J$4,Доп.расчеты!163:163) -> 0 | ... M62: =-SUMIF(Доп.расчеты!$3:$3,Свод!M$4,Доп.расчеты!163:163) -> 0
B63: Рекламное оборудование | C63: =-SUMIF(Доп.расчеты!$3:$3,Свод!C$4,Доп.расчеты!164:164) -> 0 | D63: =-SUMIF(Доп.расчеты!$3:$3,Свод!D$4,Доп.расчеты!164:164) -> 0 | E63: =-SUMIF(Доп.расчеты!$3:$3,Свод!E$4,Доп.расчеты!164:164) -> 0 | F63: =-SUMIF(Доп.расчеты!$3:$3,Свод!F$4,Доп.расчеты!164:164) -> 0 | G63: =-SUMIF(Доп.расчеты!$3:$3,Свод!G$4,Доп.расчеты!164:164) -> 0 | H63: =-SUMIF(Доп.расчеты!$3:$3,Свод!H$4,Доп.расчеты!164:164) -> 0 | I63: =-SUMIF(Доп.расчеты!$3:$3,Свод!I$4,Доп.расчеты!164:164) -> 0 | J63: =-SUMIF(Доп.расчеты!$3:$3,Свод!J$4,Доп.расчеты!164:164) -> 0 | ... M63: =-SUMIF(Доп.расчеты!$3:$3,Свод!M$4,Доп.расчеты!164:164) -> 0
B64: ИТ оборудование | C64: =-SUMIF(Доп.расчеты!$3:$3,Свод!C$4,Доп.расчеты!165:165) -> 0 | D64: =-SUMIF(Доп.расчеты!$3:$3,Свод!D$4,Доп.расчеты!165:165) -> 0 | E64: =-SUMIF(Доп.расчеты!$3:$3,Свод!E$4,Доп.расчеты!165:165) -> 0 | F64: =-SUMIF(Доп.расчеты!$3:$3,Свод!F$4,Доп.расчеты!165:165) -> 0 | G64: =-SUMIF(Доп.расчеты!$3:$3,Свод!G$4,Доп.расчеты!165:165) -> 0 | H64: =-SUMIF(Доп.расчеты!$3:$3,Свод!H$4,Доп.расчеты!165:165) -> 0 | I64: =-SUMIF(Доп.расчеты!$3:$3,Свод!I$4,Доп.расчеты!165:165) -> 0 | J64: =-SUMIF(Доп.расчеты!$3:$3,Свод!J$4,Доп.расчеты!165:165) -> 0 | ... M64: =-SUMIF(Доп.расчеты!$3:$3,Свод!M$4,Доп.расчеты!165:165) -> 0
B65: СБ оборудование | C65: =-SUMIF(Доп.расчеты!$3:$3,Свод!C$4,Доп.расчеты!166:166) -> 0 | D65: =-SUMIF(Доп.расчеты!$3:$3,Свод!D$4,Доп.расчеты!166:166) -> 0 | E65: =-SUMIF(Доп.расчеты!$3:$3,Свод!E$4,Доп.расчеты!166:166) -> 0 | F65: =-SUMIF(Доп.расчеты!$3:$3,Свод!F$4,Доп.расчеты!166:166) -> 0 | G65: =-SUMIF(Доп.расчеты!$3:$3,Свод!G$4,Доп.расчеты!166:166) -> 0 | H65: =-SUMIF(Доп.расчеты!$3:$3,Свод!H$4,Доп.расчеты!166:166) -> 0 | I65: =-SUMIF(Доп.расчеты!$3:$3,Свод!I$4,Доп.расчеты!166:166) -> 0 | J65: =-SUMIF(Доп.расчеты!$3:$3,Свод!J$4,Доп.расчеты!166:166) -> 0 | ... M65: =-SUMIF(Доп.расчеты!$3:$3,Свод!M$4,Доп.расчеты!166:166) -> 0
B66: Прочее оборудование | C66: =-SUMIF(Доп.расчеты!$3:$3,Свод!C$4,Доп.расчеты!167:167) -> 0 | D66: =-SUMIF(Доп.расчеты!$3:$3,Свод!D$4,Доп.расчеты!167:167) -> 0 | E66: =-SUMIF(Доп.расчеты!$3:$3,Свод!E$4,Доп.расчеты!167:167) -> 0 | F66: =-SUMIF(Доп.расчеты!$3:$3,Свод!F$4,Доп.расчеты!167:167) -> 0 | G66: =-SUMIF(Доп.расчеты!$3:$3,Свод!G$4,Доп.расчеты!167:167) -> 0 | H66: =-SUMIF(Доп.расчеты!$3:$3,Свод!H$4,Доп.расчеты!167:167) -> 0 | I66: =-SUMIF(Доп.расчеты!$3:$3,Свод!I$4,Доп.расчеты!167:167) -> 0 | J66: =-SUMIF(Доп.расчеты!$3:$3,Свод!J$4,Доп.расчеты!167:167) -> 0 | ... M66: =-SUMIF(Доп.расчеты!$3:$3,Свод!M$4,Доп.расчеты!167:167) -> 0
B67: Транспорт | C67: =-SUMIF(Доп.расчеты!$3:$3,Свод!C$4,Доп.расчеты!168:168) -> 0 | D67: =-SUMIF(Доп.расчеты!$3:$3,Свод!D$4,Доп.расчеты!168:168) -> 0 | E67: =-SUMIF(Доп.расчеты!$3:$3,Свод!E$4,Доп.расчеты!168:168) -> 0 | F67: =-SUMIF(Доп.расчеты!$3:$3,Свод!F$4,Доп.расчеты!168:168) -> 0 | G67: =-SUMIF(Доп.расчеты!$3:$3,Свод!G$4,Доп.расчеты!168:168) -> 0 | H67: =-SUMIF(Доп.расчеты!$3:$3,Свод!H$4,Доп.расчеты!168:168) -> 0 | I67: =-SUMIF(Доп.расчеты!$3:$3,Свод!I$4,Доп.расчеты!168:168) -> 0 | J67: =-SUMIF(Доп.расчеты!$3:$3,Свод!J$4,Доп.расчеты!168:168) -> 0 | ... M67: =-SUMIF(Доп.расчеты!$3:$3,Свод!M$4,Доп.расчеты!168:168) -> 0
B68: Нематериальные активы | C68: =-SUMIF(Доп.расчеты!$3:$3,Свод!C$4,Доп.расчеты!169:169) -> 0 | D68: =-SUMIF(Доп.расчеты!$3:$3,Свод!D$4,Доп.расчеты!169:169) -> 0 | E68: =-SUMIF(Доп.расчеты!$3:$3,Свод!E$4,Доп.расчеты!169:169) -> 0 | F68: =-SUMIF(Доп.расчеты!$3:$3,Свод!F$4,Доп.расчеты!169:169) -> 0 | G68: =-SUMIF(Доп.расчеты!$3:$3,Свод!G$4,Доп.расчеты!169:169) -> 0 | H68: =-SUMIF(Доп.расчеты!$3:$3,Свод!H$4,Доп.расчеты!169:169) -> 0 | I68: =-SUMIF(Доп.расчеты!$3:$3,Свод!I$4,Доп.расчеты!169:169) -> 0 | J68: =-SUMIF(Доп.расчеты!$3:$3,Свод!J$4,Доп.расчеты!169:169) -> 0 | ... M68: =-SUMIF(Доп.расчеты!$3:$3,Свод!M$4,Доп.расчеты!169:169) -> 0
B69: Приобретение долей в бизнесе | C69: =-SUMIF(Доп.расчеты!$3:$3,Свод!C$4,Доп.расчеты!170:170) -> 0 | D69: =-SUMIF(Доп.расчеты!$3:$3,Свод!D$4,Доп.расчеты!170:170) -> 0 | E69: =-SUMIF(Доп.расчеты!$3:$3,Свод!E$4,Доп.расчеты!170:170) -> 0 | F69: =-SUMIF(Доп.расчеты!$3:$3,Свод!F$4,Доп.расчеты!170:170) -> 0 | G69: =-SUMIF(Доп.расчеты!$3:$3,Свод!G$4,Доп.расчеты!170:170) -> 0 | H69: =-SUMIF(Доп.расчеты!$3:$3,Свод!H$4,Доп.расчеты!170:170) -> 0 | I69: =-SUMIF(Доп.расчеты!$3:$3,Свод!I$4,Доп.расчеты!170:170) -> 0 | J69: =-SUMIF(Доп.расчеты!$3:$3,Свод!J$4,Доп.расчеты!170:170) -> 0 | ... M69: =-SUMIF(Доп.расчеты!$3:$3,Свод!M$4,Доп.расчеты!170:170) -> 0
B70: Капитализируемый ФОТ | C70: =-SUMIF(Доп.расчеты!$3:$3,Свод!C$4,Доп.расчеты!171:171) -> 0 | D70: =-SUMIF(Доп.расчеты!$3:$3,Свод!D$4,Доп.расчеты!171:171) -> 0 | E70: =-SUMIF(Доп.расчеты!$3:$3,Свод!E$4,Доп.расчеты!171:171) -> 0 | F70: =-SUMIF(Доп.расчеты!$3:$3,Свод!F$4,Доп.расчеты!171:171) -> 0 | G70: =-SUMIF(Доп.расчеты!$3:$3,Свод!G$4,Доп.расчеты!171:171) -> 0 | H70: =-SUMIF(Доп.расчеты!$3:$3,Свод!H$4,Доп.расчеты!171:171) -> 0 | I70: =-SUMIF(Доп.расчеты!$3:$3,Свод!I$4,Доп.расчеты!171:171) -> 0 | J70: =-SUMIF(Доп.расчеты!$3:$3,Свод!J$4,Доп.расчеты!171:171) -> 0 | ... M70: =-SUMIF(Доп.расчеты!$3:$3,Свод!M$4,Доп.расчеты!171:171) -> 0
B71: Консультационные услуги IT | C71: =-SUMIF(Доп.расчеты!$3:$3,Свод!C$4,Доп.расчеты!172:172) -> 0 | D71: =-SUMIF(Доп.расчеты!$3:$3,Свод!D$4,Доп.расчеты!172:172) -> 0 | E71: =-SUMIF(Доп.расчеты!$3:$3,Свод!E$4,Доп.расчеты!172:172) -> 0 | F71: =-SUMIF(Доп.расчеты!$3:$3,Свод!F$4,Доп.расчеты!172:172) -> 0 | G71: =-SUMIF(Доп.расчеты!$3:$3,Свод!G$4,Доп.расчеты!172:172) -> 0 | H71: =-SUMIF(Доп.расчеты!$3:$3,Свод!H$4,Доп.расчеты!172:172) -> 0 | I71: =-SUMIF(Доп.расчеты!$3:$3,Свод!I$4,Доп.расчеты!172:172) -> 0 | J71: =-SUMIF(Доп.расчеты!$3:$3,Свод!J$4,Доп.расчеты!172:172) -> 0 | ... M71: =-SUMIF(Доп.расчеты!$3:$3,Свод!M$4,Доп.расчеты!172:172) -> 0
B72: Тепловые завесы | C72: =-SUMIF(Доп.расчеты!$3:$3,Свод!C$4,Доп.расчеты!173:173) -> 0 | D72: =-SUMIF(Доп.расчеты!$3:$3,Свод!D$4,Доп.расчеты!173:173) -> 0 | E72: =-SUMIF(Доп.расчеты!$3:$3,Свод!E$4,Доп.расчеты!173:173) -> 0 | F72: =-SUMIF(Доп.расчеты!$3:$3,Свод!F$4,Доп.расчеты!173:173) -> 0 | G72: =-SUMIF(Доп.расчеты!$3:$3,Свод!G$4,Доп.расчеты!173:173) -> 0 | H72: =-SUMIF(Доп.расчеты!$3:$3,Свод!H$4,Доп.расчеты!173:173) -> 0 | I72: =-SUMIF(Доп.расчеты!$3:$3,Свод!I$4,Доп.расчеты!173:173) -> 0 | J72: =-SUMIF(Доп.расчеты!$3:$3,Свод!J$4,Доп.расчеты!173:173) -> 0 | ... M72: =-SUMIF(Доп.расчеты!$3:$3,Свод!M$4,Доп.расчеты!173:173) -> 0
B73: Кондиционеры и сплит-системы | C73: =-SUMIF(Доп.расчеты!$3:$3,Свод!C$4,Доп.расчеты!174:174) -> 0 | D73: =-SUMIF(Доп.расчеты!$3:$3,Свод!D$4,Доп.расчеты!174:174) -> 0 | E73: =-SUMIF(Доп.расчеты!$3:$3,Свод!E$4,Доп.расчеты!174:174) -> 0 | F73: =-SUMIF(Доп.расчеты!$3:$3,Свод!F$4,Доп.расчеты!174:174) -> 0 | G73: =-SUMIF(Доп.расчеты!$3:$3,Свод!G$4,Доп.расчеты!174:174) -> 0 | H73: =-SUMIF(Доп.расчеты!$3:$3,Свод!H$4,Доп.расчеты!174:174) -> 0 | I73: =-SUMIF(Доп.расчеты!$3:$3,Свод!I$4,Доп.расчеты!174:174) -> 0 | J73: =-SUMIF(Доп.расчеты!$3:$3,Свод!J$4,Доп.расчеты!174:174) -> 0 | ... M73: =-SUMIF(Доп.расчеты!$3:$3,Свод!M$4,Доп.расчеты!174:174) -> 0
B74: Автоматические двери и ворота | C74: =-SUMIF(Доп.расчеты!$3:$3,Свод!C$4,Доп.расчеты!175:175) -> 0 | D74: =-SUMIF(Доп.расчеты!$3:$3,Свод!D$4,Доп.расчеты!175:175) -> 0 | E74: =-SUMIF(Доп.расчеты!$3:$3,Свод!E$4,Доп.расчеты!175:175) -> 0 | F74: =-SUMIF(Доп.расчеты!$3:$3,Свод!F$4,Доп.расчеты!175:175) -> 0 | G74: =-SUMIF(Доп.расчеты!$3:$3,Свод!G$4,Доп.расчеты!175:175) -> 0 | H74: =-SUMIF(Доп.расчеты!$3:$3,Свод!H$4,Доп.расчеты!175:175) -> 0 | I74: =-SUMIF(Доп.расчеты!$3:$3,Свод!I$4,Доп.расчеты!175:175) -> 0 | J74: =-SUMIF(Доп.расчеты!$3:$3,Свод!J$4,Доп.расчеты!175:175) -> 0 | ... M74: =-SUMIF(Доп.расчеты!$3:$3,Свод!M$4,Доп.расчеты!175:175) -> 0
B75: Основная деятельность | C75: =SUM(C76:C88) -> 0 | D75: =SUM(D76:D88) -> 0 | E75: =SUM(E76:E88) -> 0 | F75: =SUM(F76:F88) -> 0 | G75: =SUM(G76:G88) -> 0 | H75: =SUM(H76:H88) -> 0 | I75: =SUM(I76:I88) -> 0 | J75: =SUM(J76:J88) -> 0 | ... M75: =SUM(M76:M88) -> 0
B76: Расходы на персонал | C76: =-SUMIF(Доп.расчеты!$3:$3,Свод!C$4,Доп.расчеты!177:177) -> 0 | D76: =-SUMIF(Доп.расчеты!$3:$3,Свод!D$4,Доп.расчеты!177:177) -> 0 | E76: =-SUMIF(Доп.расчеты!$3:$3,Свод!E$4,Доп.расчеты!177:177) -> 0 | F76: =-SUMIF(Доп.расчеты!$3:$3,Свод!F$4,Доп.расчеты!177:177) -> 0 | G76: =-SUMIF(Доп.расчеты!$3:$3,Свод!G$4,Доп.расчеты!177:177) -> 0 | H76: =-SUMIF(Доп.расчеты!$3:$3,Свод!H$4,Доп.расчеты!177:177) -> 0 | I76: =-SUMIF(Доп.расчеты!$3:$3,Свод!I$4,Доп.расчеты!177:177) -> 0 | J76: =-SUMIF(Доп.расчеты!$3:$3,Свод!J$4,Доп.расчеты!177:177) -> 0 | ... M76: =-SUMIF(Доп.расчеты!$3:$3,Свод!M$4,Доп.расчеты!177:177) -> 0
B77: Ремонт и обслуживание | C77: =-SUMIF(Доп.расчеты!$3:$3,Свод!C$4,Доп.расчеты!178:178) -> 0 | D77: =-SUMIF(Доп.расчеты!$3:$3,Свод!D$4,Доп.расчеты!178:178) -> 0 | E77: =-SUMIF(Доп.расчеты!$3:$3,Свод!E$4,Доп.расчеты!178:178) -> 0 | F77: =-SUMIF(Доп.расчеты!$3:$3,Свод!F$4,Доп.расчеты!178:178) -> 0 | G77: =-SUMIF(Доп.расчеты!$3:$3,Свод!G$4,Доп.расчеты!178:178) -> 0 | H77: =-SUMIF(Доп.расчеты!$3:$3,Свод!H$4,Доп.расчеты!178:178) -> 0 | I77: =-SUMIF(Доп.расчеты!$3:$3,Свод!I$4,Доп.расчеты!178:178) -> 0 | J77: =-SUMIF(Доп.расчеты!$3:$3,Свод!J$4,Доп.расчеты!178:178) -> 0 | ... M77: =-SUMIF(Доп.расчеты!$3:$3,Свод!M$4,Доп.расчеты!178:178) -> 0
B78: Коммунальные расходы и связь | C78: =-SUMIF(Доп.расчеты!$3:$3,Свод!C$4,Доп.расчеты!179:179) -> 0 | D78: =-SUMIF(Доп.расчеты!$3:$3,Свод!D$4,Доп.расчеты!179:179) -> 0 | E78: =-SUMIF(Доп.расчеты!$3:$3,Свод!E$4,Доп.расчеты!179:179) -> 0 | F78: =-SUMIF(Доп.расчеты!$3:$3,Свод!F$4,Доп.расчеты!179:179) -> 0 | G78: =-SUMIF(Доп.расчеты!$3:$3,Свод!G$4,Доп.расчеты!179:179) -> 0 | H78: =-SUMIF(Доп.расчеты!$3:$3,Свод!H$4,Доп.расчеты!179:179) -> 0 | I78: =-SUMIF(Доп.расчеты!$3:$3,Свод!I$4,Доп.расчеты!179:179) -> 0 | J78: =-SUMIF(Доп.расчеты!$3:$3,Свод!J$4,Доп.расчеты!179:179) -> 0 | ... M78: =-SUMIF(Доп.расчеты!$3:$3,Свод!M$4,Доп.расчеты!179:179) -> 0
B79: Расходы на охрану | C79: =-SUMIF(Доп.расчеты!$3:$3,Свод!C$4,Доп.расчеты!180:180) -> 0 | D79: =-SUMIF(Доп.расчеты!$3:$3,Свод!D$4,Доп.расчеты!180:180) -> 0 | E79: =-SUMIF(Доп.расчеты!$3:$3,Свод!E$4,Доп.расчеты!180:180) -> 0 | F79: =-SUMIF(Доп.расчеты!$3:$3,Свод!F$4,Доп.расчеты!180:180) -> 0 | G79: =-SUMIF(Доп.расчеты!$3:$3,Свод!G$4,Доп.расчеты!180:180) -> 0 | H79: =-SUMIF(Доп.расчеты!$3:$3,Свод!H$4,Доп.расчеты!180:180) -> 0 | I79: =-SUMIF(Доп.расчеты!$3:$3,Свод!I$4,Доп.расчеты!180:180) -> 0 | J79: =-SUMIF(Доп.расчеты!$3:$3,Свод!J$4,Доп.расчеты!180:180) -> 0 | ... M79: =-SUMIF(Доп.расчеты!$3:$3,Свод!M$4,Доп.расчеты!180:180) -> 0
B80: Расх материалы и хоз расходы | C80: =-SUMIF(Доп.расчеты!$3:$3,Свод!C$4,Доп.расчеты!181:181) -> 0 | D80: =-SUMIF(Доп.расчеты!$3:$3,Свод!D$4,Доп.расчеты!181:181) -> 0 | E80: =-SUMIF(Доп.расчеты!$3:$3,Свод!E$4,Доп.расчеты!181:181) -> 0 | F80: =-SUMIF(Доп.расчеты!$3:$3,Свод!F$4,Доп.расчеты!181:181) -> 0 | G80: =-SUMIF(Доп.расчеты!$3:$3,Свод!G$4,Доп.расчеты!181:181) -> 0 | H80: =-SUMIF(Доп.расчеты!$3:$3,Свод!H$4,Доп.расчеты!181:181) -> 0 | I80: =-SUMIF(Доп.расчеты!$3:$3,Свод!I$4,Доп.расчеты!181:181) -> 0 | J80: =-SUMIF(Доп.расчеты!$3:$3,Свод!J$4,Доп.расчеты!181:181) -> 0 | ... M80: =-SUMIF(Доп.расчеты!$3:$3,Свод!M$4,Доп.расчеты!181:181) -> 0
B81: Консультационные, информационные услуги и страхование | C81: =-SUMIF(Доп.расчеты!$3:$3,Свод!C$4,Доп.расчеты!182:182) -> 0 | D81: =-SUMIF(Доп.расчеты!$3:$3,Свод!D$4,Доп.расчеты!182:182) -> 0 | E81: =-SUMIF(Доп.расчеты!$3:$3,Свод!E$4,Доп.расчеты!182:182) -> 0 | F81: =-SUMIF(Доп.расчеты!$3:$3,Свод!F$4,Доп.расчеты!182:182) -> 0 | G81: =-SUMIF(Доп.расчеты!$3:$3,Свод!G$4,Доп.расчеты!182:182) -> 0 | H81: =-SUMIF(Доп.расчеты!$3:$3,Свод!H$4,Доп.расчеты!182:182) -> 0 | I81: =-SUMIF(Доп.расчеты!$3:$3,Свод!I$4,Доп.расчеты!182:182) -> 0 | J81: =-SUMIF(Доп.расчеты!$3:$3,Свод!J$4,Доп.расчеты!182:182) -> 0 | ... M81: =-SUMIF(Доп.расчеты!$3:$3,Свод!M$4,Доп.расчеты!182:182) -> 0
B82: Расходы на аренду | C82: =-SUMIF(Доп.расчеты!$3:$3,Свод!C$4,Доп.расчеты!183:183) -> 0 | D82: =-SUMIF(Доп.расчеты!$3:$3,Свод!D$4,Доп.расчеты!183:183) -> 0 | E82: =-SUMIF(Доп.расчеты!$3:$3,Свод!E$4,Доп.расчеты!183:183) -> 0 | F82: =-SUMIF(Доп.расчеты!$3:$3,Свод!F$4,Доп.расчеты!183:183) -> 0 | G82: =-SUMIF(Доп.расчеты!$3:$3,Свод!G$4,Доп.расчеты!183:183) -> 0 | H82: =-SUMIF(Доп.расчеты!$3:$3,Свод!H$4,Доп.расчеты!183:183) -> 0 | I82: =-SUMIF(Доп.расчеты!$3:$3,Свод!I$4,Доп.расчеты!183:183) -> 0 | J82: =-SUMIF(Доп.расчеты!$3:$3,Свод!J$4,Доп.расчеты!183:183) -> 0 | ... M82: =-SUMIF(Доп.расчеты!$3:$3,Свод!M$4,Доп.расчеты!183:183) -> 0
B83: Реклама, маркетинг и pr | C83: =-SUMIF(Доп.расчеты!$3:$3,Свод!C$4,Доп.расчеты!184:184) -> 0 | D83: =-SUMIF(Доп.расчеты!$3:$3,Свод!D$4,Доп.расчеты!184:184) -> 0 | E83: =-SUMIF(Доп.расчеты!$3:$3,Свод!E$4,Доп.расчеты!184:184) -> 0 | F83: =-SUMIF(Доп.расчеты!$3:$3,Свод!F$4,Доп.расчеты!184:184) -> 0 | G83: =-SUMIF(Доп.расчеты!$3:$3,Свод!G$4,Доп.расчеты!184:184) -> 0 | H83: =-SUMIF(Доп.расчеты!$3:$3,Свод!H$4,Доп.расчеты!184:184) -> 0 | I83: =-SUMIF(Доп.расчеты!$3:$3,Свод!I$4,Доп.расчеты!184:184) -> 0 | J83: =-SUMIF(Доп.расчеты!$3:$3,Свод!J$4,Доп.расчеты!184:184) -> 0 | ... M83: =-SUMIF(Доп.расчеты!$3:$3,Свод!M$4,Доп.расчеты!184:184) -> 0
B84: Транспортные расходы | C84: =-SUMIF(Доп.расчеты!$3:$3,Свод!C$4,Доп.расчеты!185:185) -> 0 | D84: =-SUMIF(Доп.расчеты!$3:$3,Свод!D$4,Доп.расчеты!185:185) -> 0 | E84: =-SUMIF(Доп.расчеты!$3:$3,Свод!E$4,Доп.расчеты!185:185) -> 0 | F84: =-SUMIF(Доп.расчеты!$3:$3,Свод!F$4,Доп.расчеты!185:185) -> 0 | G84: =-SUMIF(Доп.расчеты!$3:$3,Свод!G$4,Доп.расчеты!185:185) -> 0 | H84: =-SUMIF(Доп.расчеты!$3:$3,Свод!H$4,Доп.расчеты!185:185) -> 0 | I84: =-SUMIF(Доп.расчеты!$3:$3,Свод!I$4,Доп.расчеты!185:185) -> 0 | J84: =-SUMIF(Доп.расчеты!$3:$3,Свод!J$4,Доп.расчеты!185:185) -> 0 | ... M84: =-SUMIF(Доп.расчеты!$3:$3,Свод!M$4,Доп.расчеты!185:185) -> 0
B85: Услуги сторонних логистических операторов | C85: =-SUMIF(Доп.расчеты!$3:$3,Свод!C$4,Доп.расчеты!186:186) -> 0 | D85: =-SUMIF(Доп.расчеты!$3:$3,Свод!D$4,Доп.расчеты!186:186) -> 0 | E85: =-SUMIF(Доп.расчеты!$3:$3,Свод!E$4,Доп.расчеты!186:186) -> 0 | F85: =-SUMIF(Доп.расчеты!$3:$3,Свод!F$4,Доп.расчеты!186:186) -> 0 | G85: =-SUMIF(Доп.расчеты!$3:$3,Свод!G$4,Доп.расчеты!186:186) -> 0 | H85: =-SUMIF(Доп.расчеты!$3:$3,Свод!H$4,Доп.расчеты!186:186) -> 0 | I85: =-SUMIF(Доп.расчеты!$3:$3,Свод!I$4,Доп.расчеты!186:186) -> 0 | J85: =-SUMIF(Доп.расчеты!$3:$3,Свод!J$4,Доп.расчеты!186:186) -> 0 | ... M85: =-SUMIF(Доп.расчеты!$3:$3,Свод!M$4,Доп.расчеты!186:186) -> 0
B86: Налоги | C86: =-SUMIF(Доп.расчеты!$3:$3,Свод!C$4,Доп.расчеты!187:187) -> 0 | D86: =-SUMIF(Доп.расчеты!$3:$3,Свод!D$4,Доп.расчеты!187:187) -> 0 | E86: =-SUMIF(Доп.расчеты!$3:$3,Свод!E$4,Доп.расчеты!187:187) -> 0 | F86: =-SUMIF(Доп.расчеты!$3:$3,Свод!F$4,Доп.расчеты!187:187) -> 0 | G86: =-SUMIF(Доп.расчеты!$3:$3,Свод!G$4,Доп.расчеты!187:187) -> 0 | H86: =-SUMIF(Доп.расчеты!$3:$3,Свод!H$4,Доп.расчеты!187:187) -> 0 | I86: =-SUMIF(Доп.расчеты!$3:$3,Свод!I$4,Доп.расчеты!187:187) -> 0 | J86: =-SUMIF(Доп.расчеты!$3:$3,Свод!J$4,Доп.расчеты!187:187) -> 0 | ... M86: =-SUMIF(Доп.расчеты!$3:$3,Свод!M$4,Доп.расчеты!187:187) -> 0
B87: Прочие расходы | C87: =-SUMIF(Доп.расчеты!$3:$3,Свод!C$4,Доп.расчеты!188:188) -> 0 | D87: =-SUMIF(Доп.расчеты!$3:$3,Свод!D$4,Доп.расчеты!188:188) -> 0 | E87: =-SUMIF(Доп.расчеты!$3:$3,Свод!E$4,Доп.расчеты!188:188) -> 0 | F87: =-SUMIF(Доп.расчеты!$3:$3,Свод!F$4,Доп.расчеты!188:188) -> 0 | G87: =-SUMIF(Доп.расчеты!$3:$3,Свод!G$4,Доп.расчеты!188:188) -> 0 | H87: =-SUMIF(Доп.расчеты!$3:$3,Свод!H$4,Доп.расчеты!188:188) -> 0 | I87: =-SUMIF(Доп.расчеты!$3:$3,Свод!I$4,Доп.расчеты!188:188) -> 0 | J87: =-SUMIF(Доп.расчеты!$3:$3,Свод!J$4,Доп.расчеты!188:188) -> 0 | ... M87: =-SUMIF(Доп.расчеты!$3:$3,Свод!M$4,Доп.расчеты!188:188) -> 0
B88: Командировочные расходы | C88: =-SUMIF(Доп.расчеты!$3:$3,Свод!C$4,Доп.расчеты!189:189) -> 0 | D88: =-SUMIF(Доп.расчеты!$3:$3,Свод!D$4,Доп.расчеты!189:189) -> 0 | E88: =-SUMIF(Доп.расчеты!$3:$3,Свод!E$4,Доп.расчеты!189:189) -> 0 | F88: =-SUMIF(Доп.расчеты!$3:$3,Свод!F$4,Доп.расчеты!189:189) -> 0 | G88: =-SUMIF(Доп.расчеты!$3:$3,Свод!G$4,Доп.расчеты!189:189) -> 0 | H88: =-SUMIF(Доп.расчеты!$3:$3,Свод!H$4,Доп.расчеты!189:189) -> 0 | I88: =-SUMIF(Доп.расчеты!$3:$3,Свод!I$4,Доп.расчеты!189:189) -> 0 | J88: =-SUMIF(Доп.расчеты!$3:$3,Свод!J$4,Доп.расчеты!189:189) -> 0 | ... M88: =-SUMIF(Доп.расчеты!$3:$3,Свод!M$4,Доп.расчеты!189:189) -> 0
B89: Экономический эффект
B90: САРЕХ | C90: =SUM(C91:C114) -> 0 | D90: =SUM(D91:D114) -> 0 | E90: =SUM(E91:E114) -> 0 | F90: =SUM(F91:F114) -> 0 | G90: =SUM(G91:G114) -> 0 | H90: =SUM(H91:H114) -> 0 | I90: =SUM(I91:I114) -> 0 | J90: =SUM(J91:J114) -> 0 | ... M90: =SUM(M91:M114) -> 0
B91: Земельные участки | C91: =-SUMIF(Доп.расчеты!$3:$3,Свод!C$4,Доп.расчеты!51:51) -> 0 | D91: =-SUMIF(Доп.расчеты!$3:$3,Свод!D$4,Доп.расчеты!51:51) -> 0 | E91: =-SUMIF(Доп.расчеты!$3:$3,Свод!E$4,Доп.расчеты!51:51) -> 0 | F91: =-SUMIF(Доп.расчеты!$3:$3,Свод!F$4,Доп.расчеты!51:51) -> 0 | G91: =-SUMIF(Доп.расчеты!$3:$3,Свод!G$4,Доп.расчеты!51:51) -> 0 | H91: =-SUMIF(Доп.расчеты!$3:$3,Свод!H$4,Доп.расчеты!51:51) -> 0 | I91: =-SUMIF(Доп.расчеты!$3:$3,Свод!I$4,Доп.расчеты!51:51) -> 0 | J91: =-SUMIF(Доп.расчеты!$3:$3,Свод!J$4,Доп.расчеты!51:51) -> 0 | ... M91: =-SUMIF(Доп.расчеты!$3:$3,Свод!M$4,Доп.расчеты!51:51) -> 0
B92: Здания и сооружения | C92: =-SUMIF(Доп.расчеты!$3:$3,Свод!C$4,Доп.расчеты!52:52) -> 0 | D92: =-SUMIF(Доп.расчеты!$3:$3,Свод!D$4,Доп.расчеты!52:52) -> 0 | E92: =-SUMIF(Доп.расчеты!$3:$3,Свод!E$4,Доп.расчеты!52:52) -> 0 | F92: =-SUMIF(Доп.расчеты!$3:$3,Свод!F$4,Доп.расчеты!52:52) -> 0 | G92: =-SUMIF(Доп.расчеты!$3:$3,Свод!G$4,Доп.расчеты!52:52) -> 0 | H92: =-SUMIF(Доп.расчеты!$3:$3,Свод!H$4,Доп.расчеты!52:52) -> 0 | I92: =-SUMIF(Доп.расчеты!$3:$3,Свод!I$4,Доп.расчеты!52:52) -> 0 | J92: =-SUMIF(Доп.расчеты!$3:$3,Свод!J$4,Доп.расчеты!52:52) -> 0 | ... M92: =-SUMIF(Доп.расчеты!$3:$3,Свод!M$4,Доп.расчеты!52:52) -> 0
B93: Помещения в составе зданий и сооружений | C93: =-SUMIF(Доп.расчеты!$3:$3,Свод!C$4,Доп.расчеты!53:53) -> 0 | D93: =-SUMIF(Доп.расчеты!$3:$3,Свод!D$4,Доп.расчеты!53:53) -> 0 | E93: =-SUMIF(Доп.расчеты!$3:$3,Свод!E$4,Доп.расчеты!53:53) -> 0 | F93: =-SUMIF(Доп.расчеты!$3:$3,Свод!F$4,Доп.расчеты!53:53) -> 0 | G93: =-SUMIF(Доп.расчеты!$3:$3,Свод!G$4,Доп.расчеты!53:53) -> 0 | H93: =-SUMIF(Доп.расчеты!$3:$3,Свод!H$4,Доп.расчеты!53:53) -> 0 | I93: =-SUMIF(Доп.расчеты!$3:$3,Свод!I$4,Доп.расчеты!53:53) -> 0 | J93: =-SUMIF(Доп.расчеты!$3:$3,Свод!J$4,Доп.расчеты!53:53) -> 0 | ... M93: =-SUMIF(Доп.расчеты!$3:$3,Свод!M$4,Доп.расчеты!53:53) -> 0
B94: Строительство и ремонты | C94: =-SUMIF(Доп.расчеты!$3:$3,Свод!C$4,Доп.расчеты!54:54) -> 0 | D94: =-SUMIF(Доп.расчеты!$3:$3,Свод!D$4,Доп.расчеты!54:54) -> 0 | E94: =-SUMIF(Доп.расчеты!$3:$3,Свод!E$4,Доп.расчеты!54:54) -> 0 | F94: =-SUMIF(Доп.расчеты!$3:$3,Свод!F$4,Доп.расчеты!54:54) -> 0 | G94: =-SUMIF(Доп.расчеты!$3:$3,Свод!G$4,Доп.расчеты!54:54) -> 0 | H94: =-SUMIF(Доп.расчеты!$3:$3,Свод!H$4,Доп.расчеты!54:54) -> 0 | I94: =-SUMIF(Доп.расчеты!$3:$3,Свод!I$4,Доп.расчеты!54:54) -> 0 | J94: =-SUMIF(Доп.расчеты!$3:$3,Свод!J$4,Доп.расчеты!54:54) -> 0 | ... M94: =-SUMIF(Доп.расчеты!$3:$3,Свод!M$4,Доп.расчеты!54:54) -> 0
B95: Холодильное оборудование | C95: =-SUMIF(Доп.расчеты!$3:$3,Свод!C$4,Доп.расчеты!55:55) -> 0 | D95: =-SUMIF(Доп.расчеты!$3:$3,Свод!D$4,Доп.расчеты!55:55) -> 0 | E95: =-SUMIF(Доп.расчеты!$3:$3,Свод!E$4,Доп.расчеты!55:55) -> 0 | F95: =-SUMIF(Доп.расчеты!$3:$3,Свод!F$4,Доп.расчеты!55:55) -> 0 | G95: =-SUMIF(Доп.расчеты!$3:$3,Свод!G$4,Доп.расчеты!55:55) -> 0 | H95: =-SUMIF(Доп.расчеты!$3:$3,Свод!H$4,Доп.расчеты!55:55) -> 0 | I95: =-SUMIF(Доп.расчеты!$3:$3,Свод!I$4,Доп.расчеты!55:55) -> 0 | J95: =-SUMIF(Доп.расчеты!$3:$3,Свод!J$4,Доп.расчеты!55:55) -> 0 | ... M95: =-SUMIF(Доп.расчеты!$3:$3,Свод!M$4,Доп.расчеты!55:55) -> 0
B96: Стеллажное оборудование | C96: =-SUMIF(Доп.расчеты!$3:$3,Свод!C$4,Доп.расчеты!56:56) -> 0 | D96: =-SUMIF(Доп.расчеты!$3:$3,Свод!D$4,Доп.расчеты!56:56) -> 0 | E96: =-SUMIF(Доп.расчеты!$3:$3,Свод!E$4,Доп.расчеты!56:56) -> 0 | F96: =-SUMIF(Доп.расчеты!$3:$3,Свод!F$4,Доп.расчеты!56:56) -> 0 | G96: =-SUMIF(Доп.расчеты!$3:$3,Свод!G$4,Доп.расчеты!56:56) -> 0 | H96: =-SUMIF(Доп.расчеты!$3:$3,Свод!H$4,Доп.расчеты!56:56) -> 0 | I96: =-SUMIF(Доп.расчеты!$3:$3,Свод!I$4,Доп.расчеты!56:56) -> 0 | J96: =-SUMIF(Доп.расчеты!$3:$3,Свод!J$4,Доп.расчеты!56:56) -> 0 | ... M96: =-SUMIF(Доп.расчеты!$3:$3,Свод!M$4,Доп.расчеты!56:56) -> 0
B97: Производственное оборудование | C97: =-SUMIF(Доп.расчеты!$3:$3,Свод!C$4,Доп.расчеты!57:57) -> 0 | D97: =-SUMIF(Доп.расчеты!$3:$3,Свод!D$4,Доп.расчеты!57:57) -> 0 | E97: =-SUMIF(Доп.расчеты!$3:$3,Свод!E$4,Доп.расчеты!57:57) -> 0 | F97: =-SUMIF(Доп.расчеты!$3:$3,Свод!F$4,Доп.расчеты!57:57) -> 0 | G97: =-SUMIF(Доп.расчеты!$3:$3,Свод!G$4,Доп.расчеты!57:57) -> 0 | H97: =-SUMIF(Доп.расчеты!$3:$3,Свод!H$4,Доп.расчеты!57:57) -> 0 | I97: =-SUMIF(Доп.расчеты!$3:$3,Свод!I$4,Доп.расчеты!57:57) -> 0 | J97: =-SUMIF(Доп.расчеты!$3:$3,Свод!J$4,Доп.расчеты!57:57) -> 0 | ... M97: =-SUMIF(Доп.расчеты!$3:$3,Свод!M$4,Доп.расчеты!57:57) -> 0
B98: Торговое оборудование | C98: =-SUMIF(Доп.расчеты!$3:$3,Свод!C$4,Доп.расчеты!58:58) -> 0 | D98: =-SUMIF(Доп.расчеты!$3:$3,Свод!D$4,Доп.расчеты!58:58) -> 0 | E98: =-SUMIF(Доп.расчеты!$3:$3,Свод!E$4,Доп.расчеты!58:58) -> 0 | F98: =-SUMIF(Доп.расчеты!$3:$3,Свод!F$4,Доп.расчеты!58:58) -> 0 | G98: =-SUMIF(Доп.расчеты!$3:$3,Свод!G$4,Доп.расчеты!58:58) -> 0 | H98: =-SUMIF(Доп.расчеты!$3:$3,Свод!H$4,Доп.расчеты!58:58) -> 0 | I98: =-SUMIF(Доп.расчеты!$3:$3,Свод!I$4,Доп.расчеты!58:58) -> 0 | J98: =-SUMIF(Доп.расчеты!$3:$3,Свод!J$4,Доп.расчеты!58:58) -> 0 | ... M98: =-SUMIF(Доп.расчеты!$3:$3,Свод!M$4,Доп.расчеты!58:58) -> 0
B99: Складское оборудование | C99: =-SUMIF(Доп.расчеты!$3:$3,Свод!C$4,Доп.расчеты!59:59) -> 0 | D99: =-SUMIF(Доп.расчеты!$3:$3,Свод!D$4,Доп.расчеты!59:59) -> 0 | E99: =-SUMIF(Доп.расчеты!$3:$3,Свод!E$4,Доп.расчеты!59:59) -> 0 | F99: =-SUMIF(Доп.расчеты!$3:$3,Свод!F$4,Доп.расчеты!59:59) -> 0 | G99: =-SUMIF(Доп.расчеты!$3:$3,Свод!G$4,Доп.расчеты!59:59) -> 0 | H99: =-SUMIF(Доп.расчеты!$3:$3,Свод!H$4,Доп.расчеты!59:59) -> 0 | I99: =-SUMIF(Доп.расчеты!$3:$3,Свод!I$4,Доп.расчеты!59:59) -> 0 | J99: =-SUMIF(Доп.расчеты!$3:$3,Свод!J$4,Доп.расчеты!59:59) -> 0 | ... M99: =-SUMIF(Доп.расчеты!$3:$3,Свод!M$4,Доп.расчеты!59:59) -> 0
B100: Вертикальный транспорт | C100: =-SUMIF(Доп.расчеты!$3:$3,Свод!C$4,Доп.расчеты!60:60) -> 0 | D100: =-SUMIF(Доп.расчеты!$3:$3,Свод!D$4,Доп.расчеты!60:60) -> 0 | E100: =-SUMIF(Доп.расчеты!$3:$3,Свод!E$4,Доп.расчеты!60:60) -> 0 | F100: =-SUMIF(Доп.расчеты!$3:$3,Свод!F$4,Доп.расчеты!60:60) -> 0 | G100: =-SUMIF(Доп.расчеты!$3:$3,Свод!G$4,Доп.расчеты!60:60) -> 0 | H100: =-SUMIF(Доп.расчеты!$3:$3,Свод!H$4,Доп.расчеты!60:60) -> 0 | I100: =-SUMIF(Доп.расчеты!$3:$3,Свод!I$4,Доп.расчеты!60:60) -> 0 | J100: =-SUMIF(Доп.расчеты!$3:$3,Свод!J$4,Доп.расчеты!60:60) -> 0 | ... M100: =-SUMIF(Доп.расчеты!$3:$3,Свод!M$4,Доп.расчеты!60:60) -> 0
B101: Клининговое оборудование | C101: =-SUMIF(Доп.расчеты!$3:$3,Свод!C$4,Доп.расчеты!61:61) -> 0 | D101: =-SUMIF(Доп.расчеты!$3:$3,Свод!D$4,Доп.расчеты!61:61) -> 0 | E101: =-SUMIF(Доп.расчеты!$3:$3,Свод!E$4,Доп.расчеты!61:61) -> 0 | F101: =-SUMIF(Доп.расчеты!$3:$3,Свод!F$4,Доп.расчеты!61:61) -> 0 | G101: =-SUMIF(Доп.расчеты!$3:$3,Свод!G$4,Доп.расчеты!61:61) -> 0 | H101: =-SUMIF(Доп.расчеты!$3:$3,Свод!H$4,Доп.расчеты!61:61) -> 0 | I101: =-SUMIF(Доп.расчеты!$3:$3,Свод!I$4,Доп.расчеты!61:61) -> 0 | J101: =-SUMIF(Доп.расчеты!$3:$3,Свод!J$4,Доп.расчеты!61:61) -> 0 | ... M101: =-SUMIF(Доп.расчеты!$3:$3,Свод!M$4,Доп.расчеты!61:61) -> 0
...

Sheet Как есть
A1: В ТЫС. РУБ. ! | B1: Дата начала проекта ----->>>>>> | C1: 46023 | D1: 46387 | E1: <<<<<<-----Дата окончания проекта | I1: =IF(($C$7/12)>H11,#REF!+1,"") | J1: =IF(($C$7/12)>I11,I1+1,"") | K1: =IF(($C$7/12)>J11,J1+1,"") | L1: =IF(($C$7/12)>K11,K1+1,"") | M1: =IF(($C$7/12)>L11,L1+1,"")
B2: 3 | C2: <-- выбор между CPI (2) и WACC (3)
C3: 2021 | D3: 2022 | E3: 2023 | F3: 2024 | G3: 2025 | H3: 2026 | I3: 2027 | J3: 2028
A4: CPI | C4: 0.04 | D4: 0.04 | E4: 0.059 | F4: 0.0811 | G4: 0.07 | H4: 0.07 | I4: 0.07 | J4: 0.05
A5: WACC monthly | C5: =IFERROR(HLOOKUP(C14,WACC_monthly!1:2,2,0),B5) -> 0.16 | D5: =IFERROR(HLOOKUP(D14,WACC_monthly!1:2,2,0),C5) -> 0.16 | E5: =IFERROR(HLOOKUP(E14,WACC_monthly!1:2,2,0),D5) -> 0.16 | F5: =IFERROR(HLOOKUP(F14,WACC_monthly!1:2,2,0),E5) -> 0.16 | G5: =IFERROR(HLOOKUP(G14,WACC_monthly!1:2,2,0),F5) -> 0.16 | H5: =IFERROR(HLOOKUP(H14,WACC_monthly!1:2,2,0),G5) -> 0.16 | I5: =IFERROR(HLOOKUP(I14,WACC_monthly!1:2,2,0),H5) -> 0.16 | J5: =IFERROR(HLOOKUP(J14,WACC_monthly!1:2,2,0),I5) -> 0.16 | ... GT5: =IFERROR(HLOOKUP(GT14,WACC_monthly!1:2,2,0),GS5) -> 0.16
A7: Срок полезного использования, мес | C7: 60
C9: =C12 -> 2026 | D9: =D12 -> 2026 | E9: =E12 -> 2026 | F9: =F12 -> 2026 | G9: =G12 -> 2026 | H9: =H12 -> 2026 | I9: =I12 -> 2026 | J9: =J12 -> 2026 | ... GT9: =GT12
C10: ='Как будет'!C10 -> 1 | D10: ='Как будет'!D10 -> 0.98770784 | E10: ='Как будет'!E10 -> 0.97556678 | F10: ='Как будет'!F10 -> 0.96357495 | G10: ='Как будет'!G10 -> 0.95173054 | H10: ='Как будет'!H10 -> 0.94003171 | I10: ='Как будет'!I10 -> 0.92847669 | J10: ='Как будет'!J10 -> 0.91706371 | ... GT10: ='Как будет'!GT10 -> 0.085324093
C11: 0 | D11: 1 | E11: =D11+1 -> 2 | F11: =E11+1 -> 3 | G11: =F11+1 -> 4 | H11: =G11+1 -> 5 | I11: =H11+1 -> 6 | J11: =I11+1 -> 7 | K11: =J11+1 -> 8 | L11: =K11+1 -> 9 | ... GT11: =GS11+1 -> 199
C12: =IFERROR(YEAR(C14),"") -> 2026 | D12: =IFERROR(YEAR(D14),"") -> 2026 | E12: =IFERROR(YEAR(E14),"") -> 2026 | F12: =IFERROR(YEAR(F14),"") -> 2026 | G12: =IFERROR(YEAR(G14),"") -> 2026 | H12: =IFERROR(YEAR(H14),"") -> 2026 | I12: =IFERROR(YEAR(I14),"") -> 2026 | J12: =IFERROR(YEAR(J14),"") -> 2026 | ... GT12: =IFERROR(YEAR(GT14),"")
C13: =IFERROR(MONTH(C14),"") -> 1 | D13: =IFERROR(MONTH(D14),"") -> 2 | E13: =IFERROR(MONTH(E14),"") -> 3 | F13: =IFERROR(MONTH(F14),"") -> 4 | G13: =IFERROR(MONTH(G14),"") -> 5 | H13: =IFERROR(MONTH(H14),"") -> 6 | I13: =IFERROR(MONTH(I14),"") -> 7 | J13: =IFERROR(MONTH(J14),"") -> 8 | ... GT13: =IFERROR(MONTH(GT14),"")
A14: AS IS | B14: Комментарии | C14: =DATE(YEAR(C1),MONTH(C1),1) -> 46023 | D14: =IF(D11>=$C$7,"",EDATE(C14,1)) -> 46054 | E14: =IF(E11>=$C$7,"",EDATE(D14,1)) -> 46082 | F14: =IF(F11>=$C$7,"",EDATE(E14,1)) -> 46113 | G14: =IF(G11>=$C$7,"",EDATE(F14,1)) -> 46143 | H14: =IF(H11>=$C$7,"",EDATE(G14,1)) -> 46174 | I14: =IF(I11>=$C$7,"",EDATE(H14,1)) -> 46204 | J14: =IF(J11>=$C$7,"",EDATE(I14,1)) -> 46235 | K14: =IF(K11>=$C$7,"",EDATE(J14,1)) -> 46266 | ... GT14: =IF(GT11>=$C$7,"",EDATE(GS14,1))
A15: Текущие расходы
A16: CAPEX | C16: =-SUM(C17:C24) -> 0 | D16: =-SUM(D17:D24) -> 0 | E16: =-SUM(E17:E24) -> 0 | F16: =-SUM(F17:F24) -> 0 | G16: =-SUM(G17:G24) -> 0 | H16: =-SUM(H17:H24) -> 0 | I16: =-SUM(I17:I24) -> 0 | J16: =-SUM(J17:J24) -> 0 | ... GT16: =-SUM(GT17:GT24) -> 0
A17: ИТ оборудование
A18: Капитализируемый ФОТ
A19: Консультационные услуги IT
A20: Нематериальные активы
A21: Производственное оборудование
A22: Рекламное оборудование
A23: Офисное оборудование
A24: Офисное оборудование
A25: Инвестиционный OPEX (вкл. Ранний старт) | C25: =SUM(C26:C33) -> 0 | D25: =SUM(D26:D33) -> 0 | E25: =SUM(E26:E33) -> 0 | F25: =SUM(F26:F33) -> 0 | G25: =SUM(G26:G33) -> 0 | H25: =SUM(H26:H33) -> 0 | I25: =SUM(I26:I33) -> 0 | J25: =SUM(J26:J33) -> 0 | ... GT25: =SUM(GT26:GT33) -> 0
A26: Расходы на персонал
A27: Расходы на персонал_Ранний старт
A28: Консультационные, информационные услуги и страхование
A29: Расходы на персонал
A30: Расходы на персонал_Ранний старт
A31: Консультационные, информационные услуги и страхование
A32: Расходы на персонал
A33: Расходы на персонал_Ранний старт
A34: OPEX | C34: =-SUM(C35:C42) -> 0 | D34: =-SUM(D35:D42) -> 0 | E34: =-SUM(E35:E42) -> 0 | F34: =-SUM(F35:F42) -> 0 | G34: =-SUM(G35:G42) -> 0 | H34: =-SUM(H35:H42) -> 0 | I34: =-SUM(I35:I42) -> 0 | J34: =-SUM(J35:J42) -> 0 | ... GT34: =-SUM(GT35:GT42) -> 0
A35: Прочие расходы
A36: Консультационные, информационные услуги и страхование
A37: Транспортные расходы
A38: Расходы на аренду
A39: Командировочные расходы
A43: Постпроектные расходы
A44: CAPEX | C44: =-SUM(C45:C52) -> 0 | D44: =-SUM(D45:D52) -> 0 | E44: =-SUM(E45:E52) -> 0 | F44: =-SUM(F45:F52) -> 0 | G44: =-SUM(G45:G52) -> 0 | H44: =-SUM(H45:H52) -> 0 | I44: =-SUM(I45:I52) -> 0 | J44: =-SUM(J45:J52) -> 0 | ... GT44: =-SUM(GT45:GT52) -> 0
A45: ИТ оборудование
A46: Капитализируемый ФОТ
A47: Консультационные услуги IT
A48: Нематериальные активы
A49: Производственное оборудование
A50: Рекламное оборудование
A51: Офисное оборудование
A52: Рекламное оборудование
A53: Инвестиционный OPEX (вкл. Ранний старт) | C53: =SUM(C54:C61) -> 0 | D53: =SUM(D54:D61) -> 0 | E53: =SUM(E54:E61) -> 0 | F53: =SUM(F54:F61) -> 0 | G53: =SUM(G54:G61) -> 0 | H53: =SUM(H54:H61) -> 0 | I53: =SUM(I54:I61) -> 0 | J53: =SUM(J54:J61) -> 0 | ... GT53: =SUM(GT54:GT61) -> 0
A54: Расходы на персонал
A55: Расходы на персонал_Ранний старт
A56: Консультационные, информационные услуги и страхование
A57: Расходы на персонал
A58: Расходы на персонал_Ранний старт
A59: Консультационные, информационные услуги и страхование
A60: Расходы на персонал
A61: Расходы на персонал_Ранний старт
A62: OPEX | C62: =-SUM(C63:C70) -> 0 | D62: =-SUM(D63:D70) -> 0 | E62: =-SUM(E63:E70) -> 0 | F62: =-SUM(F63:F70) -> 0 | G62: =-SUM(G63:G70) -> 0 | H62: =-SUM(H63:H70) -> 0 | I62: =-SUM(I63:I70) -> 0 | J62: =-SUM(J63:J70) -> 0 | ... GT62: =-SUM(GT63:GT70) -> 0
A63: Расходы на персонал
A64: Консультационные, информационные услуги и страхование
A65: Транспортные расходы
A66: Расходы на аренду
A67: Командировочные расходы
A71: Экономический эффект
A72: САРЕХ | C72: =-SUM(C73:C80) -> 0 | D72: =-SUM(D73:D80) -> 0 | E72: =-SUM(E73:E80) -> 0 | F72: =-SUM(F73:F80) -> 0 | G72: =-SUM(G73:G80) -> 0 | H72: =-SUM(H73:H80) -> 0 | I72: =-SUM(I73:I80) -> 0 | J72: =-SUM(J73:J80) -> 0 | ... GT72: =-SUM(GT73:GT80) -> 0
A73: Капитализируемый ФОТ
A74: ИТ оборудование
A75: Нематериальные активы
A76: Консультационные услуги IT
A77: Складское оборудование
A78: Капитализируемый ФОТ
A79: Складское оборудование
A80: Капитализируемый ФОТ
A81: Инвестиционный OPEX (вкл. Ранний старт) | C81: =-SUM(C82:C89) -> 0 | D81: =-SUM(D82:D89) -> 0 | E81: =-SUM(E82:E89) -> 0 | F81: =-SUM(F82:F89) -> 0 | G81: =-SUM(G82:G89) -> 0 | H81: =-SUM(H82:H89) -> 0 | I81: =-SUM(I82:I89) -> 0 | J81: =-SUM(J82:J89) -> 0 | ... GT81: =-SUM(GT82:GT89) -> 0
A82: Расходы на персонал
A83: Расходы на персонал_Ранний старт
A84: Консультационные, информационные услуги и страхование
A85: Расходы на персонал
A86: Расходы на персонал_Ранний старт
A87: Консультационные, информационные услуги и страхование
A88: Расходы на персонал
A89: Расходы на персонал_Ранний старт
A90: ВЫРУЧКА
A91: СЕБЕСТОИМОСТЬ | C91: =-SUM(C92:C95) -> 0 | D91: =-SUM(D92:D95) -> 0 | E91: =-SUM(E92:E95) -> 0 | F91: =-SUM(F92:F95) -> 0 | G91: =-SUM(G92:G95) -> 0 | H91: =-SUM(H92:H95) -> 0 | I91: =-SUM(I92:I95) -> 0 | J91: =-SUM(J92:J95) -> 0 | ... GT91: =-SUM(GT92:GT95) -> 0
A92: Складская логистика
A93: Затраты производства
A94: Транспортная логистика
A95: Потери
A96: Валовый доход | C96: =IF(C97=0,C90+C91,C97) -> 0 | D96: =IF(D97=0,D90+D91,D97) -> 0 | E96: =IF(E97=0,E90+E91,E97) -> 0 | F96: =IF(F97=0,F90+F91,F97) -> 0 | G96: =IF(G97=0,G90+G91,G97) -> 0 | H96: =IF(H97=0,H90+H91,H97) -> 0 | I96: =IF(I97=0,I90+I91,I97) -> 0 | J96: =IF(J97=0,J90+J91,J97) -> 0 | ... GT96: =IF(GT97=0,GT90+GT91,GT97) -> 0
A97: Коммерческая маржа | C97: =C98+C99 -> 0 | D97: =D98+D99 -> 0 | E97: =E98+E99 -> 0 | F97: =F98+F99 -> 0 | G97: =G98+G99 -> 0 | H97: =H98+H99 -> 0 | I97: =I98+I99 -> 0 | J97: =J98+J99 -> 0 | ... GT97: =GT98+GT99 -> 0
A98: Front Margin
A99: Back Margin
A100: OPEX | C100: =-SUMIFS(C101:C108,$A$101:$A$108,"<>Прочие доходы")+SUMIFS(C101:C108,$A$101:$A$108,"Прочие доходы") -> 0 | D100: =-SUMIFS(D101:D108,$A$101:$A$108,"<>Прочие доходы")+SUMIFS(D101:D108,$A$101:$A$108,"Прочие доходы") -> 0 | E100: =-SUMIFS(E101:E108,$A$101:$A$108,"<>Прочие доходы")+SUMIFS(E101:E108,$A$101:$A$108,"Прочие доходы") -> 0 | F100: =-SUMIFS(F101:F108,$A$101:$A$108,"<>Прочие доходы")+SUMIFS(F101:F108,$A$101:$A$108,"Прочие доходы") -> 0 | G100: =-SUMIFS(G101:G108,$A$101:$A$108,"<>Прочие доходы")+SUMIFS(G101:G108,$A$101:$A$108,"Прочие доходы") -> 0 | H100: =-SUMIFS(H101:H108,$A$101:$A$108,"<>Прочие доходы")+SUMIFS(H101:H108,$A$101:$A$108,"Прочие доходы") -> 0 | I100: =-SUMIFS(I101:I108,$A$101:$A$108,"<>Прочие доходы")+SUMIFS(I101:I108,$A$101:$A$108,"Прочие доходы") -> 0 | J100: =-SUMIFS(J101:J108,$A$101:$A$108,"<>Прочие доходы")+SUMIFS(J101:J108,$A$101:$A$108,"Прочие доходы") -> 0 | ... GT100: =-SUMIFS(GT101:GT108,$A$101:$A$108,"<>Прочие доходы")+SUMIFS(GT101:GT108,$A$101:$A$108,"Прочие доходы") -> 0
A101: ФОТ штатного персонала
A102: Расходы на аутстаф
A103: Прочие расходы
A104: Прочие доходы
A105: Расходы на аренду
A106: Реклама, маркетинг и PR
A107: Коммунальные расходы и связь
A108: Товарные запасы
...

Sheet Как будет
A1: В ТЫС. РУБ. ! | B1: Дата начала проекта ----->>>>>> | C1: ='Как есть'!C1 -> 46023 | D1: ='Как есть'!D1 -> 46387 | E1: <<<<<<-----Дата окончания проекта | I1: =IF(($C$7/12)>H11,#REF!+1,"") | J1: =IF(($C$7/12)>I11,I1+1,"") | K1: =IF(($C$7/12)>J11,J1+1,"") | L1: =IF(($C$7/12)>K11,K1+1,"") | M1: =IF(($C$7/12)>L11,L1+1,"")
B2: 3 | C2: <-- выбор между CPI (2) и WACC (3)
C3: 2021 | D3: 2022 | E3: 2023 | F3: 2024 | G3: 2025 | H3: 2026 | I3: 2027 | J3: 2028
A4: CPI | C4: 0.04 | D4: 0.04 | E4: 0.059 | F4: 0.0811 | G4: 0.07 | H4: 0.07 | I4: 0.07 | J4: 0.05
A5: WACC monthly | C5: =IFERROR(HLOOKUP(C14,WACC_monthly!1:2,2,0),'Как будет'!B5) -> 0.16 | D5: =IFERROR(HLOOKUP(D14,WACC_monthly!1:2,2,0),'Как будет'!C5) -> 0.16 | E5: =IFERROR(HLOOKUP(E14,WACC_monthly!1:2,2,0),'Как будет'!D5) -> 0.16 | F5: =IFERROR(HLOOKUP(F14,WACC_monthly!1:2,2,0),'Как будет'!E5) -> 0.16 | G5: =IFERROR(HLOOKUP(G14,WACC_monthly!1:2,2,0),'Как будет'!F5) -> 0.16 | H5: =IFERROR(HLOOKUP(H14,WACC_monthly!1:2,2,0),'Как будет'!G5) -> 0.16 | I5: =IFERROR(HLOOKUP(I14,WACC_monthly!1:2,2,0),'Как будет'!H5) -> 0.16 | J5: =IFERROR(HLOOKUP(J14,WACC_monthly!1:2,2,0),'Как будет'!I5) -> 0.16 | ... GT5: =IFERROR(HLOOKUP(GT14,WACC_monthly!1:2,2,0),'Как будет'!GS5) -> 0.16
A7: Срок полезного использования, мес | C7: ='Как есть'!C7 -> 60
C9: =C12 -> 2026 | D9: =D12 -> 2026 | E9: =E12 -> 2026 | F9: =F12 -> 2026 | G9: =G12 -> 2026 | H9: =H12 -> 2026 | I9: =I12 -> 2026 | J9: =J12 -> 2026 | ... GT9: =GT12
C10: =C113 -> 1 | D10: =D113 -> 0.98770784 | E10: =E113 -> 0.97556678 | F10: =F113 -> 0.96357495 | G10: =G113 -> 0.95173054 | H10: =H113 -> 0.94003171 | I10: =I113 -> 0.92847669 | J10: =J113 -> 0.91706371 | ... GT10: =GT113 -> 0.085324093
C11: 0 | D11: 1 | E11: =D11+1 -> 2 | F11: =E11+1 -> 3 | G11: =F11+1 -> 4 | H11: =G11+1 -> 5 | I11: =H11+1 -> 6 | J11: =I11+1 -> 7 | K11: =J11+1 -> 8 | L11: =K11+1 -> 9 | ... GT11: =GS11+1 -> 199
C12: =IFERROR(YEAR(C14),"") -> 2026 | D12: =IFERROR(YEAR(D14),"") -> 2026 | E12: =IFERROR(YEAR(E14),"") -> 2026 | F12: =IFERROR(YEAR(F14),"") -> 2026 | G12: =IFERROR(YEAR(G14),"") -> 2026 | H12: =IFERROR(YEAR(H14),"") -> 2026 | I12: =IFERROR(YEAR(I14),"") -> 2026 | J12: =IFERROR(YEAR(J14),"") -> 2026 | ... GT12: =IFERROR(YEAR(GT14),"")
C13: =IFERROR(MONTH(C14),"") -> 1 | D13: =IFERROR(MONTH(D14),"") -> 2 | E13: =IFERROR(MONTH(E14),"") -> 3 | F13: =IFERROR(MONTH(F14),"") -> 4 | G13: =IFERROR(MONTH(G14),"") -> 5 | H13: =IFERROR(MONTH(H14),"") -> 6 | I13: =IFERROR(MONTH(I14),"") -> 7 | J13: =IFERROR(MONTH(J14),"") -> 8 | ... GT13: =IFERROR(MONTH(GT14),"")
A14: TO BE | B14: Комментарии | C14: =DATE(YEAR(C1),MONTH(C1),1) -> 46023 | D14: =IF(D11>=$C$7,"",EDATE(C14,1)) -> 46054 | E14: =IF(E11>=$C$7,"",EDATE(D14,1)) -> 46082 | F14: =IF(F11>=$C$7,"",EDATE(E14,1)) -> 46113 | G14: =IF(G11>=$C$7,"",EDATE(F14,1)) -> 46143 | H14: =IF(H11>=$C$7,"",EDATE(G14,1)) -> 46174 | I14: =IF(I11>=$C$7,"",EDATE(H14,1)) -> 46204 | J14: =IF(J11>=$C$7,"",EDATE(I14,1)) -> 46235 | K14: =IF(K11>=$C$7,"",EDATE(J14,1)) -> 46266 | ... GT14: =IF(GT11>=$C$7,"",EDATE(GS14,1))
A15: Проектные расходы
A16: CАРЕХ | C16: =-SUM(C17:C24) -> -2011.36 | D16: =-SUM(D17:D24) -> -1048.44 | E16: =-SUM(E17:E24) -> -1520.3 | F16: =-SUM(F17:F24) -> -1283.74 | G16: =-SUM(G17:G24) -> -1014.92 | H16: =-SUM(H17:H24) -> -817.48 | I16: =-SUM(I17:I24) -> -817.48 | J16: =-SUM(J17:J24) -> -817.48 | ... GT16: =-SUM(GT17:GT24) -> 0
A17: Капитализируемый ФОТ | C17: 451.36 | D17: 488.44 | E17: 960.3 | F17: 723.74 | G17: 454.92 | H17: 257.48 | I17: 257.48 | J17: 257.48 | K17: 257.48 | L17: 257.48 | M17: 257.48 | N17: 164.1
A18: Консультационные услуги IT | C18: 560 | D18: 560 | E18: 560 | F18: 560 | G18: 560 | H18: 560 | I18: 560 | J18: 560 | K18: 560 | L18: 560 | M18: 560 | N18: 0
A19: Капитализируемый ФОТ
A20: ИТ оборудование | C20: 1000
A21: Нематериальные активы
A22: Консультационные услуги IT
A23: Складское оборудование
A24: Капитализируемый ФОТ
A25: Инвестиционный OPEX (вкл. Ранний старт) | C25: =-SUM(C26:C33) -> 0 | D25: =-SUM(D26:D33) -> 0 | E25: =-SUM(E26:E33) -> 0 | F25: =-SUM(F26:F33) -> 0 | G25: =-SUM(G26:G33) -> 0 | H25: =-SUM(H26:H33) -> 0 | I25: =-SUM(I26:I33) -> 0 | J25: =-SUM(J26:J33) -> 0 | ... GT25: =-SUM(GT26:GT33) -> 0
A26: Расходы на персонал
A27: Расходы на персонал_Ранний старт
A28: Консультационные, информационные услуги и страхование
A29: Расходы на персонал
A30: Расходы на персонал_Ранний старт
A31: Консультационные, информационные услуги и страхование
A32: Расходы на персонал
A33: Расходы на персонал_Ранний старт
A34: OPEX | C34: =-SUM(C35:C42) -> 0 | D34: =-SUM(D35:D42) -> 0 | E34: =-SUM(E35:E42) -> 0 | F34: =-SUM(F35:F42) -> 0 | G34: =-SUM(G35:G42) -> 0 | H34: =-SUM(H35:H42) -> 0 | I34: =-SUM(I35:I42) -> 0 | J34: =-SUM(J35:J42) -> 0 | ... GT34: =-SUM(GT35:GT42) -> 0
A35: Расходы на персонал
A36: Прочие расходы
A43: Постпроектные расходы
A44: CАРЕХ | C44: =-SUM(C45:C52) -> 0 | D44: =-SUM(D45:D52) -> 0 | E44: =-SUM(E45:E52) -> 0 | F44: =-SUM(F45:F52) -> 0 | G44: =-SUM(G45:G52) -> 0 | H44: =-SUM(H45:H52) -> 0 | I44: =-SUM(I45:I52) -> 0 | J44: =-SUM(J45:J52) -> 0 | ... GT44: =-SUM(GT45:GT52) -> 0
A45: Капитализируемый ФОТ
A46: ИТ оборудование
A47: Нематериальные активы
A48: Консультационные услуги IT
A49: Складское оборудование
A50: Капитализируемый ФОТ
A51: Складское оборудование
A52: Капитализируемый ФОТ
A53: Инвестиционный OPEX (вкл. Ранний старт) | C53: =-SUM(C54:C61) -> 0 | D53: =-SUM(D54:D61) -> 0 | E53: =-SUM(E54:E61) -> 0 | F53: =-SUM(F54:F61) -> 0 | G53: =-SUM(G54:G61) -> 0 | H53: =-SUM(H54:H61) -> 0 | I53: =-SUM(I54:I61) -> 0 | J53: =-SUM(J54:J61) -> 0 | ... GT53: =-SUM(GT54:GT61) -> 0
A54: Расходы на персонал
A55: Расходы на персонал_Ранний старт
A56: Консультационные, информационные услуги и страхование
A57: Расходы на персонал
A58: Расходы на персонал_Ранний старт
A59: Консультационные, информационные услуги и страхование
A60: Расходы на персонал
A61: Расходы на персонал_Ранний старт
A62: OPEX | C62: =-SUM(C63:C70) -> 0 | D62: =-SUM(D63:D70) -> 0 | E62: =-SUM(E63:E70) -> 0 | F62: =-SUM(F63:F70) -> 0 | G62: =-SUM(G63:G70) -> 0 | H62: =-SUM(H63:H70) -> 0 | I62: =-SUM(I63:I70) -> 0 | J62: =-SUM(J63:J70) -> 0 | ... GT62: =-SUM(GT63:GT70) -> 0
A63: Расходы на персонал
A64: Прочие расходы
A71: Экономический эффект
A72: САРЕХ | C72: =-SUM(C73:C80) -> 0 | D72: =-SUM(D73:D80) -> 0 | E72: =-SUM(E73:E80) -> 0 | F72: =-SUM(F73:F80) -> 0 | G72: =-SUM(G73:G80) -> 0 | H72: =-SUM(H73:H80) -> 0 | I72: =-SUM(I73:I80) -> 0 | J72: =-SUM(J73:J80) -> 0 | ... GT72: =-SUM(GT73:GT80) -> 0
A73: Капитализируемый ФОТ
A74: ИТ оборудование
A75: Нематериальные активы
A76: Консультационные услуги IT
A77: Складское оборудование
A78: Капитализируемый ФОТ
A79: Складское оборудование
A80: Капитализируемый ФОТ
A81: Инвестиционный OPEX (вкл. Ранний старт) | C81: =-SUM(C82:C89) -> 0 | D81: =-SUM(D82:D89) -> 0 | E81: =-SUM(E82:E89) -> 0 | F81: =-SUM(F82:F89) -> 0 | G81: =-SUM(G82:G89) -> 0 | H81: =-SUM(H82:H89) -> 0 | I81: =-SUM(I82:I89) -> 0 | J81: =-SUM(J82:J89) -> 0 | ... GT81: =-SUM(GT82:GT89) -> 0
A82: Расходы на персонал
A83: Расходы на персонал_Ранний старт
A84: Консультационные, информационные услуги и страхование
A85: Расходы на персонал
A86: Расходы на персонал_Ранний старт
A87: Консультационные, информационные услуги и страхование
A88: Расходы на персонал
A89: Расходы на персонал_Ранний старт
A90: ВЫРУЧКА | O90: =Приложения!G35 -> 446.24269 | P90: =Приложения!H35 -> 973.23371 | Q90: =Приложения!I35 -> 2191.2032 | R90: =Приложения!J35 -> 2108.8312 | S90: =Приложения!K35 -> 2283.0512 | T90: =Приложения!L35 -> 2958.1374 | U90: =Приложения!M35 -> 2329.9696 | V90: =Приложения!N35 -> 2580.6502 | ... BJ90: =Приложения!BB35 -> 3588.6139
A91: СЕБЕСТОИМОСТЬ | C91: =-SUM(C92:C95) -> 0 | D91: =-SUM(D92:D95) -> 0 | E91: =-SUM(E92:E95) -> 0 | F91: =-SUM(F92:F95) -> 0 | G91: =-SUM(G92:G95) -> 0 | H91: =-SUM(H92:H95) -> 0 | I91: =-SUM(I92:I95) -> 0 | J91: =-SUM(J92:J95) -> 0 | ... GT91: =-SUM(GT92:GT95) -> 0
A92: ='Как есть'!A92 -> Складская логистика
A93: ='Как есть'!A93 -> Затраты производства
A94: ='Как есть'!A94 -> Транспортная логистика
A95: ='Как есть'!A95 -> Потери
A96: Валовый доход | C96: =IF(C97=0,C90+C91,C97) -> 0 | D96: =IF(D97=0,D90+D91,D97) -> 0 | E96: =IF(E97=0,E90+E91,E97) -> 0 | F96: =IF(F97=0,F90+F91,F97) -> 0 | G96: =IF(G97=0,G90+G91,G97) -> 0 | H96: =IF(H97=0,H90+H91,H97) -> 0 | I96: =IF(I97=0,I90+I91,I97) -> 0 | J96: =IF(J97=0,J90+J91,J97) -> 0 | ... GT96: =IF(GT97=0,GT90+GT91,GT97) -> 0
A97: Коммерческая маржа | C97: =C98+C99 -> 0 | D97: =D98+D99 -> 0 | E97: =E98+E99 -> 0 | F97: =F98+F99 -> 0 | G97: =G98+G99 -> 0 | H97: =H98+H99 -> 0 | I97: =I98+I99 -> 0 | J97: =J98+J99 -> 0 | ... GT97: =GT98+GT99 -> 0
A98: Front Margin
A99: Back Margin
A100: OPEX | C100: =-SUMIFS(C101:C108,$A$101:$A$108,"<>Прочие доходы")+SUMIFS(C101:C108,$A$101:$A$108,"Прочие доходы") -> 0 | D100: =-SUMIFS(D101:D108,$A$101:$A$108,"<>Прочие доходы")+SUMIFS(D101:D108,$A$101:$A$108,"Прочие доходы") -> 0 | E100: =-SUMIFS(E101:E108,$A$101:$A$108,"<>Прочие доходы")+SUMIFS(E101:E108,$A$101:$A$108,"Прочие доходы") -> 0 | F100: =-SUMIFS(F101:F108,$A$101:$A$108,"<>Прочие доходы")+SUMIFS(F101:F108,$A$101:$A$108,"Прочие доходы") -> 0 | G100: =-SUMIFS(G101:G108,$A$101:$A$108,"<>Прочие доходы")+SUMIFS(G101:G108,$A$101:$A$108,"Прочие доходы") -> 0 | H100: =-SUMIFS(H101:H108,$A$101:$A$108,"<>Прочие доходы")+SUMIFS(H101:H108,$A$101:$A$108,"Прочие доходы") -> 0 | I100: =-SUMIFS(I101:I108,$A$101:$A$108,"<>Прочие доходы")+SUMIFS(I101:I108,$A$101:$A$108,"Прочие доходы") -> 0 | J100: =-SUMIFS(J101:J108,$A$101:$A$108,"<>Прочие доходы")+SUMIFS(J101:J108,$A$101:$A$108,"Прочие доходы") -> 0 | ... GT100: =-SUMIFS(GT101:GT108,$A$101:$A$108,"<>Прочие доходы")+SUMIFS(GT101:GT108,$A$101:$A$108,"Прочие доходы") -> 0
A101: ='Как есть'!A101 -> ФОТ штатного персонала
A102: ='Как есть'!A102 -> Расходы на аутстаф
A103: ='Как есть'!A103 -> Прочие расходы
A104: ='Как есть'!A104 -> Прочие доходы
A105: ='Как есть'!A105 -> Расходы на аренду
A106: ='Как есть'!A106 -> Реклама, маркетинг и PR
A107: ='Как есть'!A107 -> Коммунальные расходы и связь
A108: ='Как есть'!A108 -> Товарные запасы
A109: EBITDA | C109: =C96+C100+C34+C62 -> 0 | D109: =D96+D100+D34+D62 -> 0 | E109: =E96+E100+E34+E62 -> 0 | F109: =F96+F100+F34+F62 -> 0 | G109: =G96+G100+G34+G62 -> 0 | H109: =H96+H100+H34+H62 -> 0 | I109: =I96+I100+I34+I62 -> 0 | J109: =J96+J100+J34+J62 -> 0 | ... GT109: =GT96+GT100+GT34+GT62 -> 0
A111: Длина периода | C111: =1/12 -> 0.083333333 | D111: =1/12 -> 0.083333333 | E111: =1/12 -> 0.083333333 | F111: =1/12 -> 0.083333333 | G111: =1/12 -> 0.083333333 | H111: =1/12 -> 0.083333333 | I111: =1/12 -> 0.083333333 | J111: =1/12 -> 0.083333333 | ... GT111: =1/12 -> 0.083333333
A112: Дисконт-фактор по месяцам | C112: =1/(1+C5)^0 -> 1 | D112: =1/(1+D5)^D111 -> 0.98770784 | E112: =1/(1+E5)^E111 -> 0.98770784 | F112: =1/(1+F5)^F111 -> 0.98770784 | G112: =1/(1+G5)^G111 -> 0.98770784 | H112: =1/(1+H5)^H111 -> 0.98770784 | I112: =1/(1+I5)^I111 -> 0.98770784 | J112: =1/(1+J5)^J111 -> 0.98770784 | K112: =1/(1+K5)^K111 -> 0.98770784 | ... GT112: =1/(1+GT5)^GT111 -> 0.98770784
A113: Итоговый дисконт-фактор | C113: =C112 -> 1 | D113: =PRODUCT($C$112:C112)*D112 -> 0.98770784 | E113: =PRODUCT($C$112:D112)*E112 -> 0.97556678 | F113: =PRODUCT($C$112:E112)*F112 -> 0.96357495 | G113: =PRODUCT($C$112:F112)*G112 -> 0.95173054 | H113: =PRODUCT($C$112:G112)*H112 -> 0.94003171 | I113: =PRODUCT($C$112:H112)*I112 -> 0.92847669 | J113: =PRODUCT($C$112:I112)*J112 -> 0.91706371 | K113: =PRODUCT($C$112:J112)*K112 -> 0.90579101 | ... GT113: =PRODUCT($C$112:GS112)*GT112 -> 0.085324093

Sheet Доп.расчеты
B1: =IF(OR(B289<>0),1,0) -> 1 | C1: =IF(OR(C289<>0),1,0) -> 1 | D1: =IF(OR(D289<>0),1,0) -> 1 | E1: =IF(OR(E289<>0),1,0) -> 1 | F1: =IF(OR(F289<>0),1,0) -> 1 | G1: =IF(OR(G289<>0),1,0) -> 1 | H1: =IF(OR(H289<>0),1,0) -> 1 | I1: =IF(OR(I289<>0),1,0) -> 1 | ... GT1: =IF(OR(GT289<>0),1,0) -> 0
B2: =TEXT(B4,"МММГГ") -> янв26 | C2: =TEXT(C4,"МММГГ") -> февр26 | D2: =TEXT(D4,"МММГГ") -> март26 | E2: =TEXT(E4,"МММГГ") -> апр26 | F2: =TEXT(F4,"МММГГ") -> май26 | G2: =TEXT(G4,"МММГГ") -> июнь26 | H2: =TEXT(H4,"МММГГ") -> июль26 | I2: =TEXT(I4,"МММГГ") -> авг26 | ... GT2: =TEXT(GT4,"МММГГ") -> янв00
A3: Экономический эффект: | B3: ='Как есть'!C9 -> 2026 | C3: ='Как есть'!D9 -> 2026 | D3: ='Как есть'!E9 -> 2026 | E3: ='Как есть'!F9 -> 2026 | F3: ='Как есть'!G9 -> 2026 | G3: ='Как есть'!H9 -> 2026 | H3: ='Как есть'!I9 -> 2026 | I3: ='Как есть'!J9 -> 2026 | ... GT3: ='Как есть'!GU9 -> 0
A4: Себестоимость_Как есть | B4: ='Как есть'!C14 -> 46023 | C4: ='Как есть'!D14 -> 46054 | D4: ='Как есть'!E14 -> 46082 | E4: ='Как есть'!F14 -> 46113 | F4: ='Как есть'!G14 -> 46143 | G4: ='Как есть'!H14 -> 46174 | H4: ='Как есть'!I14 -> 46204 | I4: ='Как есть'!J14 -> 46235 | ... GT4: ='Как есть'!GU14 -> 0
A5: Складская логистика | B5: =SUMIF('Как есть'!$A:$A,Доп.расчеты!$A5,'Как есть'!C:C) -> 0 | C5: =SUMIF('Как есть'!$A:$A,Доп.расчеты!$A5,'Как есть'!D:D) -> 0 | D5: =SUMIF('Как есть'!$A:$A,Доп.расчеты!$A5,'Как есть'!E:E) -> 0 | E5: =SUMIF('Как есть'!$A:$A,Доп.расчеты!$A5,'Как есть'!F:F) -> 0 | F5: =SUMIF('Как есть'!$A:$A,Доп.расчеты!$A5,'Как есть'!G:G) -> 0 | G5: =SUMIF('Как есть'!$A:$A,Доп.расчеты!$A5,'Как есть'!H:H) -> 0 | H5: =SUMIF('Как есть'!$A:$A,Доп.расчеты!$A5,'Как есть'!I:I) -> 0 | I5: =SUMIF('Как есть'!$A:$A,Доп.расчеты!$A5,'Как есть'!J:J) -> 0 | J5: =SUMIF('Как есть'!$A:$A,Доп.расчеты!$A5,'Как есть'!K:K) -> 0 | K5: =SUMIF('Как есть'!$A:$A,Доп.расчеты!$A5,'Как есть'!L:L) -> 0 | L5: =SUMIF('Как есть'!$A:$A,Доп.расчеты!$A5,'Как есть'!M:M) -> 0 | M5: =SUMIF('Как есть'!$A:$A,Доп.расчеты!$A5,'Как есть'!N:N) -> 0 | N5: =SUMIF('Как есть'!$A:$A,Доп.расчеты!$A5,'Как есть'!O:O) -> 0 | O5: =SUMIF('Как есть'!$A:$A,Доп.расчеты!$A5,'Как есть'!P:P) -> 0 | P5: =SUMIF('Как есть'!$A:$A,Доп.расчеты!$A5,'Как есть'!Q:Q) -> 0 | Q5: =SUMIF('Как есть'!$A:$A,Доп.расчеты!$A5,'Как есть'!R:R) -> 0 | R5: =SUMIF('Как есть'!$A:$A,Доп.расчеты!$A5,'Как есть'!S:S) -> 0 | S5: =SUMIF('Как есть'!$A:$A,Доп.расчеты!$A5,'Как есть'!T:T) -> 0 | T5: =SUMIF('Как есть'!$A:$A,Доп.расчеты!$A5,'Как есть'!U:U) -> 0 | U5: =SUMIF('Как есть'!$A:$A,Доп.расчеты!$A5,'Как есть'!V:V) -> 0 | V5: =SUMIF('Как есть'!$A:$A,Доп.расчеты!$A5,'Как есть'!W:W) -> 0 | W5: =SUMIF('Как есть'!$A:$A,Доп.расчеты!$A5,'Как есть'!X:X) -> 0 | X5: =SUMIF('Как есть'!$A:$A,Доп.расчеты!$A5,'Как есть'!Y:Y) -> 0 | Y5: =SUMIF('Как есть'!$A:$A,Доп.расчеты!$A5,'Как есть'!Z:Z) -> 0 | Z5: =SUMIF('Как есть'!$A:$A,Доп.расчеты!$A5,'Как есть'!AA:AA) -> 0 | AA5: =SUMIF('Как есть'!$A:$A,Доп.расчеты!$A5,'Как есть'!AB:AB) -> 0 | AB5: =SUMIF('Как есть'!$A:$A,Доп.расчеты!$A5,'Как есть'!AC:AC) -> 0 | AC5: =SUMIF('Как есть'!$A:$A,Доп.расчеты!$A5,'Как есть'!AD:AD) -> 0 | AD5: =SUMIF('Как есть'!$A:$A,Доп.расчеты!$A5,'Как есть'!AE:AE) -> 0 | AE5: =SUMIF('Как есть'!$A:$A,Доп.расчеты!$A5,'Как есть'!AF:AF) -> 0 | AF5: =SUMIF('Как есть'!$A:$A,Доп.расчеты!$A5,'Как есть'!AG:AG) -> 0 | AG5: =SUMIF('Как есть'!$A:$A,Доп.расчеты!$A5,'Как есть'!AH:AH) -> 0 | AH5: =SUMIF('Как есть'!$A:$A,Доп.расчеты!$A5,'Как есть'!AI:AI) -> 0 | AI5: =SUMIF('Как есть'!$A:$A,Доп.расчеты!$A5,'Как есть'!AJ:AJ) -> 0 | AJ5: =SUMIF('Как есть'!$A:$A,Доп.расчеты!$A5,'Как есть'!AK:AK) -> 0 | AK5: =SUMIF('Как есть'!$A:$A,Доп.расчеты!$A5,'Как есть'!AL:AL) -> 0 | AL5: =SUMIF('Как есть'!$A:$A,Доп.расчеты!$A5,'Как есть'!AM:AM) -> 0 | AM5: =SUMIF('Как есть'!$A:$A,Доп.расчеты!$A5,'Как есть'!AN:AN) -> 0 | AN5: =SUMIF('Как есть'!$A:$A,Доп.расчеты!$A5,'Как есть'!AO:AO) -> 0 | AO5: =SUMIF('Как есть'!$A:$A,Доп.расчеты!$A5,'Как есть'!AP:AP) -> 0 | AP5: =SUMIF('Как есть'!$A:$A,Доп.расчеты!$A5,'Как есть'!AQ:AQ) -> 0 | AQ5: =SUMIF('Как есть'!$A:$A,Доп.расчеты!$A5,'Как есть'!AR:AR) -> 0 | AR5: =SUMIF('Как есть'!$A:$A,Доп.расчеты!$A5,'Как есть'!AS:AS) -> 0 | AS5: =SUMIF('Как есть'!$A:$A,Доп.расчеты!$A5,'Как есть'!AT:AT) -> 0 | AT5: =SUMIF('Как есть'!$A:$A,Доп.расчеты!$A5,'Как есть'!AU:AU) -> 0 | AU5: =SUMIF('Как есть'!$A:$A,Доп.расчеты!$A5,'Как есть'!AV:AV) -> 0 | AV5: =SUMIF('Как есть'!$A:$A,Доп.расчеты!$A5,'Как есть'!AW:AW) -> 0 | AW5: =SUMIF('Как есть'!$A:$A,Доп.расчеты!$A5,'Как есть'!AX:AX) -> 0 | AX5: =SUMIF('Как есть'!$A:$A,Доп.расчеты!$A5,'Как есть'!AY:AY) -> 0 | AY5: =SUMIF('Как есть'!$A:$A,Доп.расчеты!$A5,'Как есть'!AZ:AZ) -> 0 | AZ5: =SUMIF('Как есть'!$A:$A,Доп.расчеты!$A5,'Как есть'!BA:BA) -> 0 | BA5: =SUMIF('Как есть'!$A:$A,Доп.расчеты!$A5,'Как есть'!BB:BB) -> 0 | BB5: =SUMIF('Как есть'!$A:$A,Доп.расчеты!$A5,'Как есть'!BC:BC) -> 0 | BC5: =SUMIF('Как есть'!$A:$A,Доп.расчеты!$A5,'Как есть'!BD:BD) -> 0 | BD5: =SUMIF('Как есть'!$A:$A,Доп.расчеты!$A5,'Как есть'!BE:BE) -> 0 | BE5: =SUMIF('Как есть'!$A:$A,Доп.расчеты!$A5,'Как есть'!BF:BF) -> 0 | BF5: =SUMIF('Как есть'!$A:$A,Доп.расчеты!$A5,'Как есть'!BG:BG) -> 0 | BG5: =SUMIF('Как есть'!$A:$A,Доп.расчеты!$A5,'Как есть'!BH:BH) -> 0 | BH5: =SUMIF('Как есть'!$A:$A,Доп.расчеты!$A5,'Как есть'!BI:BI) -> 0 | BI5: =SUMIF('Как есть'!$A:$A,Доп.расчеты!$A5,'Как есть'!BJ:BJ) -> 0 | BJ5: =SUMIF('Как есть'!$A:$A,Доп.расчеты!$A5,'Как есть'!BK:BK) -> 0 | BK5: =SUMIF('Как есть'!$A:$A,Доп.расчеты!$A5,'Как есть'!BL:BL) -> 0 | BL5: =SUMIF('Как есть'!$A:$A,Доп.расчеты!$A5,'Как есть'!BM:BM) -> 0 | BM5: =SUMIF('Как есть'!$A:$A,Доп.расчеты!$A5,'Как есть'!BN:BN) -> 0 | BN5: =SUMIF('Как есть'!$A:$A,Доп.расчеты!$A5,'Как есть'!BO:BO) -> 0 | BO5: =SUMIF('Как есть'!$A:$A,Доп.расчеты!$A5,'Как есть'!BP:BP) -> 0 | BP5: =SUMIF('Как есть'!$A:$A,Доп.расчеты!$A5,'Как есть'!BQ:BQ) -> 0 | BQ5: =SUMIF('Как есть'!$A:$A,Доп.расчеты!$A5,'Как есть'!BR:BR) -> 0 | BR5: =SUMIF('Как есть'!$A:$A,Доп.расчеты!$A5,'Как есть'!BS:BS) -> 0 | BS5: =SUMIF('Как есть'!$A:$A,Доп.расчеты!$A5,'Как есть'!BT:BT) -> 0 | BT5: =SUMIF('Как есть'!$A:$A,Доп.расчеты!$A5,'Как есть'!BU:BU) -> 0 | BU5: =SUMIF('Как есть'!$A:$A,Доп.расчеты!$A5,'Как есть'!BV:BV) -> 0 | BV5: =SUMIF('Как есть'!$A:$A,Доп.расчеты!$A5,'Как есть'!BW:BW) -> 0 | BW5: =SUMIF('Как есть'!$A:$A,Доп.расчеты!$A5,'Как есть'!BX:BX) -> 0 | BX5: =SUMIF('Как есть'!$A:$A,Доп.расчеты!$A5,'Как есть'!BY:BY) -> 0 | BY5: =SUMIF('Как есть'!$A:$A,Доп.расчеты!$A5,'Как есть'!BZ:BZ) -> 0 | BZ5: =SUMIF('Как есть'!$A:$A,Доп.расчеты!$A5,'Как есть'!CA:CA) -> 0 | CA5: =SUMIF('Как есть'!$A:$A,Доп.расчеты!$A5,'Как есть'!CB:CB) -> 0 | CB5: =SUMIF('Как есть'!$A:$A,Доп.расчеты!$A5,'Как есть'!CC:CC) -> 0 | CC5: =SUMIF('Как есть'!$A:$A,Доп.расчеты!$A5,'Как есть'!CD:CD) -> 0 | CD5: =SUMIF('Как есть'!$A:$A,Доп.расчеты!$A5,'Как есть'!CE:CE) -> 0 | CE5: =SUMIF('Как есть'!$A:$A,Доп.расчеты!$A5,'Как есть'!CF:CF) -> 0 | CF5: =SUMIF('Как есть'!$A:$A,Доп.расчеты!$A5,'Как есть'!CG:CG) -> 0 | CG5: =SUMIF('Как есть'!$A:$A,Доп.расчеты!$A5,'Как есть'!CH:CH) -> 0 | CH5: =SUMIF('Как есть'!$A:$A,Доп.расчеты!$A5,'Как есть'!CI:CI) -> 0 | CI5: =SUMIF('Как есть'!$A:$A,Доп.расчеты!$A5,'Как есть'!CJ:CJ) -> 0 | CJ5: =SUMIF('Как есть'!$A:$A,Доп.расчеты!$A5,'Как есть'!CK:CK) -> 0 | CK5: =SUMIF('Как есть'!$A:$A,Доп.расчеты!$A5,'Как есть'!CL:CL) -> 0 | CL5: =SUMIF('Как есть'!$A:$A,Доп.расчеты!$A5,'Как есть'!CM:CM) -> 0 | CM5: =SUMIF('Как есть'!$A:$A,Доп.расчеты!$A5,'Как есть'!CN:CN) -> 0 | CN5: =SUMIF('Как есть'!$A:$A,Доп.расчеты!$A5,'Как есть'!CO:CO) -> 0 | CO5: =SUMIF('Как есть'!$A:$A,Доп.расчеты!$A5,'Как есть'!CP:CP) -> 0 | CP5: =SUMIF('Как есть'!$A:$A,Доп.расчеты!$A5,'Как есть'!CQ:CQ) -> 0 | CQ5: =SUMIF('Как есть'!$A:$A,Доп.расчеты!$A5,'Как есть'!CR:CR) -> 0 | CR5: =SUMIF('Как есть'!$A:$A,Доп.расчеты!$A5,'Как есть'!CS:CS) -> 0 | CS5: =SUMIF('Как есть'!$A:$A,Доп.расчеты!$A5,'Как есть'!CT:CT) -> 0 | CT5: =SUMIF('Как есть'!$A:$A,Доп.расчеты!$A5,'Как есть'!CU:CU) -> 0 | CU5: =SUMIF('Как есть'!$A:$A,Доп.расчеты!$A5,'Как есть'!CV:CV) -> 0 | CV5: =SUMIF('Как есть'!$A:$A,Доп.расчеты!$A5,'Как есть'!CW:CW) -> 0 | CW5: =SUMIF('Как есть'!$A:$A,Доп.расчеты!$A5,'Как есть'!CX:CX) -> 0 | CX5: =SUMIF('Как есть'!$A:$A,Доп.расчеты!$A5,'Как есть'!CY:CY) -> 0 | CY5: =SUMIF('Как есть'!$A:$A,Доп.расчеты!$A5,'Как есть'!CZ:CZ) -> 0 | CZ5: =SUMIF('Как есть'!$A:$A,Доп.расчеты!$A5,'Как есть'!DA:DA) -> 0 | DA5: =SUMIF('Как есть'!$A:$A,Доп.расчеты!$A5,'Как есть'!DB:DB) -> 0 | DB5: =SUMIF('Как есть'!$A:$A,Доп.расчеты!$A5,'Как есть'!DC:DC) -> 0 | DC5: =SUMIF('Как есть'!$A:$A,Доп.расчеты!$A5,'Как есть'!DD:DD) -> 0 | DD5: =SUMIF('Как есть'!$A:$A,Доп.расчеты!$A5,'Как есть'!DE:DE) -> 0 | DE5: =SUMIF('Как есть'!$A:$A,Доп.расчеты!$A5,'Как есть'!DF:DF) -> 0 | DF5: =SUMIF('Как есть'!$A:$A,Доп.расчеты!$A5,'Как есть'!DG:DG) -> 0 | DG5: =SUMIF('Как есть'!$A:$A,Доп.расчеты!$A5,'Как есть'!DH:DH) -> 0 | DH5: =SUMIF('Как есть'!$A:$A,Доп.расчеты!$A5,'Как есть'!DI:DI) -> 0 | DI5: =SUMIF('Как есть'!$A:$A,Доп.расчеты!$A5,'Как есть'!DJ:DJ) -> 0 | DJ5: =SUMIF('Как есть'!$A:$A,Доп.расчеты!$A5,'Как есть'!DK:DK) -> 0 | DK5: =SUMIF('Как есть'!$A:$A,Доп.расчеты!$A5,'Как есть'!DL:DL) -> 0 | DL5: =SUMIF('Как есть'!$A:$A,Доп.расчеты!$A5,'Как есть'!DM:DM) -> 0 | DM5: =SUMIF('Как есть'!$A:$A,Доп.расчеты!$A5,'Как есть'!DN:DN) -> 0 | DN5: =SUMIF('Как есть'!$A:$A,Доп.расчеты!$A5,'Как есть'!DO:DO) -> 0 | DO5: =SUMIF('Как есть'!$A:$A,Доп.расчеты!$A5,'Как есть'!DP:DP) -> 0 | DP5: =SUMIF('Как есть'!$A:$A,Доп.расчеты!$A5,'Как есть'!DQ:DQ) -> 0 | DQ5: =SUMIF('Как есть'!$A:$A,Доп.расчеты!$A5,'Как есть'!DR:DR) -> 0 | DR5: =SUMIF('Как есть'!$A:$A,Доп.расчеты!$A5,'Как есть'!DS:DS) -> 0 | DS5: =SUMIF('Как есть'!$A:$A,Доп.расчеты!$A5,'Как есть'!DT:DT) -> 0 | DT5: =SUMIF('Как есть'!$A:$A,Доп.расчеты!$A5,'Как есть'!DU:DU) -> 0 | DU5: =SUMIF('Как есть'!$A:$A,Доп.расчеты!$A5,'Как есть'!DV:DV) -> 0 | DV5: =SUMIF('Как есть'!$A:$A,Доп.расчеты!$A5,'Как есть'!DW:DW) -> 0 | DW5: =SUMIF('Как есть'!$A:$A,Доп.расчеты!$A5,'Как есть'!DX:DX) -> 0 | DX5: =SUMIF('Как есть'!$A:$A,Доп.расчеты!$A5,'Как есть'!DY:DY) -> 0 | DY5: =SUMIF('Как есть'!$A:$A,Доп.расчеты!$A5,'Как есть'!DZ:DZ) -> 0 | DZ5: =SUMIF('Как есть'!$A:$A,Доп.расчеты!$A5,'Как есть'!EA:EA) -> 0 | EA5: =SUMIF('Как есть'!$A:$A,Доп.расчеты!$A5,'Как есть'!EB:EB) -> 0 | EB5: =SUMIF('Как есть'!$A:$A,Доп.расчеты!$A5,'Как есть'!EC:EC) -> 0 | EC5: =SUMIF('Как есть'!$A:$A,Доп.расчеты!$A5,'Как есть'!ED:ED) -> 0 | ED5: =SUMIF('Как есть'!$A:$A,Доп.расчеты!$A5,'Как есть'!EE:EE) -> 0 | EE5: =SUMIF('Как есть'!$A:$A,Доп.расчеты!$A5,'Как есть'!EF:EF) -> 0 | EF5: =SUMIF('Как есть'!$A:$A,Доп.расчеты!$A5,'Как есть'!EG:EG) -> 0 | EG5: =SUMIF('Как есть'!$A:$A,Доп.расчеты!$A5,'Как есть'!EH:EH) -> 0 | EH5: =SUMIF('Как есть'!$A:$A,Доп.расчеты!$A5,'Как есть'!EI:EI) -> 0 | EI5: =SUMIF('Как есть'!$A:$A,Доп.расчеты!$A5,'Как есть'!EJ:EJ) -> 0 | EJ5: =SUMIF('Как есть'!$A:$A,Доп.расчеты!$A5,'Как есть'!EK:EK) -> 0 | EK5: =SUMIF('Как есть'!$A:$A,Доп.расчеты!$A5,'Как есть'!EL:EL) -> 0 | EL5: =SUMIF('Как есть'!$A:$A,Доп.расчеты!$A5,'Как есть'!EM:EM) -> 0 | EM5: =SUMIF('Как есть'!$A:$A,Доп.расчеты!$A5,'Как есть'!EN:EN) -> 0 | EN5: =SUMIF('Как есть'!$A:$A,Доп.расчеты!$A5,'Как есть'!EO:EO) -> 0 | EO5: =SUMIF('Как есть'!$A:$A,Доп.расчеты!$A5,'Как есть'!EP:EP) -> 0 | EP5: =SUMIF('Как есть'!$A:$A,Доп.расчеты!$A5,'Как есть'!EQ:EQ) -> 0 | EQ5: =SUMIF('Как есть'!$A:$A,Доп.расчеты!$A5,'Как есть'!ER:ER) -> 0 | ER5: =SUMIF('Как есть'!$A:$A,Доп.расчеты!$A5,'Как есть'!ES:ES) -> 0 | ES5: =SUMIF('Как есть'!$A:$A,Доп.расчеты!$A5,'Как есть'!ET:ET) -> 0 | ET5: =SUMIF('Как есть'!$A:$A,Доп.расчеты!$A5,'Как есть'!EU:EU) -> 0 | EU5: =SUMIF('Как есть'!$A:$A,Доп.расчеты!$A5,'Как есть'!EV:EV) -> 0 | EV5: =SUMIF('Как есть'!$A:$A,Доп.расчеты!$A5,'Как есть'!EW:EW) -> 0 | EW5: =SUMIF('Как есть'!$A:$A,Доп.расчеты!$A5,'Как есть'!EX:EX) -> 0 | EX5: =SUMIF('Как есть'!$A:$A,Доп.расчеты!$A5,'Как есть'!EY:EY) -> 0 | EY5: =SUMIF('Как есть'!$A:$A,Доп.расчеты!$A5,'Как есть'!EZ:EZ) -> 0 | EZ5: =SUMIF('Как есть'!$A:$A,Доп.расчеты!$A5,'Как есть'!FA:FA) -> 0 | FA5: =SUMIF('Как есть'!$A:$A,Доп.расчеты!$A5,'Как есть'!FB:FB) -> 0 | FB5: =SUMIF('Как есть'!$A:$A,Доп.расчеты!$A5,'Как есть'!FC:FC) -> 0 | FC5: =SUMIF('Как есть'!$A:$A,Доп.расчеты!$A5,'Как есть'!FD:FD) -> 0 | FD5: =SUMIF('Как есть'!$A:$A,Доп.расчеты!$A5,'Как есть'!FE:FE) -> 0 | FE5: =SUMIF('Как есть'!$A:$A,Доп.расчеты!$A5,'Как есть'!FF:FF) -> 0 | FF5: =SUMIF('Как есть'!$A:$A,Доп.расчеты!$A5,'Как есть'!FG:FG) -> 0 | FG5: =SUMIF('Как есть'!$A:$A,Доп.расчеты!$A5,'Как есть'!FH:FH) -> 0 | FH5: =SUMIF('Как есть'!$A:$A,Доп.расчеты!$A5,'Как есть'!FI:FI) -> 0 | FI5: =SUMIF('Как есть'!$A:$A,Доп.расчеты!$A5,'Как есть'!FJ:FJ) -> 0 | FJ5: =SUMIF('Как есть'!$A:$A,Доп.расчеты!$A5,'Как есть'!FK:FK) -> 0 | FK5: =SUMIF('Как есть'!$A:$A,Доп.расчеты!$A5,'Как есть'!FL:FL) -> 0 | FL5: =SUMIF('Как есть'!$A:$A,Доп.расчеты!$A5,'Как есть'!FM:FM) -> 0 | FM5: =SUMIF('Как есть'!$A:$A,Доп.расчеты!$A5,'Как есть'!FN:FN) -> 0 | FN5: =SUMIF('Как есть'!$A:$A,Доп.расчеты!$A5,'Как есть'!FO:FO) -> 0 | FO5: =SUMIF('Как есть'!$A:$A,Доп.расчеты!$A5,'Как есть'!FP:FP) -> 0 | FP5: =SUMIF('Как есть'!$A:$A,Доп.расчеты!$A5,'Как есть'!FQ:FQ) -> 0 | FQ5: =SUMIF('Как есть'!$A:$A,Доп.расчеты!$A5,'Как есть'!FR:FR) -> 0 | FR5: =SUMIF('Как есть'!$A:$A,Доп.расчеты!$A5,'Как есть'!FS:FS) -> 0 | FS5: =SUMIF('Как есть'!$A:$A,Доп.расчеты!$A5,'Как есть'!FT:FT) -> 0 | FT5: =SUMIF('Как есть'!$A:$A,Доп.расчеты!$A5,'Как есть'!FU:FU) -> 0 | FU5: =SUMIF('Как есть'!$A:$A,Доп.расчеты!$A5,'Как есть'!FV:FV) -> 0 | FV5: =SUMIF('Как есть'!$A:$A,Доп.расчеты!$A5,'Как есть'!FW:FW) -> 0 | FW5: =SUMIF('Как есть'!$A:$A,Доп.расчеты!$A5,'Как есть'!FX:FX) -> 0 | FX5: =SUMIF('Как есть'!$A:$A,Доп.расчеты!$A5,'Как есть'!FY:FY) -> 0 | FY5: =SUMIF('Как есть'!$A:$A,Доп.расчеты!$A5,'Как есть'!FZ:FZ) -> 0 | FZ5: =SUMIF('Как есть'!$A:$A,Доп.расчеты!$A5,'Как есть'!GA:GA) -> 0 | GA5: =SUMIF('Как есть'!$A:$A,Доп.расчеты!$A5,'Как есть'!GB:GB) -> 0 | GB5: =SUMIF('Как есть'!$A:$A,Доп.расчеты!$A5,'Как есть'!GC:GC) -> 0 | GC5: =SUMIF('Как есть'!$A:$A,Доп.расчеты!$A5,'Как есть'!GD:GD) -> 0 | GD5: =SUMIF('Как есть'!$A:$A,Доп.расчеты!$A5,'Как есть'!GE:GE) -> 0 | GE5: =SUMIF('Как есть'!$A:$A,Доп.расчеты!$A5,'Как есть'!GF:GF) -> 0 | GF5: =SUMIF('Как есть'!$A:$A,Доп.расчеты!$A5,'Как есть'!GG:GG) -> 0 | GG5: =SUMIF('Как есть'!$A:$A,Доп.расчеты!$A5,'Как есть'!GH:GH) -> 0 | GH5: =SUMIF('Как есть'!$A:$A,Доп.расчеты!$A5,'Как есть'!GI:GI) -> 0 | GI5: =SUMIF('Как есть'!$A:$A,Доп.расчеты!$A5,'Как есть'!GJ:GJ) -> 0 | GJ5: =SUMIF('Как есть'!$A:$A,Доп.расчеты!$A5,'Как есть'!GK:GK) -> 0 | GK5: =SUMIF('Как есть'!$A:$A,Доп.расчеты!$A5,'Как есть'!GL:GL) -> 0 | GL5: =SUMIF('Как есть'!$A:$A,Доп.расчеты!$A5,'Как есть'!GM:GM) -> 0 | GM5: =SUMIF('Как есть'!$A:$A,Доп.расчеты!$A5,'Как есть'!GN:GN) -> 0 | GN5: =SUMIF('Как есть'!$A:$A,Доп.расчеты!$A5,'Как есть'!GO:GO) -> 0 | GO5: =SUMIF('Как есть'!$A:$A,Доп.расчеты!$A5,'Как есть'!GP:GP) -> 0 | GP5: =SUMIF('Как есть'!$A:$A,Доп.расчеты!$A5,'Как есть'!GQ:GQ) -> 0 | GQ5: =SUMIF('Как есть'!$A:$A,Доп.расчеты!$A5,'Как есть'!GR:GR) -> 0 | GR5: =SUMIF('Как есть'!$A:$A,Доп.расчеты!$A5,'Как есть'!GS:GS) -> 0 | GS5: =SUMIF('Как есть'!$A:$A,Доп.расчеты!$A5,'Как есть'!GT:GT) -> 0 | GT5: =SUMIF('Как есть'!$A:$A,Доп.расчеты!$A5,'Как есть'!GU:GU) -> 0
A6: Транспортная логистика | B6: =SUMIF('Как есть'!$A:$A,Доп.расчеты!$A6,'Как есть'!C:C) -> 0 | C6: =SUMIF('Как есть'!$A:$A,Доп.расчеты!$A6,'Как есть'!D:D) -> 0 | D6: =SUMIF('Как есть'!$A:$A,Доп.расчеты!$A6,'Как есть'!E:E) -> 0 | E6: =SUMIF('Как есть'!$A:$A,Доп.расчеты!$A6,'Как есть'!F:F) -> 0 | F6: =SUMIF('Как есть'!$A:$A,Доп.расчеты!$A6,'Как есть'!G:G) -> 0 | G6: =SUMIF('Как есть'!$A:$A,Доп.расчеты!$A6,'Как есть'!H:H) -> 0 | H6: =SUMIF('Как есть'!$A:$A,Доп.расчеты!$A6,'Как есть'!I:I) -> 0 | I6: =SUMIF('Как есть'!$A:$A,Доп.расчеты!$A6,'Как есть'!J:J) -> 0 | J6: =SUMIF('Как есть'!$A:$A,Доп.расчеты!$A6,'Как есть'!K:K) -> 0 | K6: =SUMIF('Как есть'!$A:$A,Доп.расчеты!$A6,'Как есть'!L:L) -> 0 | L6: =SUMIF('Как есть'!$A:$A,Доп.расчеты!$A6,'Как есть'!M:M) -> 0 | M6: =SUMIF('Как есть'!$A:$A,Доп.расчеты!$A6,'Как есть'!N:N) -> 0 | N6: =SUMIF('Как есть'!$A:$A,Доп.расчеты!$A6,'Как есть'!O:O) -> 0 | O6: =SUMIF('Как есть'!$A:$A,Доп.расчеты!$A6,'Как есть'!P:P) -> 0 | P6: =SUMIF('Как есть'!$A:$A,Доп.расчеты!$A6,'Как есть'!Q:Q) -> 0 | Q6: =SUMIF('Как есть'!$A:$A,Доп.расчеты!$A6,'Как есть'!R:R) -> 0 | R6: =SUMIF('Как есть'!$A:$A,Доп.расчеты!$A6,'Как есть'!S:S) -> 0 | S6: =SUMIF('Как есть'!$A:$A,Доп.расчеты!$A6,'Как есть'!T:T) -> 0 | T6: =SUMIF('Как есть'!$A:$A,Доп.расчеты!$A6,'Как есть'!U:U) -> 0 | U6: =SUMIF('Как есть'!$A:$A,Доп.расчеты!$A6,'Как есть'!V:V) -> 0 | V6: =SUMIF('Как есть'!$A:$A,Доп.расчеты!$A6,'Как есть'!W:W) -> 0 | W6: =SUMIF('Как есть'!$A:$A,Доп.расчеты!$A6,'Как есть'!X:X) -> 0 | X6: =SUMIF('Как есть'!$A:$A,Доп.расчеты!$A6,'Как есть'!Y:Y) -> 0 | Y6: =SUMIF('Как есть'!$A:$A,Доп.расчеты!$A6,'Как есть'!Z:Z) -> 0 | Z6: =SUMIF('Как есть'!$A:$A,Доп.расчеты!$A6,'Как есть'!AA:AA) -> 0 | AA6: =SUMIF('Как есть'!$A:$A,Доп.расчеты!$A6,'Как есть'!AB:AB) -> 0 | AB6: =SUMIF('Как есть'!$A:$A,Доп.расчеты!$A6,'Как есть'!AC:AC) -> 0 | AC6: =SUMIF('Как есть'!$A:$A,Доп.расчеты!$A6,'Как есть'!AD:AD) -> 0 | AD6: =SUMIF('Как есть'!$A:$A,Доп.расчеты!$A6,'Как есть'!AE:AE) -> 0 | AE6: =SUMIF('Как есть'!$A:$A,Доп.расчеты!$A6,'Как есть'!AF:AF) -> 0 | AF6: =SUMIF('Как есть'!$A:$A,Доп.расчеты!$A6,'Как есть'!AG:AG) -> 0 | AG6: =SUMIF('Как есть'!$A:$A,Доп.расчеты!$A6,'Как есть'!AH:AH) -> 0 | AH6: =SUMIF('Как есть'!$A:$A,Доп.расчеты!$A6,'Как есть'!AI:AI) -> 0 | AI6: =SUMIF('Как есть'!$A:$A,Доп.расчеты!$A6,'Как есть'!AJ:AJ) -> 0 | AJ6: =SUMIF('Как есть'!$A:$A,Доп.расчеты!$A6,'Как есть'!AK:AK) -> 0 | AK6: =SUMIF('Как есть'!$A:$A,Доп.расчеты!$A6,'Как есть'!AL:AL) -> 0 | AL6: =SUMIF('Как есть'!$A:$A,Доп.расчеты!$A6,'Как есть'!AM:AM) -> 0 | AM6: =SUMIF('Как есть'!$A:$A,Доп.расчеты!$A6,'Как есть'!AN:AN) -> 0 | AN6: =SUMIF('Как есть'!$A:$A,Доп.расчеты!$A6,'Как есть'!AO:AO) -> 0 | AO6: =SUMIF('Как есть'!$A:$A,Доп.расчеты!$A6,'Как есть'!AP:AP) -> 0 | AP6: =SUMIF('Как есть'!$A:$A,Доп.расчеты!$A6,'Как есть'!AQ:AQ) -> 0 | AQ6: =SUMIF('Как есть'!$A:$A,Доп.расчеты!$A6,'Как есть'!AR:AR) -> 0 | AR6: =SUMIF('Как есть'!$A:$A,Доп.расчеты!$A6,'Как есть'!AS:AS) -> 0 | AS6: =SUMIF('Как есть'!$A:$A,Доп.расчеты!$A6,'Как есть'!AT:AT) -> 0 | AT6: =SUMIF('Как есть'!$A:$A,Доп.расчеты!$A6,'Как есть'!AU:AU) -> 0 | AU6: =SUMIF('Как есть'!$A:$A,Доп.расчеты!$A6,'Как есть'!AV:AV) -> 0 | AV6: =SUMIF('Как есть'!$A:$A,Доп.расчеты!$A6,'Как есть'!AW:AW) -> 0 | AW6: =SUMIF('Как есть'!$A:$A,Доп.расчеты!$A6,'Как есть'!AX:AX) -> 0 | AX6: =SUMIF('Как есть'!$A:$A,Доп.расчеты!$A6,'Как есть'!AY:AY) -> 0 | AY6: =SUMIF('Как есть'!$A:$A,Доп.расчеты!$A6,'Как есть'!AZ:AZ) -> 0 | AZ6: =SUMIF('Как есть'!$A:$A,Доп.расчеты!$A6,'Как есть'!BA:BA) -> 0 | BA6: =SUMIF('Как есть'!$A:$A,Доп.расчеты!$A6,'Как есть'!BB:BB) -> 0 | BB6: =SUMIF('Как есть'!$A:$A,Доп.расчеты!$A6,'Как есть'!BC:BC) -> 0 | BC6: =SUMIF('Как есть'!$A:$A,Доп.расчеты!$A6,'Как есть'!BD:BD) -> 0 | BD6: =SUMIF('Как есть'!$A:$A,Доп.расчеты!$A6,'Как есть'!BE:BE) -> 0 | BE6: =SUMIF('Как есть'!$A:$A,Доп.расчеты!$A6,'Как есть'!BF:BF) -> 0 | BF6: =SUMIF('Как есть'!$A:$A,Доп.расчеты!$A6,'Как есть'!BG:BG) -> 0 | BG6: =SUMIF('Как есть'!$A:$A,Доп.расчеты!$A6,'Как есть'!BH:BH) -> 0 | BH6: =SUMIF('Как есть'!$A:$A,Доп.расчеты!$A6,'Как есть'!BI:BI) -> 0 | BI6: =SUMIF('Как есть'!$A:$A,Доп.расчеты!$A6,'Как есть'!BJ:BJ) -> 0 | BJ6: =SUMIF('Как есть'!$A:$A,Доп.расчеты!$A6,'Как есть'!BK:BK) -> 0 | BK6: =SUMIF('Как есть'!$A:$A,Доп.расчеты!$A6,'Как есть'!BL:BL) -> 0 | BL6: =SUMIF('Как есть'!$A:$A,Доп.расчеты!$A6,'Как есть'!BM:BM) -> 0 | BM6: =SUMIF('Как есть'!$A:$A,Доп.расчеты!$A6,'Как есть'!BN:BN) -> 0 | BN6: =SUMIF('Как есть'!$A:$A,Доп.расчеты!$A6,'Как есть'!BO:BO) -> 0 | BO6: =SUMIF('Как есть'!$A:$A,Доп.расчеты!$A6,'Как есть'!BP:BP) -> 0 | BP6: =SUMIF('Как есть'!$A:$A,Доп.расчеты!$A6,'Как есть'!BQ:BQ) -> 0 | BQ6: =SUMIF('Как есть'!$A:$A,Доп.расчеты!$A6,'Как есть'!BR:BR) -> 0 | BR6: =SUMIF('Как есть'!$A:$A,Доп.расчеты!$A6,'Как есть'!BS:BS) -> 0 | BS6: =SUMIF('Как есть'!$A:$A,Доп.расчеты!$A6,'Как есть'!BT:BT) -> 0 | BT6: =SUMIF('Как есть'!$A:$A,Доп.расчеты!$A6,'Как есть'!BU:BU) -> 0 | BU6: =SUMIF('Как есть'!$A:$A,Доп.расчеты!$A6,'Как есть'!BV:BV) -> 0 | BV6: =SUMIF('Как есть'!$A:$A,Доп.расчеты!$A6,'Как есть'!BW:BW) -> 0 | BW6: =SUMIF('Как есть'!$A:$A,Доп.расчеты!$A6,'Как есть'!BX:BX) -> 0 | BX6: =SUMIF('Как есть'!$A:$A,Доп.расчеты!$A6,'Как есть'!BY:BY) -> 0 | BY6: =SUMIF('Как есть'!$A:$A,Доп.расчеты!$A6,'Как есть'!BZ:BZ) -> 0 | BZ6: =SUMIF('Как есть'!$A:$A,Доп.расчеты!$A6,'Как есть'!CA:CA) -> 0 | CA6: =SUMIF('Как есть'!$A:$A,Доп.расчеты!$A6,'Как есть'!CB:CB) -> 0 | CB6: =SUMIF('Как есть'!$A:$A,Доп.расчеты!$A6,'Как есть'!CC:CC) -> 0 | CC6: =SUMIF('Как есть'!$A:$A,Доп.расчеты!$A6,'Как есть'!CD:CD) -> 0 | CD6: =SUMIF('Как есть'!$A:$A,Доп.расчеты!$A6,'Как есть'!CE:CE) -> 0 | CE6: =SUMIF('Как есть'!$A:$A,Доп.расчеты!$A6,'Как есть'!CF:CF) -> 0 | CF6: =SUMIF('Как есть'!$A:$A,Доп.расчеты!$A6,'Как есть'!CG:CG) -> 0 | CG6: =SUMIF('Как есть'!$A:$A,Доп.расчеты!$A6,'Как есть'!CH:CH) -> 0 | CH6: =SUMIF('Как есть'!$A:$A,Доп.расчеты!$A6,'Как есть'!CI:CI) -> 0 | CI6: =SUMIF('Как есть'!$A:$A,Доп.расчеты!$A6,'Как есть'!CJ:CJ) -> 0 | CJ6: =SUMIF('Как есть'!$A:$A,Доп.расчеты!$A6,'Как есть'!CK:CK) -> 0 | CK6: =SUMIF('Как есть'!$A:$A,Доп.расчеты!$A6,'Как есть'!CL:CL) -> 0 | CL6: =SUMIF('Как есть'!$A:$A,Доп.расчеты!$A6,'Как есть'!CM:CM) -> 0 | CM6: =SUMIF('Как есть'!$A:$A,Доп.расчеты!$A6,'Как есть'!CN:CN) -> 0 | CN6: =SUMIF('Как есть'!$A:$A,Доп.расчеты!$A6,'Как есть'!CO:CO) -> 0 | CO6: =SUMIF('Как есть'!$A:$A,Доп.расчеты!$A6,'Как есть'!CP:CP) -> 0 | CP6: =SUMIF('Как есть'!$A:$A,Доп.расчеты!$A6,'Как есть'!CQ:CQ) -> 0 | CQ6: =SUMIF('Как есть'!$A:$A,Доп.расчеты!$A6,'Как есть'!CR:CR) -> 0 | CR6: =SUMIF('Как есть'!$A:$A,Доп.расчеты!$A6,'Как есть'!CS:CS) -> 0 | CS6: =SUMIF('Как есть'!$A:$A,Доп.расчеты!$A6,'Как есть'!CT:CT) -> 0 | CT6: =SUMIF('Как есть'!$A:$A,Доп.расчеты!$A6,'Как есть'!CU:CU) -> 0 | CU6: =SUMIF('Как есть'!$A:$A,Доп.расчеты!$A6,'Как есть'!CV:CV) -> 0 | CV6: =SUMIF('Как есть'!$A:$A,Доп.расчеты!$A6,'Как есть'!CW:CW) -> 0 | CW6: =SUMIF('Как есть'!$A:$A,Доп.расчеты!$A6,'Как есть'!CX:CX) -> 0 | CX6: =SUMIF('Как есть'!$A:$A,Доп.расчеты!$A6,'Как есть'!CY:CY) -> 0 | CY6: =SUMIF('Как есть'!$A:$A,Доп.расчеты!$A6,'Как есть'!CZ:CZ) -> 0 | CZ6: =SUMIF('Как есть'!$A:$A,Доп.расчеты!$A6,'Как есть'!DA:DA) -> 0 | DA6: =SUMIF('Как есть'!$A:$A,Доп.расчеты!$A6,'Как есть'!DB:DB) -> 0 | DB6: =SUMIF('Как есть'!$A:$A,Доп.расчеты!$A6,'Как есть'!DC:DC) -> 0 | DC6: =SUMIF('Как есть'!$A:$A,Доп.расчеты!$A6,'Как есть'!DD:DD) -> 0 | DD6: =SUMIF('Как есть'!$A:$A,Доп.расчеты!$A6,'Как есть'!DE:DE) -> 0 | DE6: =SUMIF('Как есть'!$A:$A,Доп.расчеты!$A6,'Как есть'!DF:DF) -> 0 | DF6: =SUMIF('Как есть'!$A:$A,Доп.расчеты!$A6,'Как есть'!DG:DG) -> 0 | DG6: =SUMIF('Как есть'!$A:$A,Доп.расчеты!$A6,'Как есть'!DH:DH) -> 0 | DH6: =SUMIF('Как есть'!$A:$A,Доп.расчеты!$A6,'Как есть'!DI:DI) -> 0 | DI6: =SUMIF('Как есть'!$A:$A,Доп.расчеты!$A6,'Как есть'!DJ:DJ) -> 0 | DJ6: =SUMIF('Как есть'!$A:$A,Доп.расчеты!$A6,'Как есть'!DK:DK) -> 0 | DK6: =SUMIF('Как есть'!$A:$A,Доп.расчеты!$A6,'Как есть'!DL:DL) -> 0 | DL6: =SUMIF('Как есть'!$A:$A,Доп.расчеты!$A6,'Как есть'!DM:DM) -> 0 | DM6: =SUMIF('Как есть'!$A:$A,Доп.расчеты!$A6,'Как есть'!DN:DN) -> 0 | DN6: =SUMIF('Как есть'!$A:$A,Доп.расчеты!$A6,'Как есть'!DO:DO) -> 0 | DO6: =SUMIF('Как есть'!$A:$A,Доп.расчеты!$A6,'Как есть'!DP:DP) -> 0 | DP6: =SUMIF('Как есть'!$A:$A,Доп.расчеты!$A6,'Как есть'!DQ:DQ) -> 0 | DQ6: =SUMIF('Как есть'!$A:$A,Доп.расчеты!$A6,'Как есть'!DR:DR) -> 0 | DR6: =SUMIF('Как есть'!$A:$A,Доп.расчеты!$A6,'Как есть'!DS:DS) -> 0 | DS6: =SUMIF('Как есть'!$A:$A,Доп.расчеты!$A6,'Как есть'!DT:DT) -> 0 | DT6: =SUMIF('Как есть'!$A:$A,Доп.расчеты!$A6,'Как есть'!DU:DU) -> 0 | DU6: =SUMIF('Как есть'!$A:$A,Доп.расчеты!$A6,'Как есть'!DV:DV) -> 0 | DV6: =SUMIF('Как есть'!$A:$A,Доп.расчеты!$A6,'Как есть'!DW:DW) -> 0 | DW6: =SUMIF('Как есть'!$A:$A,Доп.расчеты!$A6,'Как есть'!DX:DX) -> 0 | DX6: =SUMIF('Как есть'!$A:$A,Доп.расчеты!$A6,'Как есть'!DY:DY) -> 0 | DY6: =SUMIF('Как есть'!$A:$A,Доп.расчеты!$A6,'Как есть'!DZ:DZ) -> 0 | DZ6: =SUMIF('Как есть'!$A:$A,Доп.расчеты!$A6,'Как есть'!EA:EA) -> 0 | EA6: =SUMIF('Как есть'!$A:$A,Доп.расчеты!$A6,'Как есть'!EB:EB) -> 0 | EB6: =SUMIF('Как есть'!$A:$A,Доп.расчеты!$A6,'Как есть'!EC:EC) -> 0 | EC6: =SUMIF('Как есть'!$A:$A,Доп.расчеты!$A6,'Как есть'!ED:ED) -> 0 | ED6: =SUMIF('Как есть'!$A:$A,Доп.расчеты!$A6,'Как есть'!EE:EE) -> 0 | EE6: =SUMIF('Как есть'!$A:$A,Доп.расчеты!$A6,'Как есть'!EF:EF) -> 0 | EF6: =SUMIF('Как есть'!$A:$A,Доп.расчеты!$A6,'Как есть'!EG:EG) -> 0 | EG6: =SUMIF('Как есть'!$A:$A,Доп.расчеты!$A6,'Как есть'!EH:EH) -> 0 | EH6: =SUMIF('Как есть'!$A:$A,Доп.расчеты!$A6,'Как есть'!EI:EI) -> 0 | EI6: =SUMIF('Как есть'!$A:$A,Доп.расчеты!$A6,'Как есть'!EJ:EJ) -> 0 | EJ6: =SUMIF('Как есть'!$A:$A,Доп.расчеты!$A6,'Как есть'!EK:EK) -> 0 | EK6: =SUMIF('Как есть'!$A:$A,Доп.расчеты!$A6,'Как есть'!EL:EL) -> 0 | EL6: =SUMIF('Как есть'!$A:$A,Доп.расчеты!$A6,'Как есть'!EM:EM) -> 0 | EM6: =SUMIF('Как есть'!$A:$A,Доп.расчеты!$A6,'Как есть'!EN:EN) -> 0 | EN6: =SUMIF('Как есть'!$A:$A,Доп.расчеты!$A6,'Как есть'!EO:EO) -> 0 | EO6: =SUMIF('Как есть'!$A:$A,Доп.расчеты!$A6,'Как есть'!EP:EP) -> 0 | EP6: =SUMIF('Как есть'!$A:$A,Доп.расчеты!$A6,'Как есть'!EQ:EQ) -> 0 | EQ6: =SUMIF('Как есть'!$A:$A,Доп.расчеты!$A6,'Как есть'!ER:ER) -> 0 | ER6: =SUMIF('Как есть'!$A:$A,Доп.расчеты!$A6,'Как есть'!ES:ES) -> 0 | ES6: =SUMIF('Как есть'!$A:$A,Доп.расчеты!$A6,'Как есть'!ET:ET) -> 0 | ET6: =SUMIF('Как есть'!$A:$A,Доп.расчеты!$A6,'Как есть'!EU:EU) -> 0 | EU6: =SUMIF('Как есть'!$A:$A,Доп.расчеты!$A6,'Как есть'!EV:EV) -> 0 | EV6: =SUMIF('Как есть'!$A:$A,Доп.расчеты!$A6,'Как есть'!EW:EW) -> 0 | EW6: =SUMIF('Как есть'!$A:$A,Доп.расчеты!$A6,'Как есть'!EX:EX) -> 0 | EX6: =SUMIF('Как есть'!$A:$A,Доп.расчеты!$A6,'Как есть'!EY:EY) -> 0 | EY6: =SUMIF('Как есть'!$A:$A,Доп.расчеты!$A6,'Как есть'!EZ:EZ) -> 0 | EZ6: =SUMIF('Как есть'!$A:$A,Доп.расчеты!$A6,'Как есть'!FA:FA) -> 0 | FA6: =SUMIF('Как есть'!$A:$A,Доп.расчеты!$A6,'Как есть'!FB:FB) -> 0 | FB6: =SUMIF('Как есть'!$A:$A,Доп.расчеты!$A6,'Как есть'!FC:FC) -> 0 | FC6: =SUMIF('Как есть'!$A:$A,Доп.расчеты!$A6,'Как есть'!FD:FD) -> 0 | FD6: =SUMIF('Как есть'!$A:$A,Доп.расчеты!$A6,'Как есть'!FE:FE) -> 0 | FE6: =SUMIF('Как есть'!$A:$A,Доп.расчеты!$A6,'Как есть'!FF:FF) -> 0 | FF6: =SUMIF('Как есть'!$A:$A,Доп.расчеты!$A6,'Как есть'!FG:FG) -> 0 | FG6: =SUMIF('Как есть'!$A:$A,Доп.расчеты!$A6,'Как есть'!FH:FH) -> 0 | FH6: =SUMIF('Как есть'!$A:$A,Доп.расчеты!$A6,'Как есть'!FI:FI) -> 0 | FI6: =SUMIF('Как есть'!$A:$A,Доп.расчеты!$A6,'Как есть'!FJ:FJ) -> 0 | FJ6: =SUMIF('Как есть'!$A:$A,Доп.расчеты!$A6,'Как есть'!FK:FK) -> 0 | FK6: =SUMIF('Как есть'!$A:$A,Доп.расчеты!$A6,'Как есть'!FL:FL) -> 0 | FL6: =SUMIF('Как есть'!$A:$A,Доп.расчеты!$A6,'Как есть'!FM:FM) -> 0 | FM6: =SUMIF('Как есть'!$A:$A,Доп.расчеты!$A6,'Как есть'!FN:FN) -> 0 | FN6: =SUMIF('Как есть'!$A:$A,Доп.расчеты!$A6,'Как есть'!FO:FO) -> 0 | FO6: =SUMIF('Как есть'!$A:$A,Доп.расчеты!$A6,'Как есть'!FP:FP) -> 0 | FP6: =SUMIF('Как есть'!$A:$A,Доп.расчеты!$A6,'Как есть'!FQ:FQ) -> 0 | FQ6: =SUMIF('Как есть'!$A:$A,Доп.расчеты!$A6,'Как есть'!FR:FR) -> 0 | FR6: =SUMIF('Как есть'!$A:$A,Доп.расчеты!$A6,'Как есть'!FS:FS) -> 0 | FS6: =SUMIF('Как есть'!$A:$A,Доп.расчеты!$A6,'Как есть'!FT:FT) -> 0 | FT6: =SUMIF('Как есть'!$A:$A,Доп.расчеты!$A6,'Как есть'!FU:FU) -> 0 | FU6: =SUMIF('Как есть'!$A:$A,Доп.расчеты!$A6,'Как есть'!FV:FV) -> 0 | FV6: =SUMIF('Как есть'!$A:$A,Доп.расчеты!$A6,'Как есть'!FW:FW) -> 0 | FW6: =SUMIF('Как есть'!$A:$A,Доп.расчеты!$A6,'Как есть'!FX:FX) -> 0 | FX6: =SUMIF('Как есть'!$A:$A,Доп.расчеты!$A6,'Как есть'!FY:FY) -> 0 | FY6: =SUMIF('Как есть'!$A:$A,Доп.расчеты!$A6,'Как есть'!FZ:FZ) -> 0 | FZ6: =SUMIF('Как есть'!$A:$A,Доп.расчеты!$A6,'Как есть'!GA:GA) -> 0 | GA6: =SUMIF('Как есть'!$A:$A,Доп.расчеты!$A6,'Как есть'!GB:GB) -> 0 | GB6: =SUMIF('Как есть'!$A:$A,Доп.расчеты!$A6,'Как есть'!GC:GC) -> 0 | GC6: =SUMIF('Как есть'!$A:$A,Доп.расчеты!$A6,'Как есть'!GD:GD) -> 0 | GD6: =SUMIF('Как есть'!$A:$A,Доп.расчеты!$A6,'Как есть'!GE:GE) -> 0 | GE6: =SUMIF('Как есть'!$A:$A,Доп.расчеты!$A6,'Как есть'!GF:GF) -> 0 | GF6: =SUMIF('Как есть'!$A:$A,Доп.расчеты!$A6,'Как есть'!GG:GG) -> 0 | GG6: =SUMIF('Как есть'!$A:$A,Доп.расчеты!$A6,'Как есть'!GH:GH) -> 0 | GH6: =SUMIF('Как есть'!$A:$A,Доп.расчеты!$A6,'Как есть'!GI:GI) -> 0 | GI6: =SUMIF('Как есть'!$A:$A,Доп.расчеты!$A6,'Как есть'!GJ:GJ) -> 0 | GJ6: =SUMIF('Как есть'!$A:$A,Доп.расчеты!$A6,'Как есть'!GK:GK) -> 0 | GK6: =SUMIF('Как есть'!$A:$A,Доп.расчеты!$A6,'Как есть'!GL:GL) -> 0 | GL6: =SUMIF('Как есть'!$A:$A,Доп.расчеты!$A6,'Как есть'!GM:GM) -> 0 | GM6: =SUMIF('Как есть'!$A:$A,Доп.расчеты!$A6,'Как есть'!GN:GN) -> 0 | GN6: =SUMIF('Как есть'!$A:$A,Доп.расчеты!$A6,'Как есть'!GO:GO) -> 0 | GO6: =SUMIF('Как есть'!$A:$A,Доп.расчеты!$A6,'Как есть'!GP:GP) -> 0 | GP6: =SUMIF('Как есть'!$A:$A,Доп.расчеты!$A6,'Как есть'!GQ:GQ) -> 0 | GQ6: =SUMIF('Как есть'!$A:$A,Доп.расчеты!$A6,'Как есть'!GR:GR) -> 0 | GR6: =SUMIF('Как есть'!$A:$A,Доп.расчеты!$A6,'Как есть'!GS:GS) -> 0 | GS6: =SUMIF('Как есть'!$A:$A,Доп.расчеты!$A6,'Как есть'!GT:GT) -> 0 | GT6: =SUMIF('Как есть'!$A:$A,Доп.расчеты!$A6,'Как есть'!GU:GU) -> 0
A7: Затраты производства | B7: =SUMIF('Как есть'!$A:$A,Доп.расчеты!$A7,'Как есть'!C:C) -> 0 | C7: =SUMIF('Как есть'!$A:$A,Доп.расчеты!$A7,'Как есть'!D:D) -> 0 | D7: =SUMIF('Как есть'!$A:$A,Доп.расчеты!$A7,'Как есть'!E:E) -> 0 | E7: =SUMIF('Как есть'!$A:$A,Доп.расчеты!$A7,'Как есть'!F:F) -> 0 | F7: =SUMIF('Как есть'!$A:$A,Доп.расчеты!$A7,'Как есть'!G:G) -> 0 | G7: =SUMIF('Как есть'!$A:$A,Доп.расчеты!$A7,'Как есть'!H:H) -> 0 | H7: =SUMIF('Как есть'!$A:$A,Доп.расчеты!$A7,'Как есть'!I:I) -> 0 | I7: =SUMIF('Как есть'!$A:$A,Доп.расчеты!$A7,'Как есть'!J:J) -> 0 | J7: =SUMIF('Как есть'!$A:$A,Доп.расчеты!$A7,'Как есть'!K:K) -> 0 | K7: =SUMIF('Как есть'!$A:$A,Доп.расчеты!$A7,'Как есть'!L:L) -> 0 | L7: =SUMIF('Как есть'!$A:$A,Доп.расчеты!$A7,'Как есть'!M:M) -> 0 | M7: =SUMIF('Как есть'!$A:$A,Доп.расчеты!$A7,'Как есть'!N:N) -> 0 | N7: =SUMIF('Как есть'!$A:$A,Доп.расчеты!$A7,'Как есть'!O:O) -> 0 | O7: =SUMIF('Как есть'!$A:$A,Доп.расчеты!$A7,'Как есть'!P:P) -> 0 | P7: =SUMIF('Как есть'!$A:$A,Доп.расчеты!$A7,'Как есть'!Q:Q) -> 0 | Q7: =SUMIF('Как есть'!$A:$A,Доп.расчеты!$A7,'Как есть'!R:R) -> 0 | R7: =SUMIF('Как есть'!$A:$A,Доп.расчеты!$A7,'Как есть'!S:S) -> 0 | S7: =SUMIF('Как есть'!$A:$A,Доп.расчеты!$A7,'Как есть'!T:T) -> 0 | T7: =SUMIF('Как есть'!$A:$A,Доп.расчеты!$A7,'Как есть'!U:U) -> 0 | U7: =SUMIF('Как есть'!$A:$A,Доп.расчеты!$A7,'Как есть'!V:V) -> 0 | V7: =SUMIF('Как есть'!$A:$A,Доп.расчеты!$A7,'Как есть'!W:W) -> 0 | W7: =SUMIF('Как есть'!$A:$A,Доп.расчеты!$A7,'Как есть'!X:X) -> 0 | X7: =SUMIF('Как есть'!$A:$A,Доп.расчеты!$A7,'Как есть'!Y:Y) -> 0 | Y7: =SUMIF('Как есть'!$A:$A,Доп.расчеты!$A7,'Как есть'!Z:Z) -> 0 | Z7: =SUMIF('Как есть'!$A:$A,Доп.расчеты!$A7,'Как есть'!AA:AA) -> 0 | AA7: =SUMIF('Как есть'!$A:$A,Доп.расчеты!$A7,'Как есть'!AB:AB) -> 0 | AB7: =SUMIF('Как есть'!$A:$A,Доп.расчеты!$A7,'Как есть'!AC:AC) -> 0 | AC7: =SUMIF('Как есть'!$A:$A,Доп.расчеты!$A7,'Как есть'!AD:AD) -> 0 | AD7: =SUMIF('Как есть'!$A:$A,Доп.расчеты!$A7,'Как есть'!AE:AE) -> 0 | AE7: =SUMIF('Как есть'!$A:$A,Доп.расчеты!$A7,'Как есть'!AF:AF) -> 0 | AF7: =SUMIF('Как есть'!$A:$A,Доп.расчеты!$A7,'Как есть'!AG:AG) -> 0 | AG7: =SUMIF('Как есть'!$A:$A,Доп.расчеты!$A7,'Как есть'!AH:AH) -> 0 | AH7: =SUMIF('Как есть'!$A:$A,Доп.расчеты!$A7,'Как есть'!AI:AI) -> 0 | AI7: =SUMIF('Как есть'!$A:$A,Доп.расчеты!$A7,'Как есть'!AJ:AJ) -> 0 | AJ7: =SUMIF('Как есть'!$A:$A,Доп.расчеты!$A7,'Как есть'!AK:AK) -> 0 | AK7: =SUMIF('Как есть'!$A:$A,Доп.расчеты!$A7,'Как есть'!AL:AL) -> 0 | AL7: =SUMIF('Как есть'!$A:$A,Доп.расчеты!$A7,'Как есть'!AM:AM) -> 0 | AM7: =SUMIF('Как есть'!$A:$A,Доп.расчеты!$A7,'Как есть'!AN:AN) -> 0 | AN7: =SUMIF('Как есть'!$A:$A,Доп.расчеты!$A7,'Как есть'!AO:AO) -> 0 | AO7: =SUMIF('Как есть'!$A:$A,Доп.расчеты!$A7,'Как есть'!AP:AP) -> 0 | AP7: =SUMIF('Как есть'!$A:$A,Доп.расчеты!$A7,'Как есть'!AQ:AQ) -> 0 | AQ7: =SUMIF('Как есть'!$A:$A,Доп.расчеты!$A7,'Как есть'!AR:AR) -> 0 | AR7: =SUMIF('Как есть'!$A:$A,Доп.расчеты!$A7,'Как есть'!AS:AS) -> 0 | AS7: =SUMIF('Как есть'!$A:$A,Доп.расчеты!$A7,'Как есть'!AT:AT) -> 0 | AT7: =SUMIF('Как есть'!$A:$A,Доп.расчеты!$A7,'Как есть'!AU:AU) -> 0 | AU7: =SUMIF('Как есть'!$A:$A,Доп.расчеты!$A7,'Как есть'!AV:AV) -> 0 | AV7: =SUMIF('Как есть'!$A:$A,Доп.расчеты!$A7,'Как есть'!AW:AW) -> 0 | AW7: =SUMIF('Как есть'!$A:$A,Доп.расчеты!$A7,'Как есть'!AX:AX) -> 0 | AX7: =SUMIF('Как есть'!$A:$A,Доп.расчеты!$A7,'Как есть'!AY:AY) -> 0 | AY7: =SUMIF('Как есть'!$A:$A,Доп.расчеты!$A7,'Как есть'!AZ:AZ) -> 0 | AZ7: =SUMIF('Как есть'!$A:$A,Доп.расчеты!$A7,'Как есть'!BA:BA) -> 0 | BA7: =SUMIF('Как есть'!$A:$A,Доп.расчеты!$A7,'Как есть'!BB:BB) -> 0 | BB7: =SUMIF('Как есть'!$A:$A,Доп.расчеты!$A7,'Как есть'!BC:BC) -> 0 | BC7: =SUMIF('Как есть'!$A:$A,Доп.расчеты!$A7,'Как есть'!BD:BD) -> 0 | BD7: =SUMIF('Как есть'!$A:$A,Доп.расчеты!$A7,'Как есть'!BE:BE) -> 0 | BE7: =SUMIF('Как есть'!$A:$A,Доп.расчеты!$A7,'Как есть'!BF:BF) -> 0 | BF7: =SUMIF('Как есть'!$A:$A,Доп.расчеты!$A7,'Как есть'!BG:BG) -> 0 | BG7: =SUMIF('Как есть'!$A:$A,Доп.расчеты!$A7,'Как есть'!BH:BH) -> 0 | BH7: =SUMIF('Как есть'!$A:$A,Доп.расчеты!$A7,'Как есть'!BI:BI) -> 0 | BI7: =SUMIF('Как есть'!$A:$A,Доп.расчеты!$A7,'Как есть'!BJ:BJ) -> 0 | BJ7: =SUMIF('Как есть'!$A:$A,Доп.расчеты!$A7,'Как есть'!BK:BK) -> 0 | BK7: =SUMIF('Как есть'!$A:$A,Доп.расчеты!$A7,'Как есть'!BL:BL) -> 0 | BL7: =SUMIF('Как есть'!$A:$A,Доп.расчеты!$A7,'Как есть'!BM:BM) -> 0 | BM7: =SUMIF('Как есть'!$A:$A,Доп.расчеты!$A7,'Как есть'!BN:BN) -> 0 | BN7: =SUMIF('Как есть'!$A:$A,Доп.расчеты!$A7,'Как есть'!BO:BO) -> 0 | BO7: =SUMIF('Как есть'!$A:$A,Доп.расчеты!$A7,'Как есть'!BP:BP) -> 0 | BP7: =SUMIF('Как есть'!$A:$A,Доп.расчеты!$A7,'Как есть'!BQ:BQ) -> 0 | BQ7: =SUMIF('Как есть'!$A:$A,Доп.расчеты!$A7,'Как есть'!BR:BR) -> 0 | BR7: =SUMIF('Как есть'!$A:$A,Доп.расчеты!$A7,'Как есть'!BS:BS) -> 0 | BS7: =SUMIF('Как есть'!$A:$A,Доп.расчеты!$A7,'Как есть'!BT:BT) -> 0 | BT7: =SUMIF('Как есть'!$A:$A,Доп.расчеты!$A7,'Как есть'!BU:BU) -> 0 | BU7: =SUMIF('Как есть'!$A:$A,Доп.расчеты!$A7,'Как есть'!BV:BV) -> 0 | BV7: =SUMIF('Как есть'!$A:$A,Доп.расчеты!$A7,'Как есть'!BW:BW) -> 0 | BW7: =SUMIF('Как есть'!$A:$A,Доп.расчеты!$A7,'Как есть'!BX:BX) -> 0 | BX7: =SUMIF('Как есть'!$A:$A,Доп.расчеты!$A7,'Как есть'!BY:BY) -> 0 | BY7: =SUMIF('Как есть'!$A:$A,Доп.расчеты!$A7,'Как есть'!BZ:BZ) -> 0 | BZ7: =SUMIF('Как есть'!$A:$A,Доп.расчеты!$A7,'Как есть'!CA:CA) -> 0 | CA7: =SUMIF('Как есть'!$A:$A,Доп.расчеты!$A7,'Как есть'!CB:CB) -> 0 | CB7: =SUMIF('Как есть'!$A:$A,Доп.расчеты!$A7,'Как есть'!CC:CC) -> 0 | CC7: =SUMIF('Как есть'!$A:$A,Доп.расчеты!$A7,'Как есть'!CD:CD) -> 0 | CD7: =SUMIF('Как есть'!$A:$A,Доп.расчеты!$A7,'Как есть'!CE:CE) -> 0 | CE7: =SUMIF('Как есть'!$A:$A,Доп.расчеты!$A7,'Как есть'!CF:CF) -> 0 | CF7: =SUMIF('Как есть'!$A:$A,Доп.расчеты!$A7,'Как есть'!CG:CG) -> 0 | CG7: =SUMIF('Как есть'!$A:$A,Доп.расчеты!$A7,'Как есть'!CH:CH) -> 0 | CH7: =SUMIF('Как есть'!$A:$A,Доп.расчеты!$A7,'Как есть'!CI:CI) -> 0 | CI7: =SUMIF('Как есть'!$A:$A,Доп.расчеты!$A7,'Как есть'!CJ:CJ) -> 0 | CJ7: =SUMIF('Как есть'!$A:$A,Доп.расчеты!$A7,'Как есть'!CK:CK) -> 0 | CK7: =SUMIF('Как есть'!$A:$A,Доп.расчеты!$A7,'Как есть'!CL:CL) -> 0 | CL7: =SUMIF('Как есть'!$A:$A,Доп.расчеты!$A7,'Как есть'!CM:CM) -> 0 | CM7: =SUMIF('Как есть'!$A:$A,Доп.расчеты!$A7,'Как есть'!CN:CN) -> 0 | CN7: =SUMIF('Как есть'!$A:$A,Доп.расчеты!$A7,'Как есть'!CO:CO) -> 0 | CO7: =SUMIF('Как есть'!$A:$A,Доп.расчеты!$A7,'Как есть'!CP:CP) -> 0 | CP7: =SUMIF('Как есть'!$A:$A,Доп.расчеты!$A7,'Как есть'!CQ:CQ) -> 0 | CQ7: =SUMIF('Как есть'!$A:$A,Доп.расчеты!$A7,'Как есть'!CR:CR) -> 0 | CR7: =SUMIF('Как есть'!$A:$A,Доп.расчеты!$A7,'Как есть'!CS:CS) -> 0 | CS7: =SUMIF('Как есть'!$A:$A,Доп.расчеты!$A7,'Как есть'!CT:CT) -> 0 | CT7: =SUMIF('Как есть'!$A:$A,Доп.расчеты!$A7,'Как есть'!CU:CU) -> 0 | CU7: =SUMIF('Как есть'!$A:$A,Доп.расчеты!$A7,'Как есть'!CV:CV) -> 0 | CV7: =SUMIF('Как есть'!$A:$A,Доп.расчеты!$A7,'Как есть'!CW:CW) -> 0 | CW7: =SUMIF('Как есть'!$A:$A,Доп.расчеты!$A7,'Как есть'!CX:CX) -> 0 | CX7: =SUMIF('Как есть'!$A:$A,Доп.расчеты!$A7,'Как есть'!CY:CY) -> 0 | CY7: =SUMIF('Как есть'!$A:$A,Доп.расчеты!$A7,'Как есть'!CZ:CZ) -> 0 | CZ7: =SUMIF('Как есть'!$A:$A,Доп.расчеты!$A7,'Как есть'!DA:DA) -> 0 | DA7: =SUMIF('Как есть'!$A:$A,Доп.расчеты!$A7,'Как есть'!DB:DB) -> 0 | DB7: =SUMIF('Как есть'!$A:$A,Доп.расчеты!$A7,'Как есть'!DC:DC) -> 0 | DC7: =SUMIF('Как есть'!$A:$A,Доп.расчеты!$A7,'Как есть'!DD:DD) -> 0 | DD7: =SUMIF('Как есть'!$A:$A,Доп.расчеты!$A7,'Как есть'!DE:DE) -> 0 | DE7: =SUMIF('Как есть'!$A:$A,Доп.расчеты!$A7,'Как есть'!DF:DF) -> 0 | DF7: =SUMIF('Как есть'!$A:$A,Доп.расчеты!$A7,'Как есть'!DG:DG) -> 0 | DG7: =SUMIF('Как есть'!$A:$A,Доп.расчеты!$A7,'Как есть'!DH:DH) -> 0 | DH7: =SUMIF('Как есть'!$A:$A,Доп.расчеты!$A7,'Как есть'!DI:DI) -> 0 | DI7: =SUMIF('Как есть'!$A:$A,Доп.расчеты!$A7,'Как есть'!DJ:DJ) -> 0 | DJ7: =SUMIF('Как есть'!$A:$A,Доп.расчеты!$A7,'Как есть'!DK:DK) -> 0 | DK7: =SUMIF('Как есть'!$A:$A,Доп.расчеты!$A7,'Как есть'!DL:DL) -> 0 | DL7: =SUMIF('Как есть'!$A:$A,Доп.расчеты!$A7,'Как есть'!DM:DM) -> 0 | DM7: =SUMIF('Как есть'!$A:$A,Доп.расчеты!$A7,'Как есть'!DN:DN) -> 0 | DN7: =SUMIF('Как есть'!$A:$A,Доп.расчеты!$A7,'Как есть'!DO:DO) -> 0 | DO7: =SUMIF('Как есть'!$A:$A,Доп.расчеты!$A7,'Как есть'!DP:DP) -> 0 | DP7: =SUMIF('Как есть'!$A:$A,Доп.расчеты!$A7,'Как есть'!DQ:DQ) -> 0 | DQ7: =SUMIF('Как есть'!$A:$A,Доп.расчеты!$A7,'Как есть'!DR:DR) -> 0 | DR7: =SUMIF('Как есть'!$A:$A,Доп.расчеты!$A7,'Как есть'!DS:DS) -> 0 | DS7: =SUMIF('Как есть'!$A:$A,Доп.расчеты!$A7,'Как есть'!DT:DT) -> 0 | DT7: =SUMIF('Как есть'!$A:$A,Доп.расчеты!$A7,'Как есть'!DU:DU) -> 0 | DU7: =SUMIF('Как есть'!$A:$A,Доп.расчеты!$A7,'Как есть'!DV:DV) -> 0 | DV7: =SUMIF('Как есть'!$A:$A,Доп.расчеты!$A7,'Как есть'!DW:DW) -> 0 | DW7: =SUMIF('Как есть'!$A:$A,Доп.расчеты!$A7,'Как есть'!DX:DX) -> 0 | DX7: =SUMIF('Как есть'!$A:$A,Доп.расчеты!$A7,'Как есть'!DY:DY) -> 0 | DY7: =SUMIF('Как есть'!$A:$A,Доп.расчеты!$A7,'Как есть'!DZ:DZ) -> 0 | DZ7: =SUMIF('Как есть'!$A:$A,Доп.расчеты!$A7,'Как есть'!EA:EA) -> 0 | EA7: =SUMIF('Как есть'!$A:$A,Доп.расчеты!$A7,'Как есть'!EB:EB) -> 0 | EB7: =SUMIF('Как есть'!$A:$A,Доп.расчеты!$A7,'Как есть'!EC:EC) -> 0 | EC7: =SUMIF('Как есть'!$A:$A,Доп.расчеты!$A7,'Как есть'!ED:ED) -> 0 | ED7: =SUMIF('Как есть'!$A:$A,Доп.расчеты!$A7,'Как есть'!EE:EE) -> 0 | EE7: =SUMIF('Как есть'!$A:$A,Доп.расчеты!$A7,'Как есть'!EF:EF) -> 0 | EF7: =SUMIF('Как есть'!$A:$A,Доп.расчеты!$A7,'Как есть'!EG:EG) -> 0 | EG7: =SUMIF('Как есть'!$A:$A,Доп.расчеты!$A7,'Как есть'!EH:EH) -> 0 | EH7: =SUMIF('Как есть'!$A:$A,Доп.расчеты!$A7,'Как есть'!EI:EI) -> 0 | EI7: =SUMIF('Как есть'!$A:$A,Доп.расчеты!$A7,'Как есть'!EJ:EJ) -> 0 | EJ7: =SUMIF('Как есть'!$A:$A,Доп.расчеты!$A7,'Как есть'!EK:EK) -> 0 | EK7: =SUMIF('Как есть'!$A:$A,Доп.расчеты!$A7,'Как есть'!EL:EL) -> 0 | EL7: =SUMIF('Как есть'!$A:$A,Доп.расчеты!$A7,'Как есть'!EM:EM) -> 0 | EM7: =SUMIF('Как есть'!$A:$A,Доп.расчеты!$A7,'Как есть'!EN:EN) -> 0 | EN7: =SUMIF('Как есть'!$A:$A,Доп.расчеты!$A7,'Как есть'!EO:EO) -> 0 | EO7: =SUMIF('Как есть'!$A:$A,Доп.расчеты!$A7,'Как есть'!EP:EP) -> 0 | EP7: =SUMIF('Как есть'!$A:$A,Доп.расчеты!$A7,'Как есть'!EQ:EQ) -> 0 | EQ7: =SUMIF('Как есть'!$A:$A,Доп.расчеты!$A7,'Как есть'!ER:ER) -> 0 | ER7: =SUMIF('Как есть'!$A:$A,Доп.расчеты!$A7,'Как есть'!ES:ES) -> 0 | ES7: =SUMIF('Как есть'!$A:$A,Доп.расчеты!$A7,'Как есть'!ET:ET) -> 0 | ET7: =SUMIF('Как есть'!$A:$A,Доп.расчеты!$A7,'Как есть'!EU:EU) -> 0 | EU7: =SUMIF('Как есть'!$A:$A,Доп.расчеты!$A7,'Как есть'!EV:EV) -> 0 | EV7: =SUMIF('Как есть'!$A:$A,Доп.расчеты!$A7,'Как есть'!EW:EW) -> 0 | EW7: =SUMIF('Как есть'!$A:$A,Доп.расчеты!$A7,'Как есть'!EX:EX) -> 0 | EX7: =SUMIF('Как есть'!$A:$A,Доп.расчеты!$A7,'Как есть'!EY:EY) -> 0 | EY7: =SUMIF('Как есть'!$A:$A,Доп.расчеты!$A7,'Как есть'!EZ:EZ) -> 0 | EZ7: =SUMIF('Как есть'!$A:$A,Доп.расчеты!$A7,'Как есть'!FA:FA) -> 0 | FA7: =SUMIF('Как есть'!$A:$A,Доп.расчеты!$A7,'Как есть'!FB:FB) -> 0 | FB7: =SUMIF('Как есть'!$A:$A,Доп.расчеты!$A7,'Как есть'!FC:FC) -> 0 | FC7: =SUMIF('Как есть'!$A:$A,Доп.расчеты!$A7,'Как есть'!FD:FD) -> 0 | FD7: =SUMIF('Как есть'!$A:$A,Доп.расчеты!$A7,'Как есть'!FE:FE) -> 0 | FE7: =SUMIF('Как есть'!$A:$A,Доп.расчеты!$A7,'Как есть'!FF:FF) -> 0 | FF7: =SUMIF('Как есть'!$A:$A,Доп.расчеты!$A7,'Как есть'!FG:FG) -> 0 | FG7: =SUMIF('Как есть'!$A:$A,Доп.расчеты!$A7,'Как есть'!FH:FH) -> 0 | FH7: =SUMIF('Как есть'!$A:$A,Доп.расчеты!$A7,'Как есть'!FI:FI) -> 0 | FI7: =SUMIF('Как есть'!$A:$A,Доп.расчеты!$A7,'Как есть'!FJ:FJ) -> 0 | FJ7: =SUMIF('Как есть'!$A:$A,Доп.расчеты!$A7,'Как есть'!FK:FK) -> 0 | FK7: =SUMIF('Как есть'!$A:$A,Доп.расчеты!$A7,'Как есть'!FL:FL) -> 0 | FL7: =SUMIF('Как есть'!$A:$A,Доп.расчеты!$A7,'Как есть'!FM:FM) -> 0 | FM7: =SUMIF('Как есть'!$A:$A,Доп.расчеты!$A7,'Как есть'!FN:FN) -> 0 | FN7: =SUMIF('Как есть'!$A:$A,Доп.расчеты!$A7,'Как есть'!FO:FO) -> 0 | FO7: =SUMIF('Как есть'!$A:$A,Доп.расчеты!$A7,'Как есть'!FP:FP) -> 0 | FP7: =SUMIF('Как есть'!$A:$A,Доп.расчеты!$A7,'Как есть'!FQ:FQ) -> 0 | FQ7: =SUMIF('Как есть'!$A:$A,Доп.расчеты!$A7,'Как есть'!FR:FR) -> 0 | FR7: =SUMIF('Как есть'!$A:$A,Доп.расчеты!$A7,'Как есть'!FS:FS) -> 0 | FS7: =SUMIF('Как есть'!$A:$A,Доп.расчеты!$A7,'Как есть'!FT:FT) -> 0 | FT7: =SUMIF('Как есть'!$A:$A,Доп.расчеты!$A7,'Как есть'!FU:FU) -> 0 | FU7: =SUMIF('Как есть'!$A:$A,Доп.расчеты!$A7,'Как есть'!FV:FV) -> 0 | FV7: =SUMIF('Как есть'!$A:$A,Доп.расчеты!$A7,'Как есть'!FW:FW) -> 0 | FW7: =SUMIF('Как есть'!$A:$A,Доп.расчеты!$A7,'Как есть'!FX:FX) -> 0 | FX7: =SUMIF('Как есть'!$A:$A,Доп.расчеты!$A7,'Как есть'!FY:FY) -> 0 | FY7: =SUMIF('Как есть'!$A:$A,Доп.расчеты!$A7,'Как есть'!FZ:FZ) -> 0 | FZ7: =SUMIF('Как есть'!$A:$A,Доп.расчеты!$A7,'Как есть'!GA:GA) -> 0 | GA7: =SUMIF('Как есть'!$A:$A,Доп.расчеты!$A7,'Как есть'!GB:GB) -> 0 | GB7: =SUMIF('Как есть'!$A:$A,Доп.расчеты!$A7,'Как есть'!GC:GC) -> 0 | GC7: =SUMIF('Как есть'!$A:$A,Доп.расчеты!$A7,'Как есть'!GD:GD) -> 0 | GD7: =SUMIF('Как есть'!$A:$A,Доп.расчеты!$A7,'Как есть'!GE:GE) -> 0 | GE7: =SUMIF('Как есть'!$A:$A,Доп.расчеты!$A7,'Как есть'!GF:GF) -> 0 | GF7: =SUMIF('Как есть'!$A:$A,Доп.расчеты!$A7,'Как есть'!GG:GG) -> 0 | GG7: =SUMIF('Как есть'!$A:$A,Доп.расчеты!$A7,'Как есть'!GH:GH) -> 0 | GH7: =SUMIF('Как есть'!$A:$A,Доп.расчеты!$A7,'Как есть'!GI:GI) -> 0 | GI7: =SUMIF('Как есть'!$A:$A,Доп.расчеты!$A7,'Как есть'!GJ:GJ) -> 0 | GJ7: =SUMIF('Как есть'!$A:$A,Доп.расчеты!$A7,'Как есть'!GK:GK) -> 0 | GK7: =SUMIF('Как есть'!$A:$A,Доп.расчеты!$A7,'Как есть'!GL:GL) -> 0 | GL7: =SUMIF('Как есть'!$A:$A,Доп.расчеты!$A7,'Как есть'!GM:GM) -> 0 | GM7: =SUMIF('Как есть'!$A:$A,Доп.расчеты!$A7,'Как есть'!GN:GN) -> 0 | GN7: =SUMIF('Как есть'!$A:$A,Доп.расчеты!$A7,'Как есть'!GO:GO) -> 0 | GO7: =SUMIF('Как есть'!$A:$A,Доп.расчеты!$A7,'Как есть'!GP:GP) -> 0 | GP7: =SUMIF('Как есть'!$A:$A,Доп.расчеты!$A7,'Как есть'!GQ:GQ) -> 0 | GQ7: =SUMIF('Как есть'!$A:$A,Доп.расчеты!$A7,'Как есть'!GR:GR) -> 0 | GR7: =SUMIF('Как есть'!$A:$A,Доп.расчеты!$A7,'Как есть'!GS:GS) -> 0 | GS7: =SUMIF('Как есть'!$A:$A,Доп.расчеты!$A7,'Как есть'!GT:GT) -> 0 | GT7: =SUMIF('Как есть'!$A:$A,Доп.расчеты!$A7,'Как есть'!GU:GU) -> 0
A8: Потери | B8: =SUMIF('Как есть'!$A:$A,Доп.расчеты!$A8,'Как есть'!C:C) -> 0 | C8: =SUMIF('Как есть'!$A:$A,Доп.расчеты!$A8,'Как есть'!D:D) -> 0 | D8: =SUMIF('Как есть'!$A:$A,Доп.расчеты!$A8,'Как есть'!E:E) -> 0 | E8: =SUMIF('Как есть'!$A:$A,Доп.расчеты!$A8,'Как есть'!F:F) -> 0 | F8: =SUMIF('Как есть'!$A:$A,Доп.расчеты!$A8,'Как есть'!G:G) -> 0 | G8: =SUMIF('Как есть'!$A:$A,Доп.расчеты!$A8,'Как есть'!H:H) -> 0 | H8: =SUMIF('Как есть'!$A:$A,Доп.расчеты!$A8,'Как есть'!I:I) -> 0 | I8: =SUMIF('Как есть'!$A:$A,Доп.расчеты!$A8,'Как есть'!J:J) -> 0 | J8: =SUMIF('Как есть'!$A:$A,Доп.расчеты!$A8,'Как есть'!K:K) -> 0 | K8: =SUMIF('Как есть'!$A:$A,Доп.расчеты!$A8,'Как есть'!L:L) -> 0 | L8: =SUMIF('Как есть'!$A:$A,Доп.расчеты!$A8,'Как есть'!M:M) -> 0 | M8: =SUMIF('Как есть'!$A:$A,Доп.расчеты!$A8,'Как есть'!N:N) -> 0 | N8: =SUMIF('Как есть'!$A:$A,Доп.расчеты!$A8,'Как есть'!O:O) -> 0 | O8: =SUMIF('Как есть'!$A:$A,Доп.расчеты!$A8,'Как есть'!P:P) -> 0 | P8: =SUMIF('Как есть'!$A:$A,Доп.расчеты!$A8,'Как есть'!Q:Q) -> 0 | Q8: =SUMIF('Как есть'!$A:$A,Доп.расчеты!$A8,'Как есть'!R:R) -> 0 | R8: =SUMIF('Как есть'!$A:$A,Доп.расчеты!$A8,'Как есть'!S:S) -> 0 | S8: =SUMIF('Как есть'!$A:$A,Доп.расчеты!$A8,'Как есть'!T:T) -> 0 | T8: =SUMIF('Как есть'!$A:$A,Доп.расчеты!$A8,'Как есть'!U:U) -> 0 | U8: =SUMIF('Как есть'!$A:$A,Доп.расчеты!$A8,'Как есть'!V:V) -> 0 | V8: =SUMIF('Как есть'!$A:$A,Доп.расчеты!$A8,'Как есть'!W:W) -> 0 | W8: =SUMIF('Как есть'!$A:$A,Доп.расчеты!$A8,'Как есть'!X:X) -> 0 | X8: =SUMIF('Как есть'!$A:$A,Доп.расчеты!$A8,'Как есть'!Y:Y) -> 0 | Y8: =SUMIF('Как есть'!$A:$A,Доп.расчеты!$A8,'Как есть'!Z:Z) -> 0 | Z8: =SUMIF('Как есть'!$A:$A,Доп.расчеты!$A8,'Как есть'!AA:AA) -> 0 | AA8: =SUMIF('Как есть'!$A:$A,Доп.расчеты!$A8,'Как есть'!AB:AB) -> 0 | AB8: =SUMIF('Как есть'!$A:$A,Доп.расчеты!$A8,'Как есть'!AC:AC) -> 0 | AC8: =SUMIF('Как есть'!$A:$A,Доп.расчеты!$A8,'Как есть'!AD:AD) -> 0 | AD8: =SUMIF('Как есть'!$A:$A,Доп.расчеты!$A8,'Как есть'!AE:AE) -> 0 | AE8: =SUMIF('Как есть'!$A:$A,Доп.расчеты!$A8,'Как есть'!AF:AF) -> 0 | AF8: =SUMIF('Как есть'!$A:$A,Доп.расчеты!$A8,'Как есть'!AG:AG) -> 0 | AG8: =SUMIF('Как есть'!$A:$A,Доп.расчеты!$A8,'Как есть'!AH:AH) -> 0 | AH8: =SUMIF('Как есть'!$A:$A,Доп.расчеты!$A8,'Как есть'!AI:AI) -> 0 | AI8: =SUMIF('Как есть'!$A:$A,Доп.расчеты!$A8,'Как есть'!AJ:AJ) -> 0 | AJ8: =SUMIF('Как есть'!$A:$A,Доп.расчеты!$A8,'Как есть'!AK:AK) -> 0 | AK8: =SUMIF('Как есть'!$A:$A,Доп.расчеты!$A8,'Как есть'!AL:AL) -> 0 | AL8: =SUMIF('Как есть'!$A:$A,Доп.расчеты!$A8,'Как есть'!AM:AM) -> 0 | AM8: =SUMIF('Как есть'!$A:$A,Доп.расчеты!$A8,'Как есть'!AN:AN) -> 0 | AN8: =SUMIF('Как есть'!$A:$A,Доп.расчеты!$A8,'Как есть'!AO:AO) -> 0 | AO8: =SUMIF('Как есть'!$A:$A,Доп.расчеты!$A8,'Как есть'!AP:AP) -> 0 | AP8: =SUMIF('Как есть'!$A:$A,Доп.расчеты!$A8,'Как есть'!AQ:AQ) -> 0 | AQ8: =SUMIF('Как есть'!$A:$A,Доп.расчеты!$A8,'Как есть'!AR:AR) -> 0 | AR8: =SUMIF('Как есть'!$A:$A,Доп.расчеты!$A8,'Как есть'!AS:AS) -> 0 | AS8: =SUMIF('Как есть'!$A:$A,Доп.расчеты!$A8,'Как есть'!AT:AT) -> 0 | AT8: =SUMIF('Как есть'!$A:$A,Доп.расчеты!$A8,'Как есть'!AU:AU) -> 0 | AU8: =SUMIF('Как есть'!$A:$A,Доп.расчеты!$A8,'Как есть'!AV:AV) -> 0 | AV8: =SUMIF('Как есть'!$A:$A,Доп.расчеты!$A8,'Как есть'!AW:AW) -> 0 | AW8: =SUMIF('Как есть'!$A:$A,Доп.расчеты!$A8,'Как есть'!AX:AX) -> 0 | AX8: =SUMIF('Как есть'!$A:$A,Доп.расчеты!$A8,'Как есть'!AY:AY) -> 0 | AY8: =SUMIF('Как есть'!$A:$A,Доп.расчеты!$A8,'Как есть'!AZ:AZ) -> 0 | AZ8: =SUMIF('Как есть'!$A:$A,Доп.расчеты!$A8,'Как есть'!BA:BA) -> 0 | BA8: =SUMIF('Как есть'!$A:$A,Доп.расчеты!$A8,'Как есть'!BB:BB) -> 0 | BB8: =SUMIF('Как есть'!$A:$A,Доп.расчеты!$A8,'Как есть'!BC:BC) -> 0 | BC8: =SUMIF('Как есть'!$A:$A,Доп.расчеты!$A8,'Как есть'!BD:BD) -> 0 | BD8: =SUMIF('Как есть'!$A:$A,Доп.расчеты!$A8,'Как есть'!BE:BE) -> 0 | BE8: =SUMIF('Как есть'!$A:$A,Доп.расчеты!$A8,'Как есть'!BF:BF) -> 0 | BF8: =SUMIF('Как есть'!$A:$A,Доп.расчеты!$A8,'Как есть'!BG:BG) -> 0 | BG8: =SUMIF('Как есть'!$A:$A,Доп.расчеты!$A8,'Как есть'!BH:BH) -> 0 | BH8: =SUMIF('Как есть'!$A:$A,Доп.расчеты!$A8,'Как есть'!BI:BI) -> 0 | BI8: =SUMIF('Как есть'!$A:$A,Доп.расчеты!$A8,'Как есть'!BJ:BJ) -> 0 | BJ8: =SUMIF('Как есть'!$A:$A,Доп.расчеты!$A8,'Как есть'!BK:BK) -> 0 | BK8: =SUMIF('Как есть'!$A:$A,Доп.расчеты!$A8,'Как есть'!BL:BL) -> 0 | BL8: =SUMIF('Как есть'!$A:$A,Доп.расчеты!$A8,'Как есть'!BM:BM) -> 0 | BM8: =SUMIF('Как есть'!$A:$A,Доп.расчеты!$A8,'Как есть'!BN:BN) -> 0 | BN8: =SUMIF('Как есть'!$A:$A,Доп.расчеты!$A8,'Как есть'!BO:BO) -> 0 | BO8: =SUMIF('Как есть'!$A:$A,Доп.расчеты!$A8,'Как есть'!BP:BP) -> 0 | BP8: =SUMIF('Как есть'!$A:$A,Доп.расчеты!$A8,'Как есть'!BQ:BQ) -> 0 | BQ8: =SUMIF('Как есть'!$A:$A,Доп.расчеты!$A8,'Как есть'!BR:BR) -> 0 | BR8: =SUMIF('Как есть'!$A:$A,Доп.расчеты!$A8,'Как есть'!BS:BS) -> 0 | BS8: =SUMIF('Как есть'!$A:$A,Доп.расчеты!$A8,'Как есть'!BT:BT) -> 0 | BT8: =SUMIF('Как есть'!$A:$A,Доп.расчеты!$A8,'Как есть'!BU:BU) -> 0 | BU8: =SUMIF('Как есть'!$A:$A,Доп.расчеты!$A8,'Как есть'!BV:BV) -> 0 | BV8: =SUMIF('Как есть'!$A:$A,Доп.расчеты!$A8,'Как есть'!BW:BW) -> 0 | BW8: =SUMIF('Как есть'!$A:$A,Доп.расчеты!$A8,'Как есть'!BX:BX) -> 0 | BX8: =SUMIF('Как есть'!$A:$A,Доп.расчеты!$A8,'Как есть'!BY:BY) -> 0 | BY8: =SUMIF('Как есть'!$A:$A,Доп.расчеты!$A8,'Как есть'!BZ:BZ) -> 0 | BZ8: =SUMIF('Как есть'!$A:$A,Доп.расчеты!$A8,'Как есть'!CA:CA) -> 0 | CA8: =SUMIF('Как есть'!$A:$A,Доп.расчеты!$A8,'Как есть'!CB:CB) -> 0 | CB8: =SUMIF('Как есть'!$A:$A,Доп.расчеты!$A8,'Как есть'!CC:CC) -> 0 | CC8: =SUMIF('Как есть'!$A:$A,Доп.расчеты!$A8,'Как есть'!CD:CD) -> 0 | CD8: =SUMIF('Как есть'!$A:$A,Доп.расчеты!$A8,'Как есть'!CE:CE) -> 0 | CE8: =SUMIF('Как есть'!$A:$A,Доп.расчеты!$A8,'Как есть'!CF:CF) -> 0 | CF8: =SUMIF('Как есть'!$A:$A,Доп.расчеты!$A8,'Как есть'!CG:CG) -> 0 | CG8: =SUMIF('Как есть'!$A:$A,Доп.расчеты!$A8,'Как есть'!CH:CH) -> 0 | CH8: =SUMIF('Как есть'!$A:$A,Доп.расчеты!$A8,'Как есть'!CI:CI) -> 0 | CI8: =SUMIF('Как есть'!$A:$A,Доп.расчеты!$A8,'Как есть'!CJ:CJ) -> 0 | CJ8: =SUMIF('Как есть'!$A:$A,Доп.расчеты!$A8,'Как есть'!CK:CK) -> 0 | CK8: =SUMIF('Как есть'!$A:$A,Доп.расчеты!$A8,'Как есть'!CL:CL) -> 0 | CL8: =SUMIF('Как есть'!$A:$A,Доп.расчеты!$A8,'Как есть'!CM:CM) -> 0 | CM8: =SUMIF('Как есть'!$A:$A,Доп.расчеты!$A8,'Как есть'!CN:CN) -> 0 | CN8: =SUMIF('Как есть'!$A:$A,Доп.расчеты!$A8,'Как есть'!CO:CO) -> 0 | CO8: =SUMIF('Как есть'!$A:$A,Доп.расчеты!$A8,'Как есть'!CP:CP) -> 0 | CP8: =SUMIF('Как есть'!$A:$A,Доп.расчеты!$A8,'Как есть'!CQ:CQ) -> 0 | CQ8: =SUMIF('Как есть'!$A:$A,Доп.расчеты!$A8,'Как есть'!CR:CR) -> 0 | CR8: =SUMIF('Как есть'!$A:$A,Доп.расчеты!$A8,'Как есть'!CS:CS) -> 0 | CS8: =SUMIF('Как есть'!$A:$A,Доп.расчеты!$A8,'Как есть'!CT:CT) -> 0 | CT8: =SUMIF('Как есть'!$A:$A,Доп.расчеты!$A8,'Как есть'!CU:CU) -> 0 | CU8: =SUMIF('Как есть'!$A:$A,Доп.расчеты!$A8,'Как есть'!CV:CV) -> 0 | CV8: =SUMIF('Как есть'!$A:$A,Доп.расчеты!$A8,'Как есть'!CW:CW) -> 0 | CW8: =SUMIF('Как есть'!$A:$A,Доп.расчеты!$A8,'Как есть'!CX:CX) -> 0 | CX8: =SUMIF('Как есть'!$A:$A,Доп.расчеты!$A8,'Как есть'!CY:CY) -> 0 | CY8: =SUMIF('Как есть'!$A:$A,Доп.расчеты!$A8,'Как есть'!CZ:CZ) -> 0 | CZ8: =SUMIF('Как есть'!$A:$A,Доп.расчеты!$A8,'Как есть'!DA:DA) -> 0 | DA8: =SUMIF('Как есть'!$A:$A,Доп.расчеты!$A8,'Как есть'!DB:DB) -> 0 | DB8: =SUMIF('Как есть'!$A:$A,Доп.расчеты!$A8,'Как есть'!DC:DC) -> 0 | DC8: =SUMIF('Как есть'!$A:$A,Доп.расчеты!$A8,'Как есть'!DD:DD) -> 0 | DD8: =SUMIF('Как есть'!$A:$A,Доп.расчеты!$A8,'Как есть'!DE:DE) -> 0 | DE8: =SUMIF('Как есть'!$A:$A,Доп.расчеты!$A8,'Как есть'!DF:DF) -> 0 | DF8: =SUMIF('Как есть'!$A:$A,Доп.расчеты!$A8,'Как есть'!DG:DG) -> 0 | DG8: =SUMIF('Как есть'!$A:$A,Доп.расчеты!$A8,'Как есть'!DH:DH) -> 0 | DH8: =SUMIF('Как есть'!$A:$A,Доп.расчеты!$A8,'Как есть'!DI:DI) -> 0 | DI8: =SUMIF('Как есть'!$A:$A,Доп.расчеты!$A8,'Как есть'!DJ:DJ) -> 0 | DJ8: =SUMIF('Как есть'!$A:$A,Доп.расчеты!$A8,'Как есть'!DK:DK) -> 0 | DK8: =SUMIF('Как есть'!$A:$A,Доп.расчеты!$A8,'Как есть'!DL:DL) -> 0 | DL8: =SUMIF('Как есть'!$A:$A,Доп.расчеты!$A8,'Как есть'!DM:DM) -> 0 | DM8: =SUMIF('Как есть'!$A:$A,Доп.расчеты!$A8,'Как есть'!DN:DN) -> 0 | DN8: =SUMIF('Как есть'!$A:$A,Доп.расчеты!$A8,'Как есть'!DO:DO) -> 0 | DO8: =SUMIF('Как есть'!$A:$A,Доп.расчеты!$A8,'Как есть'!DP:DP) -> 0 | DP8: =SUMIF('Как есть'!$A:$A,Доп.расчеты!$A8,'Как есть'!DQ:DQ) -> 0 | DQ8: =SUMIF('Как есть'!$A:$A,Доп.расчеты!$A8,'Как есть'!DR:DR) -> 0 | DR8: =SUMIF('Как есть'!$A:$A,Доп.расчеты!$A8,'Как есть'!DS:DS) -> 0 | DS8: =SUMIF('Как есть'!$A:$A,Доп.расчеты!$A8,'Как есть'!DT:DT) -> 0 | DT8: =SUMIF('Как есть'!$A:$A,Доп.расчеты!$A8,'Как есть'!DU:DU) -> 0 | DU8: =SUMIF('Как есть'!$A:$A,Доп.расчеты!$A8,'Как есть'!DV:DV) -> 0 | DV8: =SUMIF('Как есть'!$A:$A,Доп.расчеты!$A8,'Как есть'!DW:DW) -> 0 | DW8: =SUMIF('Как есть'!$A:$A,Доп.расчеты!$A8,'Как есть'!DX:DX) -> 0 | DX8: =SUMIF('Как есть'!$A:$A,Доп.расчеты!$A8,'Как есть'!DY:DY) -> 0 | DY8: =SUMIF('Как есть'!$A:$A,Доп.расчеты!$A8,'Как есть'!DZ:DZ) -> 0 | DZ8: =SUMIF('Как есть'!$A:$A,Доп.расчеты!$A8,'Как есть'!EA:EA) -> 0 | EA8: =SUMIF('Как есть'!$A:$A,Доп.расчеты!$A8,'Как есть'!EB:EB) -> 0 | EB8: =SUMIF('Как есть'!$A:$A,Доп.расчеты!$A8,'Как есть'!EC:EC) -> 0 | EC8: =SUMIF('Как есть'!$A:$A,Доп.расчеты!$A8,'Как есть'!ED:ED) -> 0 | ED8: =SUMIF('Как есть'!$A:$A,Доп.расчеты!$A8,'Как есть'!EE:EE) -> 0 | EE8: =SUMIF('Как есть'!$A:$A,Доп.расчеты!$A8,'Как есть'!EF:EF) -> 0 | EF8: =SUMIF('Как есть'!$A:$A,Доп.расчеты!$A8,'Как есть'!EG:EG) -> 0 | EG8: =SUMIF('Как есть'!$A:$A,Доп.расчеты!$A8,'Как есть'!EH:EH) -> 0 | EH8: =SUMIF('Как есть'!$A:$A,Доп.расчеты!$A8,'Как есть'!EI:EI) -> 0 | EI8: =SUMIF('Как есть'!$A:$A,Доп.расчеты!$A8,'Как есть'!EJ:EJ) -> 0 | EJ8: =SUMIF('Как есть'!$A:$A,Доп.расчеты!$A8,'Как есть'!EK:EK) -> 0 | EK8: =SUMIF('Как есть'!$A:$A,Доп.расчеты!$A8,'Как есть'!EL:EL) -> 0 | EL8: =SUMIF('Как есть'!$A:$A,Доп.расчеты!$A8,'Как есть'!EM:EM) -> 0 | EM8: =SUMIF('Как есть'!$A:$A,Доп.расчеты!$A8,'Как есть'!EN:EN) -> 0 | EN8: =SUMIF('Как есть'!$A:$A,Доп.расчеты!$A8,'Как есть'!EO:EO) -> 0 | EO8: =SUMIF('Как есть'!$A:$A,Доп.расчеты!$A8,'Как есть'!EP:EP) -> 0 | EP8: =SUMIF('Как есть'!$A:$A,Доп.расчеты!$A8,'Как есть'!EQ:EQ) -> 0 | EQ8: =SUMIF('Как есть'!$A:$A,Доп.расчеты!$A8,'Как есть'!ER:ER) -> 0 | ER8: =SUMIF('Как есть'!$A:$A,Доп.расчеты!$A8,'Как есть'!ES:ES) -> 0 | ES8: =SUMIF('Как есть'!$A:$A,Доп.расчеты!$A8,'Как есть'!ET:ET) -> 0 | ET8: =SUMIF('Как есть'!$A:$A,Доп.расчеты!$A8,'Как есть'!EU:EU) -> 0 | EU8: =SUMIF('Как есть'!$A:$A,Доп.расчеты!$A8,'Как есть'!EV:EV) -> 0 | EV8: =SUMIF('Как есть'!$A:$A,Доп.расчеты!$A8,'Как есть'!EW:EW) -> 0 | EW8: =SUMIF('Как есть'!$A:$A,Доп.расчеты!$A8,'Как есть'!EX:EX) -> 0 | EX8: =SUMIF('Как есть'!$A:$A,Доп.расчеты!$A8,'Как есть'!EY:EY) -> 0 | EY8: =SUMIF('Как есть'!$A:$A,Доп.расчеты!$A8,'Как есть'!EZ:EZ) -> 0 | EZ8: =SUMIF('Как есть'!$A:$A,Доп.расчеты!$A8,'Как есть'!FA:FA) -> 0 | FA8: =SUMIF('Как есть'!$A:$A,Доп.расчеты!$A8,'Как есть'!FB:FB) -> 0 | FB8: =SUMIF('Как есть'!$A:$A,Доп.расчеты!$A8,'Как есть'!FC:FC) -> 0 | FC8: =SUMIF('Как есть'!$A:$A,Доп.расчеты!$A8,'Как есть'!FD:FD) -> 0 | FD8: =SUMIF('Как есть'!$A:$A,Доп.расчеты!$A8,'Как есть'!FE:FE) -> 0 | FE8: =SUMIF('Как есть'!$A:$A,Доп.расчеты!$A8,'Как есть'!FF:FF) -> 0 | FF8: =SUMIF('Как есть'!$A:$A,Доп.расчеты!$A8,'Как есть'!FG:FG) -> 0 | FG8: =SUMIF('Как есть'!$A:$A,Доп.расчеты!$A8,'Как есть'!FH:FH) -> 0 | FH8: =SUMIF('Как есть'!$A:$A,Доп.расчеты!$A8,'Как есть'!FI:FI) -> 0 | FI8: =SUMIF('Как есть'!$A:$A,Доп.расчеты!$A8,'Как есть'!FJ:FJ) -> 0 | FJ8: =SUMIF('Как есть'!$A:$A,Доп.расчеты!$A8,'Как есть'!FK:FK) -> 0 | FK8: =SUMIF('Как есть'!$A:$A,Доп.расчеты!$A8,'Как есть'!FL:FL) -> 0 | FL8: =SUMIF('Как есть'!$A:$A,Доп.расчеты!$A8,'Как есть'!FM:FM) -> 0 | FM8: =SUMIF('Как есть'!$A:$A,Доп.расчеты!$A8,'Как есть'!FN:FN) -> 0 | FN8: =SUMIF('Как есть'!$A:$A,Доп.расчеты!$A8,'Как есть'!FO:FO) -> 0 | FO8: =SUMIF('Как есть'!$A:$A,Доп.расчеты!$A8,'Как есть'!FP:FP) -> 0 | FP8: =SUMIF('Как есть'!$A:$A,Доп.расчеты!$A8,'Как есть'!FQ:FQ) -> 0 | FQ8: =SUMIF('Как есть'!$A:$A,Доп.расчеты!$A8,'Как есть'!FR:FR) -> 0 | FR8: =SUMIF('Как есть'!$A:$A,Доп.расчеты!$A8,'Как есть'!FS:FS) -> 0 | FS8: =SUMIF('Как есть'!$A:$A,Доп.расчеты!$A8,'Как есть'!FT:FT) -> 0 | FT8: =SUMIF('Как есть'!$A:$A,Доп.расчеты!$A8,'Как есть'!FU:FU) -> 0 | FU8: =SUMIF('Как есть'!$A:$A,Доп.расчеты!$A8,'Как есть'!FV:FV) -> 0 | FV8: =SUMIF('Как есть'!$A:$A,Доп.расчеты!$A8,'Как есть'!FW:FW) -> 0 | FW8: =SUMIF('Как есть'!$A:$A,Доп.расчеты!$A8,'Как есть'!FX:FX) -> 0 | FX8: =SUMIF('Как есть'!$A:$A,Доп.расчеты!$A8,'Как есть'!FY:FY) -> 0 | FY8: =SUMIF('Как есть'!$A:$A,Доп.расчеты!$A8,'Как есть'!FZ:FZ) -> 0 | FZ8: =SUMIF('Как есть'!$A:$A,Доп.расчеты!$A8,'Как есть'!GA:GA) -> 0 | GA8: =SUMIF('Как есть'!$A:$A,Доп.расчеты!$A8,'Как есть'!GB:GB) -> 0 | GB8: =SUMIF('Как есть'!$A:$A,Доп.расчеты!$A8,'Как есть'!GC:GC) -> 0 | GC8: =SUMIF('Как есть'!$A:$A,Доп.расчеты!$A8,'Как есть'!GD:GD) -> 0 | GD8: =SUMIF('Как есть'!$A:$A,Доп.расчеты!$A8,'Как есть'!GE:GE) -> 0 | GE8: =SUMIF('Как есть'!$A:$A,Доп.расчеты!$A8,'Как есть'!GF:GF) -> 0 | GF8: =SUMIF('Как есть'!$A:$A,Доп.расчеты!$A8,'Как есть'!GG:GG) -> 0 | GG8: =SUMIF('Как есть'!$A:$A,Доп.расчеты!$A8,'Как есть'!GH:GH) -> 0 | GH8: =SUMIF('Как есть'!$A:$A,Доп.расчеты!$A8,'Как есть'!GI:GI) -> 0 | GI8: =SUMIF('Как есть'!$A:$A,Доп.расчеты!$A8,'Как есть'!GJ:GJ) -> 0 | GJ8: =SUMIF('Как есть'!$A:$A,Доп.расчеты!$A8,'Как есть'!GK:GK) -> 0 | GK8: =SUMIF('Как есть'!$A:$A,Доп.расчеты!$A8,'Как есть'!GL:GL) -> 0 | GL8: =SUMIF('Как есть'!$A:$A,Доп.расчеты!$A8,'Как есть'!GM:GM) -> 0 | GM8: =SUMIF('Как есть'!$A:$A,Доп.расчеты!$A8,'Как есть'!GN:GN) -> 0 | GN8: =SUMIF('Как есть'!$A:$A,Доп.расчеты!$A8,'Как есть'!GO:GO) -> 0 | GO8: =SUMIF('Как есть'!$A:$A,Доп.расчеты!$A8,'Как есть'!GP:GP) -> 0 | GP8: =SUMIF('Как есть'!$A:$A,Доп.расчеты!$A8,'Как есть'!GQ:GQ) -> 0 | GQ8: =SUMIF('Как есть'!$A:$A,Доп.расчеты!$A8,'Как есть'!GR:GR) -> 0 | GR8: =SUMIF('Как есть'!$A:$A,Доп.расчеты!$A8,'Как есть'!GS:GS) -> 0 | GS8: =SUMIF('Как есть'!$A:$A,Доп.расчеты!$A8,'Как есть'!GT:GT) -> 0 | GT8: =SUMIF('Как есть'!$A:$A,Доп.расчеты!$A8,'Как есть'!GU:GU) -> 0
A11: Себестоимость_Как будет
A12: Складская логистика | B12: =SUMIF('Как будет'!$A:$A,Доп.расчеты!$A12,'Как будет'!C:C) -> 0 | C12: =SUMIF('Как будет'!$A:$A,Доп.расчеты!$A12,'Как будет'!D:D) -> 0 | D12: =SUMIF('Как будет'!$A:$A,Доп.расчеты!$A12,'Как будет'!E:E) -> 0 | E12: =SUMIF('Как будет'!$A:$A,Доп.расчеты!$A12,'Как будет'!F:F) -> 0 | F12: =SUMIF('Как будет'!$A:$A,Доп.расчеты!$A12,'Как будет'!G:G) -> 0 | G12: =SUMIF('Как будет'!$A:$A,Доп.расчеты!$A12,'Как будет'!H:H) -> 0 | H12: =SUMIF('Как будет'!$A:$A,Доп.расчеты!$A12,'Как будет'!I:I) -> 0 | I12: =SUMIF('Как будет'!$A:$A,Доп.расчеты!$A12,'Как будет'!J:J) -> 0 | J12: =SUMIF('Как будет'!$A:$A,Доп.расчеты!$A12,'Как будет'!K:K) -> 0 | K12: =SUMIF('Как будет'!$A:$A,Доп.расчеты!$A12,'Как будет'!L:L) -> 0 | L12: =SUMIF('Как будет'!$A:$A,Доп.расчеты!$A12,'Как будет'!M:M) -> 0 | M12: =SUMIF('Как будет'!$A:$A,Доп.расчеты!$A12,'Как будет'!N:N) -> 0 | N12: =SUMIF('Как будет'!$A:$A,Доп.расчеты!$A12,'Как будет'!O:O) -> 0 | O12: =SUMIF('Как будет'!$A:$A,Доп.расчеты!$A12,'Как будет'!P:P) -> 0 | P12: =SUMIF('Как будет'!$A:$A,Доп.расчеты!$A12,'Как будет'!Q:Q) -> 0 | Q12: =SUMIF('Как будет'!$A:$A,Доп.расчеты!$A12,'Как будет'!R:R) -> 0 | R12: =SUMIF('Как будет'!$A:$A,Доп.расчеты!$A12,'Как будет'!S:S) -> 0 | S12: =SUMIF('Как будет'!$A:$A,Доп.расчеты!$A12,'Как будет'!T:T) -> 0 | T12: =SUMIF('Как будет'!$A:$A,Доп.расчеты!$A12,'Как будет'!U:U) -> 0 | U12: =SUMIF('Как будет'!$A:$A,Доп.расчеты!$A12,'Как будет'!V:V) -> 0 | V12: =SUMIF('Как будет'!$A:$A,Доп.расчеты!$A12,'Как будет'!W:W) -> 0 | W12: =SUMIF('Как будет'!$A:$A,Доп.расчеты!$A12,'Как будет'!X:X) -> 0 | X12: =SUMIF('Как будет'!$A:$A,Доп.расчеты!$A12,'Как будет'!Y:Y) -> 0 | Y12: =SUMIF('Как будет'!$A:$A,Доп.расчеты!$A12,'Как будет'!Z:Z) -> 0 | Z12: =SUMIF('Как будет'!$A:$A,Доп.расчеты!$A12,'Как будет'!AA:AA) -> 0 | AA12: =SUMIF('Как будет'!$A:$A,Доп.расчеты!$A12,'Как будет'!AB:AB) -> 0 | AB12: =SUMIF('Как будет'!$A:$A,Доп.расчеты!$A12,'Как будет'!AC:AC) -> 0 | AC12: =SUMIF('Как будет'!$A:$A,Доп.расчеты!$A12,'Как будет'!AD:AD) -> 0 | AD12: =SUMIF('Как будет'!$A:$A,Доп.расчеты!$A12,'Как будет'!AE:AE) -> 0 | AE12: =SUMIF('Как будет'!$A:$A,Доп.расчеты!$A12,'Как будет'!AF:AF) -> 0 | AF12: =SUMIF('Как будет'!$A:$A,Доп.расчеты!$A12,'Как будет'!AG:AG) -> 0 | AG12: =SUMIF('Как будет'!$A:$A,Доп.расчеты!$A12,'Как будет'!AH:AH) -> 0 | AH12: =SUMIF('Как будет'!$A:$A,Доп.расчеты!$A12,'Как будет'!AI:AI) -> 0 | AI12: =SUMIF('Как будет'!$A:$A,Доп.расчеты!$A12,'Как будет'!AJ:AJ) -> 0 | AJ12: =SUMIF('Как будет'!$A:$A,Доп.расчеты!$A12,'Как будет'!AK:AK) -> 0 | AK12: =SUMIF('Как будет'!$A:$A,Доп.расчеты!$A12,'Как будет'!AL:AL) -> 0 | AL12: =SUMIF('Как будет'!$A:$A,Доп.расчеты!$A12,'Как будет'!AM:AM) -> 0 | AM12: =SUMIF('Как будет'!$A:$A,Доп.расчеты!$A12,'Как будет'!AN:AN) -> 0 | AN12: =SUMIF('Как будет'!$A:$A,Доп.расчеты!$A12,'Как будет'!AO:AO) -> 0 | AO12: =SUMIF('Как будет'!$A:$A,Доп.расчеты!$A12,'Как будет'!AP:AP) -> 0 | AP12: =SUMIF('Как будет'!$A:$A,Доп.расчеты!$A12,'Как будет'!AQ:AQ) -> 0 | AQ12: =SUMIF('Как будет'!$A:$A,Доп.расчеты!$A12,'Как будет'!AR:AR) -> 0 | AR12: =SUMIF('Как будет'!$A:$A,Доп.расчеты!$A12,'Как будет'!AS:AS) -> 0 | AS12: =SUMIF('Как будет'!$A:$A,Доп.расчеты!$A12,'Как будет'!AT:AT) -> 0 | AT12: =SUMIF('Как будет'!$A:$A,Доп.расчеты!$A12,'Как будет'!AU:AU) -> 0 | AU12: =SUMIF('Как будет'!$A:$A,Доп.расчеты!$A12,'Как будет'!AV:AV) -> 0 | AV12: =SUMIF('Как будет'!$A:$A,Доп.расчеты!$A12,'Как будет'!AW:AW) -> 0 | AW12: =SUMIF('Как будет'!$A:$A,Доп.расчеты!$A12,'Как будет'!AX:AX) -> 0 | AX12: =SUMIF('Как будет'!$A:$A,Доп.расчеты!$A12,'Как будет'!AY:AY) -> 0 | AY12: =SUMIF('Как будет'!$A:$A,Доп.расчеты!$A12,'Как будет'!AZ:AZ) -> 0 | AZ12: =SUMIF('Как будет'!$A:$A,Доп.расчеты!$A12,'Как будет'!BA:BA) -> 0 | BA12: =SUMIF('Как будет'!$A:$A,Доп.расчеты!$A12,'Как будет'!BB:BB) -> 0 | BB12: =SUMIF('Как будет'!$A:$A,Доп.расчеты!$A12,'Как будет'!BC:BC) -> 0 | BC12: =SUMIF('Как будет'!$A:$A,Доп.расчеты!$A12,'Как будет'!BD:BD) -> 0 | BD12: =SUMIF('Как будет'!$A:$A,Доп.расчеты!$A12,'Как будет'!BE:BE) -> 0 | BE12: =SUMIF('Как будет'!$A:$A,Доп.расчеты!$A12,'Как будет'!BF:BF) -> 0 | BF12: =SUMIF('Как будет'!$A:$A,Доп.расчеты!$A12,'Как будет'!BG:BG) -> 0 | BG12: =SUMIF('Как будет'!$A:$A,Доп.расчеты!$A12,'Как будет'!BH:BH) -> 0 | BH12: =SUMIF('Как будет'!$A:$A,Доп.расчеты!$A12,'Как будет'!BI:BI) -> 0 | BI12: =SUMIF('Как будет'!$A:$A,Доп.расчеты!$A12,'Как будет'!BJ:BJ) -> 0 | BJ12: =SUMIF('Как будет'!$A:$A,Доп.расчеты!$A12,'Как будет'!BK:BK) -> 0 | BK12: =SUMIF('Как будет'!$A:$A,Доп.расчеты!$A12,'Как будет'!BL:BL) -> 0 | BL12: =SUMIF('Как будет'!$A:$A,Доп.расчеты!$A12,'Как будет'!BM:BM) -> 0 | BM12: =SUMIF('Как будет'!$A:$A,Доп.расчеты!$A12,'Как будет'!BN:BN) -> 0 | BN12: =SUMIF('Как будет'!$A:$A,Доп.расчеты!$A12,'Как будет'!BO:BO) -> 0 | BO12: =SUMIF('Как будет'!$A:$A,Доп.расчеты!$A12,'Как будет'!BP:BP) -> 0 | BP12: =SUMIF('Как будет'!$A:$A,Доп.расчеты!$A12,'Как будет'!BQ:BQ) -> 0 | BQ12: =SUMIF('Как будет'!$A:$A,Доп.расчеты!$A12,'Как будет'!BR:BR) -> 0 | BR12: =SUMIF('Как будет'!$A:$A,Доп.расчеты!$A12,'Как будет'!BS:BS) -> 0 | BS12: =SUMIF('Как будет'!$A:$A,Доп.расчеты!$A12,'Как будет'!BT:BT) -> 0 | BT12: =SUMIF('Как будет'!$A:$A,Доп.расчеты!$A12,'Как будет'!BU:BU) -> 0 | BU12: =SUMIF('Как будет'!$A:$A,Доп.расчеты!$A12,'Как будет'!BV:BV) -> 0 | BV12: =SUMIF('Как будет'!$A:$A,Доп.расчеты!$A12,'Как будет'!BW:BW) -> 0 | BW12: =SUMIF('Как будет'!$A:$A,Доп.расчеты!$A12,'Как будет'!BX:BX) -> 0 | BX12: =SUMIF('Как будет'!$A:$A,Доп.расчеты!$A12,'Как будет'!BY:BY) -> 0 | BY12: =SUMIF('Как будет'!$A:$A,Доп.расчеты!$A12,'Как будет'!BZ:BZ) -> 0 | BZ12: =SUMIF('Как будет'!$A:$A,Доп.расчеты!$A12,'Как будет'!CA:CA) -> 0 | CA12: =SUMIF('Как будет'!$A:$A,Доп.расчеты!$A12,'Как будет'!CB:CB) -> 0 | CB12: =SUMIF('Как будет'!$A:$A,Доп.расчеты!$A12,'Как будет'!CC:CC) -> 0 | CC12: =SUMIF('Как будет'!$A:$A,Доп.расчеты!$A12,'Как будет'!CD:CD) -> 0 | CD12: =SUMIF('Как будет'!$A:$A,Доп.расчеты!$A12,'Как будет'!CE:CE) -> 0 | CE12: =SUMIF('Как будет'!$A:$A,Доп.расчеты!$A12,'Как будет'!CF:CF) -> 0 | CF12: =SUMIF('Как будет'!$A:$A,Доп.расчеты!$A12,'Как будет'!CG:CG) -> 0 | CG12: =SUMIF('Как будет'!$A:$A,Доп.расчеты!$A12,'Как будет'!CH:CH) -> 0 | CH12: =SUMIF('Как будет'!$A:$A,Доп.расчеты!$A12,'Как будет'!CI:CI) -> 0 | CI12: =SUMIF('Как будет'!$A:$A,Доп.расчеты!$A12,'Как будет'!CJ:CJ) -> 0 | CJ12: =SUMIF('Как будет'!$A:$A,Доп.расчеты!$A12,'Как будет'!CK:CK) -> 0 | CK12: =SUMIF('Как будет'!$A:$A,Доп.расчеты!$A12,'Как будет'!CL:CL) -> 0 | CL12: =SUMIF('Как будет'!$A:$A,Доп.расчеты!$A12,'Как будет'!CM:CM) -> 0 | CM12: =SUMIF('Как будет'!$A:$A,Доп.расчеты!$A12,'Как будет'!CN:CN) -> 0 | CN12: =SUMIF('Как будет'!$A:$A,Доп.расчеты!$A12,'Как будет'!CO:CO) -> 0 | CO12: =SUMIF('Как будет'!$A:$A,Доп.расчеты!$A12,'Как будет'!CP:CP) -> 0 | CP12: =SUMIF('Как будет'!$A:$A,Доп.расчеты!$A12,'Как будет'!CQ:CQ) -> 0 | CQ12: =SUMIF('Как будет'!$A:$A,Доп.расчеты!$A12,'Как будет'!CR:CR) -> 0 | CR12: =SUMIF('Как будет'!$A:$A,Доп.расчеты!$A12,'Как будет'!CS:CS) -> 0 | CS12: =SUMIF('Как будет'!$A:$A,Доп.расчеты!$A12,'Как будет'!CT:CT) -> 0 | CT12: =SUMIF('Как будет'!$A:$A,Доп.расчеты!$A12,'Как будет'!CU:CU) -> 0 | CU12: =SUMIF('Как будет'!$A:$A,Доп.расчеты!$A12,'Как будет'!CV:CV) -> 0 | CV12: =SUMIF('Как будет'!$A:$A,Доп.расчеты!$A12,'Как будет'!CW:CW) -> 0 | CW12: =SUMIF('Как будет'!$A:$A,Доп.расчеты!$A12,'Как будет'!CX:CX) -> 0 | CX12: =SUMIF('Как будет'!$A:$A,Доп.расчеты!$A12,'Как будет'!CY:CY) -> 0 | CY12: =SUMIF('Как будет'!$A:$A,Доп.расчеты!$A12,'Как будет'!CZ:CZ) -> 0 | CZ12: =SUMIF('Как будет'!$A:$A,Доп.расчеты!$A12,'Как будет'!DA:DA) -> 0 | DA12: =SUMIF('Как будет'!$A:$A,Доп.расчеты!$A12,'Как будет'!DB:DB) -> 0 | DB12: =SUMIF('Как будет'!$A:$A,Доп.расчеты!$A12,'Как будет'!DC:DC) -> 0 | DC12: =SUMIF('Как будет'!$A:$A,Доп.расчеты!$A12,'Как будет'!DD:DD) -> 0 | DD12: =SUMIF('Как будет'!$A:$A,Доп.расчеты!$A12,'Как будет'!DE:DE) -> 0 | DE12: =SUMIF('Как будет'!$A:$A,Доп.расчеты!$A12,'Как будет'!DF:DF) -> 0 | DF12: =SUMIF('Как будет'!$A:$A,Доп.расчеты!$A12,'Как будет'!DG:DG) -> 0 | DG12: =SUMIF('Как будет'!$A:$A,Доп.расчеты!$A12,'Как будет'!DH:DH) -> 0 | DH12: =SUMIF('Как будет'!$A:$A,Доп.расчеты!$A12,'Как будет'!DI:DI) -> 0 | DI12: =SUMIF('Как будет'!$A:$A,Доп.расчеты!$A12,'Как будет'!DJ:DJ) -> 0 | DJ12: =SUMIF('Как будет'!$A:$A,Доп.расчеты!$A12,'Как будет'!DK:DK) -> 0 | DK12: =SUMIF('Как будет'!$A:$A,Доп.расчеты!$A12,'Как будет'!DL:DL) -> 0 | DL12: =SUMIF('Как будет'!$A:$A,Доп.расчеты!$A12,'Как будет'!DM:DM) -> 0 | DM12: =SUMIF('Как будет'!$A:$A,Доп.расчеты!$A12,'Как будет'!DN:DN) -> 0 | DN12: =SUMIF('Как будет'!$A:$A,Доп.расчеты!$A12,'Как будет'!DO:DO) -> 0 | DO12: =SUMIF('Как будет'!$A:$A,Доп.расчеты!$A12,'Как будет'!DP:DP) -> 0 | DP12: =SUMIF('Как будет'!$A:$A,Доп.расчеты!$A12,'Как будет'!DQ:DQ) -> 0 | DQ12: =SUMIF('Как будет'!$A:$A,Доп.расчеты!$A12,'Как будет'!DR:DR) -> 0 | DR12: =SUMIF('Как будет'!$A:$A,Доп.расчеты!$A12,'Как будет'!DS:DS) -> 0 | DS12: =SUMIF('Как будет'!$A:$A,Доп.расчеты!$A12,'Как будет'!DT:DT) -> 0 | DT12: =SUMIF('Как будет'!$A:$A,Доп.расчеты!$A12,'Как будет'!DU:DU) -> 0 | DU12: =SUMIF('Как будет'!$A:$A,Доп.расчеты!$A12,'Как будет'!DV:DV) -> 0 | DV12: =SUMIF('Как будет'!$A:$A,Доп.расчеты!$A12,'Как будет'!DW:DW) -> 0 | DW12: =SUMIF('Как будет'!$A:$A,Доп.расчеты!$A12,'Как будет'!DX:DX) -> 0 | DX12: =SUMIF('Как будет'!$A:$A,Доп.расчеты!$A12,'Как будет'!DY:DY) -> 0 | DY12: =SUMIF('Как будет'!$A:$A,Доп.расчеты!$A12,'Как будет'!DZ:DZ) -> 0 | DZ12: =SUMIF('Как будет'!$A:$A,Доп.расчеты!$A12,'Как будет'!EA:EA) -> 0 | EA12: =SUMIF('Как будет'!$A:$A,Доп.расчеты!$A12,'Как будет'!EB:EB) -> 0 | EB12: =SUMIF('Как будет'!$A:$A,Доп.расчеты!$A12,'Как будет'!EC:EC) -> 0 | EC12: =SUMIF('Как будет'!$A:$A,Доп.расчеты!$A12,'Как будет'!ED:ED) -> 0 | ED12: =SUMIF('Как будет'!$A:$A,Доп.расчеты!$A12,'Как будет'!EE:EE) -> 0 | EE12: =SUMIF('Как будет'!$A:$A,Доп.расчеты!$A12,'Как будет'!EF:EF) -> 0 | EF12: =SUMIF('Как будет'!$A:$A,Доп.расчеты!$A12,'Как будет'!EG:EG) -> 0 | EG12: =SUMIF('Как будет'!$A:$A,Доп.расчеты!$A12,'Как будет'!EH:EH) -> 0 | EH12: =SUMIF('Как будет'!$A:$A,Доп.расчеты!$A12,'Как будет'!EI:EI) -> 0 | EI12: =SUMIF('Как будет'!$A:$A,Доп.расчеты!$A12,'Как будет'!EJ:EJ) -> 0 | EJ12: =SUMIF('Как будет'!$A:$A,Доп.расчеты!$A12,'Как будет'!EK:EK) -> 0 | EK12: =SUMIF('Как будет'!$A:$A,Доп.расчеты!$A12,'Как будет'!EL:EL) -> 0 | EL12: =SUMIF('Как будет'!$A:$A,Доп.расчеты!$A12,'Как будет'!EM:EM) -> 0 | EM12: =SUMIF('Как будет'!$A:$A,Доп.расчеты!$A12,'Как будет'!EN:EN) -> 0 | EN12: =SUMIF('Как будет'!$A:$A,Доп.расчеты!$A12,'Как будет'!EO:EO) -> 0 | EO12: =SUMIF('Как будет'!$A:$A,Доп.расчеты!$A12,'Как будет'!EP:EP) -> 0 | EP12: =SUMIF('Как будет'!$A:$A,Доп.расчеты!$A12,'Как будет'!EQ:EQ) -> 0 | EQ12: =SUMIF('Как будет'!$A:$A,Доп.расчеты!$A12,'Как будет'!ER:ER) -> 0 | ER12: =SUMIF('Как будет'!$A:$A,Доп.расчеты!$A12,'Как будет'!ES:ES) -> 0 | ES12: =SUMIF('Как будет'!$A:$A,Доп.расчеты!$A12,'Как будет'!ET:ET) -> 0 | ET12: =SUMIF('Как будет'!$A:$A,Доп.расчеты!$A12,'Как будет'!EU:EU) -> 0 | EU12: =SUMIF('Как будет'!$A:$A,Доп.расчеты!$A12,'Как будет'!EV:EV) -> 0 | EV12: =SUMIF('Как будет'!$A:$A,Доп.расчеты!$A12,'Как будет'!EW:EW) -> 0 | EW12: =SUMIF('Как будет'!$A:$A,Доп.расчеты!$A12,'Как будет'!EX:EX) -> 0 | EX12: =SUMIF('Как будет'!$A:$A,Доп.расчеты!$A12,'Как будет'!EY:EY) -> 0 | EY12: =SUMIF('Как будет'!$A:$A,Доп.расчеты!$A12,'Как будет'!EZ:EZ) -> 0 | EZ12: =SUMIF('Как будет'!$A:$A,Доп.расчеты!$A12,'Как будет'!FA:FA) -> 0 | FA12: =SUMIF('Как будет'!$A:$A,Доп.расчеты!$A12,'Как будет'!FB:FB) -> 0 | FB12: =SUMIF('Как будет'!$A:$A,Доп.расчеты!$A12,'Как будет'!FC:FC) -> 0 | FC12: =SUMIF('Как будет'!$A:$A,Доп.расчеты!$A12,'Как будет'!FD:FD) -> 0 | FD12: =SUMIF('Как будет'!$A:$A,Доп.расчеты!$A12,'Как будет'!FE:FE) -> 0 | FE12: =SUMIF('Как будет'!$A:$A,Доп.расчеты!$A12,'Как будет'!FF:FF) -> 0 | FF12: =SUMIF('Как будет'!$A:$A,Доп.расчеты!$A12,'Как будет'!FG:FG) -> 0 | FG12: =SUMIF('Как будет'!$A:$A,Доп.расчеты!$A12,'Как будет'!FH:FH) -> 0 | FH12: =SUMIF('Как будет'!$A:$A,Доп.расчеты!$A12,'Как будет'!FI:FI) -> 0 | FI12: =SUMIF('Как будет'!$A:$A,Доп.расчеты!$A12,'Как будет'!FJ:FJ) -> 0 | FJ12: =SUMIF('Как будет'!$A:$A,Доп.расчеты!$A12,'Как будет'!FK:FK) -> 0 | FK12: =SUMIF('Как будет'!$A:$A,Доп.расчеты!$A12,'Как будет'!FL:FL) -> 0 | FL12: =SUMIF('Как будет'!$A:$A,Доп.расчеты!$A12,'Как будет'!FM:FM) -> 0 | FM12: =SUMIF('Как будет'!$A:$A,Доп.расчеты!$A12,'Как будет'!FN:FN) -> 0 | FN12: =SUMIF('Как будет'!$A:$A,Доп.расчеты!$A12,'Как будет'!FO:FO) -> 0 | FO12: =SUMIF('Как будет'!$A:$A,Доп.расчеты!$A12,'Как будет'!FP:FP) -> 0 | FP12: =SUMIF('Как будет'!$A:$A,Доп.расчеты!$A12,'Как будет'!FQ:FQ) -> 0 | FQ12: =SUMIF('Как будет'!$A:$A,Доп.расчеты!$A12,'Как будет'!FR:FR) -> 0 | FR12: =SUMIF('Как будет'!$A:$A,Доп.расчеты!$A12,'Как будет'!FS:FS) -> 0 | FS12: =SUMIF('Как будет'!$A:$A,Доп.расчеты!$A12,'Как будет'!FT:FT) -> 0 | FT12: =SUMIF('Как будет'!$A:$A,Доп.расчеты!$A12,'Как будет'!FU:FU) -> 0 | FU12: =SUMIF('Как будет'!$A:$A,Доп.расчеты!$A12,'Как будет'!FV:FV) -> 0 | FV12: =SUMIF('Как будет'!$A:$A,Доп.расчеты!$A12,'Как будет'!FW:FW) -> 0 | FW12: =SUMIF('Как будет'!$A:$A,Доп.расчеты!$A12,'Как будет'!FX:FX) -> 0 | FX12: =SUMIF('Как будет'!$A:$A,Доп.расчеты!$A12,'Как будет'!FY:FY) -> 0 | FY12: =SUMIF('Как будет'!$A:$A,Доп.расчеты!$A12,'Как будет'!FZ:FZ) -> 0 | FZ12: =SUMIF('Как будет'!$A:$A,Доп.расчеты!$A12,'Как будет'!GA:GA) -> 0 | GA12: =SUMIF('Как будет'!$A:$A,Доп.расчеты!$A12,'Как будет'!GB:GB) -> 0 | GB12: =SUMIF('Как будет'!$A:$A,Доп.расчеты!$A12,'Как будет'!GC:GC) -> 0 | GC12: =SUMIF('Как будет'!$A:$A,Доп.расчеты!$A12,'Как будет'!GD:GD) -> 0 | GD12: =SUMIF('Как будет'!$A:$A,Доп.расчеты!$A12,'Как будет'!GE:GE) -> 0 | GE12: =SUMIF('Как будет'!$A:$A,Доп.расчеты!$A12,'Как будет'!GF:GF) -> 0 | GF12: =SUMIF('Как будет'!$A:$A,Доп.расчеты!$A12,'Как будет'!GG:GG) -> 0 | GG12: =SUMIF('Как будет'!$A:$A,Доп.расчеты!$A12,'Как будет'!GH:GH) -> 0 | GH12: =SUMIF('Как будет'!$A:$A,Доп.расчеты!$A12,'Как будет'!GI:GI) -> 0 | GI12: =SUMIF('Как будет'!$A:$A,Доп.расчеты!$A12,'Как будет'!GJ:GJ) -> 0 | GJ12: =SUMIF('Как будет'!$A:$A,Доп.расчеты!$A12,'Как будет'!GK:GK) -> 0 | GK12: =SUMIF('Как будет'!$A:$A,Доп.расчеты!$A12,'Как будет'!GL:GL) -> 0 | GL12: =SUMIF('Как будет'!$A:$A,Доп.расчеты!$A12,'Как будет'!GM:GM) -> 0 | GM12: =SUMIF('Как будет'!$A:$A,Доп.расчеты!$A12,'Как будет'!GN:GN) -> 0 | GN12: =SUMIF('Как будет'!$A:$A,Доп.расчеты!$A12,'Как будет'!GO:GO) -> 0 | GO12: =SUMIF('Как будет'!$A:$A,Доп.расчеты!$A12,'Как будет'!GP:GP) -> 0 | GP12: =SUMIF('Как будет'!$A:$A,Доп.расчеты!$A12,'Как будет'!GQ:GQ) -> 0 | GQ12: =SUMIF('Как будет'!$A:$A,Доп.расчеты!$A12,'Как будет'!GR:GR) -> 0 | GR12: =SUMIF('Как будет'!$A:$A,Доп.расчеты!$A12,'Как будет'!GS:GS) -> 0 | GS12: =SUMIF('Как будет'!$A:$A,Доп.расчеты!$A12,'Как будет'!GT:GT) -> 0 | GT12: =SUMIF('Как будет'!$A:$A,Доп.расчеты!$A12,'Как будет'!GU:GU) -> 0
A13: Транспортная логистика | B13: =SUMIF('Как будет'!$A:$A,Доп.расчеты!$A13,'Как будет'!C:C) -> 0 | C13: =SUMIF('Как будет'!$A:$A,Доп.расчеты!$A13,'Как будет'!D:D) -> 0 | D13: =SUMIF('Как будет'!$A:$A,Доп.расчеты!$A13,'Как будет'!E:E) -> 0 | E13: =SUMIF('Как будет'!$A:$A,Доп.расчеты!$A13,'Как будет'!F:F) -> 0 | F13: =SUMIF('Как будет'!$A:$A,Доп.расчеты!$A13,'Как будет'!G:G) -> 0 | G13: =SUMIF('Как будет'!$A:$A,Доп.расчеты!$A13,'Как будет'!H:H) -> 0 | H13: =SUMIF('Как будет'!$A:$A,Доп.расчеты!$A13,'Как будет'!I:I) -> 0 | I13: =SUMIF('Как будет'!$A:$A,Доп.расчеты!$A13,'Как будет'!J:J) -> 0 | J13: =SUMIF('Как будет'!$A:$A,Доп.расчеты!$A13,'Как будет'!K:K) -> 0 | K13: =SUMIF('Как будет'!$A:$A,Доп.расчеты!$A13,'Как будет'!L:L) -> 0 | L13: =SUMIF('Как будет'!$A:$A,Доп.расчеты!$A13,'Как будет'!M:M) -> 0 | M13: =SUMIF('Как будет'!$A:$A,Доп.расчеты!$A13,'Как будет'!N:N) -> 0 | N13: =SUMIF('Как будет'!$A:$A,Доп.расчеты!$A13,'Как будет'!O:O) -> 0 | O13: =SUMIF('Как будет'!$A:$A,Доп.расчеты!$A13,'Как будет'!P:P) -> 0 | P13: =SUMIF('Как будет'!$A:$A,Доп.расчеты!$A13,'Как будет'!Q:Q) -> 0 | Q13: =SUMIF('Как будет'!$A:$A,Доп.расчеты!$A13,'Как будет'!R:R) -> 0 | R13: =SUMIF('Как будет'!$A:$A,Доп.расчеты!$A13,'Как будет'!S:S) -> 0 | S13: =SUMIF('Как будет'!$A:$A,Доп.расчеты!$A13,'Как будет'!T:T) -> 0 | T13: =SUMIF('Как будет'!$A:$A,Доп.расчеты!$A13,'Как будет'!U:U) -> 0 | U13: =SUMIF('Как будет'!$A:$A,Доп.расчеты!$A13,'Как будет'!V:V) -> 0 | V13: =SUMIF('Как будет'!$A:$A,Доп.расчеты!$A13,'Как будет'!W:W) -> 0 | W13: =SUMIF('Как будет'!$A:$A,Доп.расчеты!$A13,'Как будет'!X:X) -> 0 | X13: =SUMIF('Как будет'!$A:$A,Доп.расчеты!$A13,'Как будет'!Y:Y) -> 0 | Y13: =SUMIF('Как будет'!$A:$A,Доп.расчеты!$A13,'Как будет'!Z:Z) -> 0 | Z13: =SUMIF('Как будет'!$A:$A,Доп.расчеты!$A13,'Как будет'!AA:AA) -> 0 | AA13: =SUMIF('Как будет'!$A:$A,Доп.расчеты!$A13,'Как будет'!AB:AB) -> 0 | AB13: =SUMIF('Как будет'!$A:$A,Доп.расчеты!$A13,'Как будет'!AC:AC) -> 0 | AC13: =SUMIF('Как будет'!$A:$A,Доп.расчеты!$A13,'Как будет'!AD:AD) -> 0 | AD13: =SUMIF('Как будет'!$A:$A,Доп.расчеты!$A13,'Как будет'!AE:AE) -> 0 | AE13: =SUMIF('Как будет'!$A:$A,Доп.расчеты!$A13,'Как будет'!AF:AF) -> 0 | AF13: =SUMIF('Как будет'!$A:$A,Доп.расчеты!$A13,'Как будет'!AG:AG) -> 0 | AG13: =SUMIF('Как будет'!$A:$A,Доп.расчеты!$A13,'Как будет'!AH:AH) -> 0 | AH13: =SUMIF('Как будет'!$A:$A,Доп.расчеты!$A13,'Как будет'!AI:AI) -> 0 | AI13: =SUMIF('Как будет'!$A:$A,Доп.расчеты!$A13,'Как будет'!AJ:AJ) -> 0 | AJ13: =SUMIF('Как будет'!$A:$A,Доп.расчеты!$A13,'Как будет'!AK:AK) -> 0 | AK13: =SUMIF('Как будет'!$A:$A,Доп.расчеты!$A13,'Как будет'!AL:AL) -> 0 | AL13: =SUMIF('Как будет'!$A:$A,Доп.расчеты!$A13,'Как будет'!AM:AM) -> 0 | AM13: =SUMIF('Как будет'!$A:$A,Доп.расчеты!$A13,'Как будет'!AN:AN) -> 0 | AN13: =SUMIF('Как будет'!$A:$A,Доп.расчеты!$A13,'Как будет'!AO:AO) -> 0 | AO13: =SUMIF('Как будет'!$A:$A,Доп.расчеты!$A13,'Как будет'!AP:AP) -> 0 | AP13: =SUMIF('Как будет'!$A:$A,Доп.расчеты!$A13,'Как будет'!AQ:AQ) -> 0 | AQ13: =SUMIF('Как будет'!$A:$A,Доп.расчеты!$A13,'Как будет'!AR:AR) -> 0 | AR13: =SUMIF('Как будет'!$A:$A,Доп.расчеты!$A13,'Как будет'!AS:AS) -> 0 | AS13: =SUMIF('Как будет'!$A:$A,Доп.расчеты!$A13,'Как будет'!AT:AT) -> 0 | AT13: =SUMIF('Как будет'!$A:$A,Доп.расчеты!$A13,'Как будет'!AU:AU) -> 0 | AU13: =SUMIF('Как будет'!$A:$A,Доп.расчеты!$A13,'Как будет'!AV:AV) -> 0 | AV13: =SUMIF('Как будет'!$A:$A,Доп.расчеты!$A13,'Как будет'!AW:AW) -> 0 | AW13: =SUMIF('Как будет'!$A:$A,Доп.расчеты!$A13,'Как будет'!AX:AX) -> 0 | AX13: =SUMIF('Как будет'!$A:$A,Доп.расчеты!$A13,'Как будет'!AY:AY) -> 0 | AY13: =SUMIF('Как будет'!$A:$A,Доп.расчеты!$A13,'Как будет'!AZ:AZ) -> 0 | AZ13: =SUMIF('Как будет'!$A:$A,Доп.расчеты!$A13,'Как будет'!BA:BA) -> 0 | BA13: =SUMIF('Как будет'!$A:$A,Доп.расчеты!$A13,'Как будет'!BB:BB) -> 0 | BB13: =SUMIF('Как будет'!$A:$A,Доп.расчеты!$A13,'Как будет'!BC:BC) -> 0 | BC13: =SUMIF('Как будет'!$A:$A,Доп.расчеты!$A13,'Как будет'!BD:BD) -> 0 | BD13: =SUMIF('Как будет'!$A:$A,Доп.расчеты!$A13,'Как будет'!BE:BE) -> 0 | BE13: =SUMIF('Как будет'!$A:$A,Доп.расчеты!$A13,'Как будет'!BF:BF) -> 0 | BF13: =SUMIF('Как будет'!$A:$A,Доп.расчеты!$A13,'Как будет'!BG:BG) -> 0 | BG13: =SUMIF('Как будет'!$A:$A,Доп.расчеты!$A13,'Как будет'!BH:BH) -> 0 | BH13: =SUMIF('Как будет'!$A:$A,Доп.расчеты!$A13,'Как будет'!BI:BI) -> 0 | BI13: =SUMIF('Как будет'!$A:$A,Доп.расчеты!$A13,'Как будет'!BJ:BJ) -> 0 | BJ13: =SUMIF('Как будет'!$A:$A,Доп.расчеты!$A13,'Как будет'!BK:BK) -> 0 | BK13: =SUMIF('Как будет'!$A:$A,Доп.расчеты!$A13,'Как будет'!BL:BL) -> 0 | BL13: =SUMIF('Как будет'!$A:$A,Доп.расчеты!$A13,'Как будет'!BM:BM) -> 0 | BM13: =SUMIF('Как будет'!$A:$A,Доп.расчеты!$A13,'Как будет'!BN:BN) -> 0 | BN13: =SUMIF('Как будет'!$A:$A,Доп.расчеты!$A13,'Как будет'!BO:BO) -> 0 | BO13: =SUMIF('Как будет'!$A:$A,Доп.расчеты!$A13,'Как будет'!BP:BP) -> 0 | BP13: =SUMIF('Как будет'!$A:$A,Доп.расчеты!$A13,'Как будет'!BQ:BQ) -> 0 | BQ13: =SUMIF('Как будет'!$A:$A,Доп.расчеты!$A13,'Как будет'!BR:BR) -> 0 | BR13: =SUMIF('Как будет'!$A:$A,Доп.расчеты!$A13,'Как будет'!BS:BS) -> 0 | BS13: =SUMIF('Как будет'!$A:$A,Доп.расчеты!$A13,'Как будет'!BT:BT) -> 0 | BT13: =SUMIF('Как будет'!$A:$A,Доп.расчеты!$A13,'Как будет'!BU:BU) -> 0 | BU13: =SUMIF('Как будет'!$A:$A,Доп.расчеты!$A13,'Как будет'!BV:BV) -> 0 | BV13: =SUMIF('Как будет'!$A:$A,Доп.расчеты!$A13,'Как будет'!BW:BW) -> 0 | BW13: =SUMIF('Как будет'!$A:$A,Доп.расчеты!$A13,'Как будет'!BX:BX) -> 0 | BX13: =SUMIF('Как будет'!$A:$A,Доп.расчеты!$A13,'Как будет'!BY:BY) -> 0 | BY13: =SUMIF('Как будет'!$A:$A,Доп.расчеты!$A13,'Как будет'!BZ:BZ) -> 0 | BZ13: =SUMIF('Как будет'!$A:$A,Доп.расчеты!$A13,'Как будет'!CA:CA) -> 0 | CA13: =SUMIF('Как будет'!$A:$A,Доп.расчеты!$A13,'Как будет'!CB:CB) -> 0 | CB13: =SUMIF('Как будет'!$A:$A,Доп.расчеты!$A13,'Как будет'!CC:CC) -> 0 | CC13: =SUMIF('Как будет'!$A:$A,Доп.расчеты!$A13,'Как будет'!CD:CD) -> 0 | CD13: =SUMIF('Как будет'!$A:$A,Доп.расчеты!$A13,'Как будет'!CE:CE) -> 0 | CE13: =SUMIF('Как будет'!$A:$A,Доп.расчеты!$A13,'Как будет'!CF:CF) -> 0 | CF13: =SUMIF('Как будет'!$A:$A,Доп.расчеты!$A13,'Как будет'!CG:CG) -> 0 | CG13: =SUMIF('Как будет'!$A:$A,Доп.расчеты!$A13,'Как будет'!CH:CH) -> 0 | CH13: =SUMIF('Как будет'!$A:$A,Доп.расчеты!$A13,'Как будет'!CI:CI) -> 0 | CI13: =SUMIF('Как будет'!$A:$A,Доп.расчеты!$A13,'Как будет'!CJ:CJ) -> 0 | CJ13: =SUMIF('Как будет'!$A:$A,Доп.расчеты!$A13,'Как будет'!CK:CK) -> 0 | CK13: =SUMIF('Как будет'!$A:$A,Доп.расчеты!$A13,'Как будет'!CL:CL) -> 0 | CL13: =SUMIF('Как будет'!$A:$A,Доп.расчеты!$A13,'Как будет'!CM:CM) -> 0 | CM13: =SUMIF('Как будет'!$A:$A,Доп.расчеты!$A13,'Как будет'!CN:CN) -> 0 | CN13: =SUMIF('Как будет'!$A:$A,Доп.расчеты!$A13,'Как будет'!CO:CO) -> 0 | CO13: =SUMIF('Как будет'!$A:$A,Доп.расчеты!$A13,'Как будет'!CP:CP) -> 0 | CP13: =SUMIF('Как будет'!$A:$A,Доп.расчеты!$A13,'Как будет'!CQ:CQ) -> 0 | CQ13: =SUMIF('Как будет'!$A:$A,Доп.расчеты!$A13,'Как будет'!CR:CR) -> 0 | CR13: =SUMIF('Как будет'!$A:$A,Доп.расчеты!$A13,'Как будет'!CS:CS) -> 0 | CS13: =SUMIF('Как будет'!$A:$A,Доп.расчеты!$A13,'Как будет'!CT:CT) -> 0 | CT13: =SUMIF('Как будет'!$A:$A,Доп.расчеты!$A13,'Как будет'!CU:CU) -> 0 | CU13: =SUMIF('Как будет'!$A:$A,Доп.расчеты!$A13,'Как будет'!CV:CV) -> 0 | CV13: =SUMIF('Как будет'!$A:$A,Доп.расчеты!$A13,'Как будет'!CW:CW) -> 0 | CW13: =SUMIF('Как будет'!$A:$A,Доп.расчеты!$A13,'Как будет'!CX:CX) -> 0 | CX13: =SUMIF('Как будет'!$A:$A,Доп.расчеты!$A13,'Как будет'!CY:CY) -> 0 | CY13: =SUMIF('Как будет'!$A:$A,Доп.расчеты!$A13,'Как будет'!CZ:CZ) -> 0 | CZ13: =SUMIF('Как будет'!$A:$A,Доп.расчеты!$A13,'Как будет'!DA:DA) -> 0 | DA13: =SUMIF('Как будет'!$A:$A,Доп.расчеты!$A13,'Как будет'!DB:DB) -> 0 | DB13: =SUMIF('Как будет'!$A:$A,Доп.расчеты!$A13,'Как будет'!DC:DC) -> 0 | DC13: =SUMIF('Как будет'!$A:$A,Доп.расчеты!$A13,'Как будет'!DD:DD) -> 0 | DD13: =SUMIF('Как будет'!$A:$A,Доп.расчеты!$A13,'Как будет'!DE:DE) -> 0 | DE13: =SUMIF('Как будет'!$A:$A,Доп.расчеты!$A13,'Как будет'!DF:DF) -> 0 | DF13: =SUMIF('Как будет'!$A:$A,Доп.расчеты!$A13,'Как будет'!DG:DG) -> 0 | DG13: =SUMIF('Как будет'!$A:$A,Доп.расчеты!$A13,'Как будет'!DH:DH) -> 0 | DH13: =SUMIF('Как будет'!$A:$A,Доп.расчеты!$A13,'Как будет'!DI:DI) -> 0 | DI13: =SUMIF('Как будет'!$A:$A,Доп.расчеты!$A13,'Как будет'!DJ:DJ) -> 0 | DJ13: =SUMIF('Как будет'!$A:$A,Доп.расчеты!$A13,'Как будет'!DK:DK) -> 0 | DK13: =SUMIF('Как будет'!$A:$A,Доп.расчеты!$A13,'Как будет'!DL:DL) -> 0 | DL13: =SUMIF('Как будет'!$A:$A,Доп.расчеты!$A13,'Как будет'!DM:DM) -> 0 | DM13: =SUMIF('Как будет'!$A:$A,Доп.расчеты!$A13,'Как будет'!DN:DN) -> 0 | DN13: =SUMIF('Как будет'!$A:$A,Доп.расчеты!$A13,'Как будет'!DO:DO) -> 0 | DO13: =SUMIF('Как будет'!$A:$A,Доп.расчеты!$A13,'Как будет'!DP:DP) -> 0 | DP13: =SUMIF('Как будет'!$A:$A,Доп.расчеты!$A13,'Как будет'!DQ:DQ) -> 0 | DQ13: =SUMIF('Как будет'!$A:$A,Доп.расчеты!$A13,'Как будет'!DR:DR) -> 0 | DR13: =SUMIF('Как будет'!$A:$A,Доп.расчеты!$A13,'Как будет'!DS:DS) -> 0 | DS13: =SUMIF('Как будет'!$A:$A,Доп.расчеты!$A13,'Как будет'!DT:DT) -> 0 | DT13: =SUMIF('Как будет'!$A:$A,Доп.расчеты!$A13,'Как будет'!DU:DU) -> 0 | DU13: =SUMIF('Как будет'!$A:$A,Доп.расчеты!$A13,'Как будет'!DV:DV) -> 0 | DV13: =SUMIF('Как будет'!$A:$A,Доп.расчеты!$A13,'Как будет'!DW:DW) -> 0 | DW13: =SUMIF('Как будет'!$A:$A,Доп.расчеты!$A13,'Как будет'!DX:DX) -> 0 | DX13: =SUMIF('Как будет'!$A:$A,Доп.расчеты!$A13,'Как будет'!DY:DY) -> 0 | DY13: =SUMIF('Как будет'!$A:$A,Доп.расчеты!$A13,'Как будет'!DZ:DZ) -> 0 | DZ13: =SUMIF('Как будет'!$A:$A,Доп.расчеты!$A13,'Как будет'!EA:EA) -> 0 | EA13: =SUMIF('Как будет'!$A:$A,Доп.расчеты!$A13,'Как будет'!EB:EB) -> 0 | EB13: =SUMIF('Как будет'!$A:$A,Доп.расчеты!$A13,'Как будет'!EC:EC) -> 0 | EC13: =SUMIF('Как будет'!$A:$A,Доп.расчеты!$A13,'Как будет'!ED:ED) -> 0 | ED13: =SUMIF('Как будет'!$A:$A,Доп.расчеты!$A13,'Как будет'!EE:EE) -> 0 | EE13: =SUMIF('Как будет'!$A:$A,Доп.расчеты!$A13,'Как будет'!EF:EF) -> 0 | EF13: =SUMIF('Как будет'!$A:$A,Доп.расчеты!$A13,'Как будет'!EG:EG) -> 0 | EG13: =SUMIF('Как будет'!$A:$A,Доп.расчеты!$A13,'Как будет'!EH:EH) -> 0 | EH13: =SUMIF('Как будет'!$A:$A,Доп.расчеты!$A13,'Как будет'!EI:EI) -> 0 | EI13: =SUMIF('Как будет'!$A:$A,Доп.расчеты!$A13,'Как будет'!EJ:EJ) -> 0 | EJ13: =SUMIF('Как будет'!$A:$A,Доп.расчеты!$A13,'Как будет'!EK:EK) -> 0 | EK13: =SUMIF('Как будет'!$A:$A,Доп.расчеты!$A13,'Как будет'!EL:EL) -> 0 | EL13: =SUMIF('Как будет'!$A:$A,Доп.расчеты!$A13,'Как будет'!EM:EM) -> 0 | EM13: =SUMIF('Как будет'!$A:$A,Доп.расчеты!$A13,'Как будет'!EN:EN) -> 0 | EN13: =SUMIF('Как будет'!$A:$A,Доп.расчеты!$A13,'Как будет'!EO:EO) -> 0 | EO13: =SUMIF('Как будет'!$A:$A,Доп.расчеты!$A13,'Как будет'!EP:EP) -> 0 | EP13: =SUMIF('Как будет'!$A:$A,Доп.расчеты!$A13,'Как будет'!EQ:EQ) -> 0 | EQ13: =SUMIF('Как будет'!$A:$A,Доп.расчеты!$A13,'Как будет'!ER:ER) -> 0 | ER13: =SUMIF('Как будет'!$A:$A,Доп.расчеты!$A13,'Как будет'!ES:ES) -> 0 | ES13: =SUMIF('Как будет'!$A:$A,Доп.расчеты!$A13,'Как будет'!ET:ET) -> 0 | ET13: =SUMIF('Как будет'!$A:$A,Доп.расчеты!$A13,'Как будет'!EU:EU) -> 0 | EU13: =SUMIF('Как будет'!$A:$A,Доп.расчеты!$A13,'Как будет'!EV:EV) -> 0 | EV13: =SUMIF('Как будет'!$A:$A,Доп.расчеты!$A13,'Как будет'!EW:EW) -> 0 | EW13: =SUMIF('Как будет'!$A:$A,Доп.расчеты!$A13,'Как будет'!EX:EX) -> 0 | EX13: =SUMIF('Как будет'!$A:$A,Доп.расчеты!$A13,'Как будет'!EY:EY) -> 0 | EY13: =SUMIF('Как будет'!$A:$A,Доп.расчеты!$A13,'Как будет'!EZ:EZ) -> 0 | EZ13: =SUMIF('Как будет'!$A:$A,Доп.расчеты!$A13,'Как будет'!FA:FA) -> 0 | FA13: =SUMIF('Как будет'!$A:$A,Доп.расчеты!$A13,'Как будет'!FB:FB) -> 0 | FB13: =SUMIF('Как будет'!$A:$A,Доп.расчеты!$A13,'Как будет'!FC:FC) -> 0 | FC13: =SUMIF('Как будет'!$A:$A,Доп.расчеты!$A13,'Как будет'!FD:FD) -> 0 | FD13: =SUMIF('Как будет'!$A:$A,Доп.расчеты!$A13,'Как будет'!FE:FE) -> 0 | FE13: =SUMIF('Как будет'!$A:$A,Доп.расчеты!$A13,'Как будет'!FF:FF) -> 0 | FF13: =SUMIF('Как будет'!$A:$A,Доп.расчеты!$A13,'Как будет'!FG:FG) -> 0 | FG13: =SUMIF('Как будет'!$A:$A,Доп.расчеты!$A13,'Как будет'!FH:FH) -> 0 | FH13: =SUMIF('Как будет'!$A:$A,Доп.расчеты!$A13,'Как будет'!FI:FI) -> 0 | FI13: =SUMIF('Как будет'!$A:$A,Доп.расчеты!$A13,'Как будет'!FJ:FJ) -> 0 | FJ13: =SUMIF('Как будет'!$A:$A,Доп.расчеты!$A13,'Как будет'!FK:FK) -> 0 | FK13: =SUMIF('Как будет'!$A:$A,Доп.расчеты!$A13,'Как будет'!FL:FL) -> 0 | FL13: =SUMIF('Как будет'!$A:$A,Доп.расчеты!$A13,'Как будет'!FM:FM) -> 0 | FM13: =SUMIF('Как будет'!$A:$A,Доп.расчеты!$A13,'Как будет'!FN:FN) -> 0 | FN13: =SUMIF('Как будет'!$A:$A,Доп.расчеты!$A13,'Как будет'!FO:FO) -> 0 | FO13: =SUMIF('Как будет'!$A:$A,Доп.расчеты!$A13,'Как будет'!FP:FP) -> 0 | FP13: =SUMIF('Как будет'!$A:$A,Доп.расчеты!$A13,'Как будет'!FQ:FQ) -> 0 | FQ13: =SUMIF('Как будет'!$A:$A,Доп.расчеты!$A13,'Как будет'!FR:FR) -> 0 | FR13: =SUMIF('Как будет'!$A:$A,Доп.расчеты!$A13,'Как будет'!FS:FS) -> 0 | FS13: =SUMIF('Как будет'!$A:$A,Доп.расчеты!$A13,'Как будет'!FT:FT) -> 0 | FT13: =SUMIF('Как будет'!$A:$A,Доп.расчеты!$A13,'Как будет'!FU:FU) -> 0 | FU13: =SUMIF('Как будет'!$A:$A,Доп.расчеты!$A13,'Как будет'!FV:FV) -> 0 | FV13: =SUMIF('Как будет'!$A:$A,Доп.расчеты!$A13,'Как будет'!FW:FW) -> 0 | FW13: =SUMIF('Как будет'!$A:$A,Доп.расчеты!$A13,'Как будет'!FX:FX) -> 0 | FX13: =SUMIF('Как будет'!$A:$A,Доп.расчеты!$A13,'Как будет'!FY:FY) -> 0 | FY13: =SUMIF('Как будет'!$A:$A,Доп.расчеты!$A13,'Как будет'!FZ:FZ) -> 0 | FZ13: =SUMIF('Как будет'!$A:$A,Доп.расчеты!$A13,'Как будет'!GA:GA) -> 0 | GA13: =SUMIF('Как будет'!$A:$A,Доп.расчеты!$A13,'Как будет'!GB:GB) -> 0 | GB13: =SUMIF('Как будет'!$A:$A,Доп.расчеты!$A13,'Как будет'!GC:GC) -> 0 | GC13: =SUMIF('Как будет'!$A:$A,Доп.расчеты!$A13,'Как будет'!GD:GD) -> 0 | GD13: =SUMIF('Как будет'!$A:$A,Доп.расчеты!$A13,'Как будет'!GE:GE) -> 0 | GE13: =SUMIF('Как будет'!$A:$A,Доп.расчеты!$A13,'Как будет'!GF:GF) -> 0 | GF13: =SUMIF('Как будет'!$A:$A,Доп.расчеты!$A13,'Как будет'!GG:GG) -> 0 | GG13: =SUMIF('Как будет'!$A:$A,Доп.расчеты!$A13,'Как будет'!GH:GH) -> 0 | GH13: =SUMIF('Как будет'!$A:$A,Доп.расчеты!$A13,'Как будет'!GI:GI) -> 0 | GI13: =SUMIF('Как будет'!$A:$A,Доп.расчеты!$A13,'Как будет'!GJ:GJ) -> 0 | GJ13: =SUMIF('Как будет'!$A:$A,Доп.расчеты!$A13,'Как будет'!GK:GK) -> 0 | GK13: =SUMIF('Как будет'!$A:$A,Доп.расчеты!$A13,'Как будет'!GL:GL) -> 0 | GL13: =SUMIF('Как будет'!$A:$A,Доп.расчеты!$A13,'Как будет'!GM:GM) -> 0 | GM13: =SUMIF('Как будет'!$A:$A,Доп.расчеты!$A13,'Как будет'!GN:GN) -> 0 | GN13: =SUMIF('Как будет'!$A:$A,Доп.расчеты!$A13,'Как будет'!GO:GO) -> 0 | GO13: =SUMIF('Как будет'!$A:$A,Доп.расчеты!$A13,'Как будет'!GP:GP) -> 0 | GP13: =SUMIF('Как будет'!$A:$A,Доп.расчеты!$A13,'Как будет'!GQ:GQ) -> 0 | GQ13: =SUMIF('Как будет'!$A:$A,Доп.расчеты!$A13,'Как будет'!GR:GR) -> 0 | GR13: =SUMIF('Как будет'!$A:$A,Доп.расчеты!$A13,'Как будет'!GS:GS) -> 0 | GS13: =SUMIF('Как будет'!$A:$A,Доп.расчеты!$A13,'Как будет'!GT:GT) -> 0 | GT13: =SUMIF('Как будет'!$A:$A,Доп.расчеты!$A13,'Как будет'!GU:GU) -> 0
A14: Затраты производства | B14: =SUMIF('Как будет'!$A:$A,Доп.расчеты!$A14,'Как будет'!C:C) -> 0 | C14: =SUMIF('Как будет'!$A:$A,Доп.расчеты!$A14,'Как будет'!D:D) -> 0 | D14: =SUMIF('Как будет'!$A:$A,Доп.расчеты!$A14,'Как будет'!E:E) -> 0 | E14: =SUMIF('Как будет'!$A:$A,Доп.расчеты!$A14,'Как будет'!F:F) -> 0 | F14: =SUMIF('Как будет'!$A:$A,Доп.расчеты!$A14,'Как будет'!G:G) -> 0 | G14: =SUMIF('Как будет'!$A:$A,Доп.расчеты!$A14,'Как будет'!H:H) -> 0 | H14: =SUMIF('Как будет'!$A:$A,Доп.расчеты!$A14,'Как будет'!I:I) -> 0 | I14: =SUMIF('Как будет'!$A:$A,Доп.расчеты!$A14,'Как будет'!J:J) -> 0 | J14: =SUMIF('Как будет'!$A:$A,Доп.расчеты!$A14,'Как будет'!K:K) -> 0 | K14: =SUMIF('Как будет'!$A:$A,Доп.расчеты!$A14,'Как будет'!L:L) -> 0 | L14: =SUMIF('Как будет'!$A:$A,Доп.расчеты!$A14,'Как будет'!M:M) -> 0 | M14: =SUMIF('Как будет'!$A:$A,Доп.расчеты!$A14,'Как будет'!N:N) -> 0 | N14: =SUMIF('Как будет'!$A:$A,Доп.расчеты!$A14,'Как будет'!O:O) -> 0 | O14: =SUMIF('Как будет'!$A:$A,Доп.расчеты!$A14,'Как будет'!P:P) -> 0 | P14: =SUMIF('Как будет'!$A:$A,Доп.расчеты!$A14,'Как будет'!Q:Q) -> 0 | Q14: =SUMIF('Как будет'!$A:$A,Доп.расчеты!$A14,'Как будет'!R:R) -> 0 | R14: =SUMIF('Как будет'!$A:$A,Доп.расчеты!$A14,'Как будет'!S:S) -> 0 | S14: =SUMIF('Как будет'!$A:$A,Доп.расчеты!$A14,'Как будет'!T:T) -> 0 | T14: =SUMIF('Как будет'!$A:$A,Доп.расчеты!$A14,'Как будет'!U:U) -> 0 | U14: =SUMIF('Как будет'!$A:$A,Доп.расчеты!$A14,'Как будет'!V:V) -> 0 | V14: =SUMIF('Как будет'!$A:$A,Доп.расчеты!$A14,'Как будет'!W:W) -> 0 | W14: =SUMIF('Как будет'!$A:$A,Доп.расчеты!$A14,'Как будет'!X:X) -> 0 | X14: =SUMIF('Как будет'!$A:$A,Доп.расчеты!$A14,'Как будет'!Y:Y) -> 0 | Y14: =SUMIF('Как будет'!$A:$A,Доп.расчеты!$A14,'Как будет'!Z:Z) -> 0 | Z14: =SUMIF('Как будет'!$A:$A,Доп.расчеты!$A14,'Как будет'!AA:AA) -> 0 | AA14: =SUMIF('Как будет'!$A:$A,Доп.расчеты!$A14,'Как будет'!AB:AB) -> 0 | AB14: =SUMIF('Как будет'!$A:$A,Доп.расчеты!$A14,'Как будет'!AC:AC) -> 0 | AC14: =SUMIF('Как будет'!$A:$A,Доп.расчеты!$A14,'Как будет'!AD:AD) -> 0 | AD14: =SUMIF('Как будет'!$A:$A,Доп.расчеты!$A14,'Как будет'!AE:AE) -> 0 | AE14: =SUMIF('Как будет'!$A:$A,Доп.расчеты!$A14,'Как будет'!AF:AF) -> 0 | AF14: =SUMIF('Как будет'!$A:$A,Доп.расчеты!$A14,'Как будет'!AG:AG) -> 0 | AG14: =SUMIF('Как будет'!$A:$A,Доп.расчеты!$A14,'Как будет'!AH:AH) -> 0 | AH14: =SUMIF('Как будет'!$A:$A,Доп.расчеты!$A14,'Как будет'!AI:AI) -> 0 | AI14: =SUMIF('Как будет'!$A:$A,Доп.расчеты!$A14,'Как будет'!AJ:AJ) -> 0 | AJ14: =SUMIF('Как будет'!$A:$A,Доп.расчеты!$A14,'Как будет'!AK:AK) -> 0 | AK14: =SUMIF('Как будет'!$A:$A,Доп.расчеты!$A14,'Как будет'!AL:AL) -> 0 | AL14: =SUMIF('Как будет'!$A:$A,Доп.расчеты!$A14,'Как будет'!AM:AM) -> 0 | AM14: =SUMIF('Как будет'!$A:$A,Доп.расчеты!$A14,'Как будет'!AN:AN) -> 0 | AN14: =SUMIF('Как будет'!$A:$A,Доп.расчеты!$A14,'Как будет'!AO:AO) -> 0 | AO14: =SUMIF('Как будет'!$A:$A,Доп.расчеты!$A14,'Как будет'!AP:AP) -> 0 | AP14: =SUMIF('Как будет'!$A:$A,Доп.расчеты!$A14,'Как будет'!AQ:AQ) -> 0 | AQ14: =SUMIF('Как будет'!$A:$A,Доп.расчеты!$A14,'Как будет'!AR:AR) -> 0 | AR14: =SUMIF('Как будет'!$A:$A,Доп.расчеты!$A14,'Как будет'!AS:AS) -> 0 | AS14: =SUMIF('Как будет'!$A:$A,Доп.расчеты!$A14,'Как будет'!AT:AT) -> 0 | AT14: =SUMIF('Как будет'!$A:$A,Доп.расчеты!$A14,'Как будет'!AU:AU) -> 0 | AU14: =SUMIF('Как будет'!$A:$A,Доп.расчеты!$A14,'Как будет'!AV:AV) -> 0 | AV14: =SUMIF('Как будет'!$A:$A,Доп.расчеты!$A14,'Как будет'!AW:AW) -> 0 | AW14: =SUMIF('Как будет'!$A:$A,Доп.расчеты!$A14,'Как будет'!AX:AX) -> 0 | AX14: =SUMIF('Как будет'!$A:$A,Доп.расчеты!$A14,'Как будет'!AY:AY) -> 0 | AY14: =SUMIF('Как будет'!$A:$A,Доп.расчеты!$A14,'Как будет'!AZ:AZ) -> 0 | AZ14: =SUMIF('Как будет'!$A:$A,Доп.расчеты!$A14,'Как будет'!BA:BA) -> 0 | BA14: =SUMIF('Как будет'!$A:$A,Доп.расчеты!$A14,'Как будет'!BB:BB) -> 0 | BB14: =SUMIF('Как будет'!$A:$A,Доп.расчеты!$A14,'Как будет'!BC:BC) -> 0 | BC14: =SUMIF('Как будет'!$A:$A,Доп.расчеты!$A14,'Как будет'!BD:BD) -> 0 | BD14: =SUMIF('Как будет'!$A:$A,Доп.расчеты!$A14,'Как будет'!BE:BE) -> 0 | BE14: =SUMIF('Как будет'!$A:$A,Доп.расчеты!$A14,'Как будет'!BF:BF) -> 0 | BF14: =SUMIF('Как будет'!$A:$A,Доп.расчеты!$A14,'Как будет'!BG:BG) -> 0 | BG14: =SUMIF('Как будет'!$A:$A,Доп.расчеты!$A14,'Как будет'!BH:BH) -> 0 | BH14: =SUMIF('Как будет'!$A:$A,Доп.расчеты!$A14,'Как будет'!BI:BI) -> 0 | BI14: =SUMIF('Как будет'!$A:$A,Доп.расчеты!$A14,'Как будет'!BJ:BJ) -> 0 | BJ14: =SUMIF('Как будет'!$A:$A,Доп.расчеты!$A14,'Как будет'!BK:BK) -> 0 | BK14: =SUMIF('Как будет'!$A:$A,Доп.расчеты!$A14,'Как будет'!BL:BL) -> 0 | BL14: =SUMIF('Как будет'!$A:$A,Доп.расчеты!$A14,'Как будет'!BM:BM) -> 0 | BM14: =SUMIF('Как будет'!$A:$A,Доп.расчеты!$A14,'Как будет'!BN:BN) -> 0 | BN14: =SUMIF('Как будет'!$A:$A,Доп.расчеты!$A14,'Как будет'!BO:BO) -> 0 | BO14: =SUMIF('Как будет'!$A:$A,Доп.расчеты!$A14,'Как будет'!BP:BP) -> 0 | BP14: =SUMIF('Как будет'!$A:$A,Доп.расчеты!$A14,'Как будет'!BQ:BQ) -> 0 | BQ14: =SUMIF('Как будет'!$A:$A,Доп.расчеты!$A14,'Как будет'!BR:BR) -> 0 | BR14: =SUMIF('Как будет'!$A:$A,Доп.расчеты!$A14,'Как будет'!BS:BS) -> 0 | BS14: =SUMIF('Как будет'!$A:$A,Доп.расчеты!$A14,'Как будет'!BT:BT) -> 0 | BT14: =SUMIF('Как будет'!$A:$A,Доп.расчеты!$A14,'Как будет'!BU:BU) -> 0 | BU14: =SUMIF('Как будет'!$A:$A,Доп.расчеты!$A14,'Как будет'!BV:BV) -> 0 | BV14: =SUMIF('Как будет'!$A:$A,Доп.расчеты!$A14,'Как будет'!BW:BW) -> 0 | BW14: =SUMIF('Как будет'!$A:$A,Доп.расчеты!$A14,'Как будет'!BX:BX) -> 0 | BX14: =SUMIF('Как будет'!$A:$A,Доп.расчеты!$A14,'Как будет'!BY:BY) -> 0 | BY14: =SUMIF('Как будет'!$A:$A,Доп.расчеты!$A14,'Как будет'!BZ:BZ) -> 0 | BZ14: =SUMIF('Как будет'!$A:$A,Доп.расчеты!$A14,'Как будет'!CA:CA) -> 0 | CA14: =SUMIF('Как будет'!$A:$A,Доп.расчеты!$A14,'Как будет'!CB:CB) -> 0 | CB14: =SUMIF('Как будет'!$A:$A,Доп.расчеты!$A14,'Как будет'!CC:CC) -> 0 | CC14: =SUMIF('Как будет'!$A:$A,Доп.расчеты!$A14,'Как будет'!CD:CD) -> 0 | CD14: =SUMIF('Как будет'!$A:$A,Доп.расчеты!$A14,'Как будет'!CE:CE) -> 0 | CE14: =SUMIF('Как будет'!$A:$A,Доп.расчеты!$A14,'Как будет'!CF:CF) -> 0 | CF14: =SUMIF('Как будет'!$A:$A,Доп.расчеты!$A14,'Как будет'!CG:CG) -> 0 | CG14: =SUMIF('Как будет'!$A:$A,Доп.расчеты!$A14,'Как будет'!CH:CH) -> 0 | CH14: =SUMIF('Как будет'!$A:$A,Доп.расчеты!$A14,'Как будет'!CI:CI) -> 0 | CI14: =SUMIF('Как будет'!$A:$A,Доп.расчеты!$A14,'Как будет'!CJ:CJ) -> 0 | CJ14: =SUMIF('Как будет'!$A:$A,Доп.расчеты!$A14,'Как будет'!CK:CK) -> 0 | CK14: =SUMIF('Как будет'!$A:$A,Доп.расчеты!$A14,'Как будет'!CL:CL) -> 0 | CL14: =SUMIF('Как будет'!$A:$A,Доп.расчеты!$A14,'Как будет'!CM:CM) -> 0 | CM14: =SUMIF('Как будет'!$A:$A,Доп.расчеты!$A14,'Как будет'!CN:CN) -> 0 | CN14: =SUMIF('Как будет'!$A:$A,Доп.расчеты!$A14,'Как будет'!CO:CO) -> 0 | CO14: =SUMIF('Как будет'!$A:$A,Доп.расчеты!$A14,'Как будет'!CP:CP) -> 0 | CP14: =SUMIF('Как будет'!$A:$A,Доп.расчеты!$A14,'Как будет'!CQ:CQ) -> 0 | CQ14: =SUMIF('Как будет'!$A:$A,Доп.расчеты!$A14,'Как будет'!CR:CR) -> 0 | CR14: =SUMIF('Как будет'!$A:$A,Доп.расчеты!$A14,'Как будет'!CS:CS) -> 0 | CS14: =SUMIF('Как будет'!$A:$A,Доп.расчеты!$A14,'Как будет'!CT:CT) -> 0 | CT14: =SUMIF('Как будет'!$A:$A,Доп.расчеты!$A14,'Как будет'!CU:CU) -> 0 | CU14: =SUMIF('Как будет'!$A:$A,Доп.расчеты!$A14,'Как будет'!CV:CV) -> 0 | CV14: =SUMIF('Как будет'!$A:$A,Доп.расчеты!$A14,'Как будет'!CW:CW) -> 0 | CW14: =SUMIF('Как будет'!$A:$A,Доп.расчеты!$A14,'Как будет'!CX:CX) -> 0 | CX14: =SUMIF('Как будет'!$A:$A,Доп.расчеты!$A14,'Как будет'!CY:CY) -> 0 | CY14: =SUMIF('Как будет'!$A:$A,Доп.расчеты!$A14,'Как будет'!CZ:CZ) -> 0 | CZ14: =SUMIF('Как будет'!$A:$A,Доп.расчеты!$A14,'Как будет'!DA:DA) -> 0 | DA14: =SUMIF('Как будет'!$A:$A,Доп.расчеты!$A14,'Как будет'!DB:DB) -> 0 | DB14: =SUMIF('Как будет'!$A:$A,Доп.расчеты!$A14,'Как будет'!DC:DC) -> 0 | DC14: =SUMIF('Как будет'!$A:$A,Доп.расчеты!$A14,'Как будет'!DD:DD) -> 0 | DD14: =SUMIF('Как будет'!$A:$A,Доп.расчеты!$A14,'Как будет'!DE:DE) -> 0 | DE14: =SUMIF('Как будет'!$A:$A,Доп.расчеты!$A14,'Как будет'!DF:DF) -> 0 | DF14: =SUMIF('Как будет'!$A:$A,Доп.расчеты!$A14,'Как будет'!DG:DG) -> 0 | DG14: =SUMIF('Как будет'!$A:$A,Доп.расчеты!$A14,'Как будет'!DH:DH) -> 0 | DH14: =SUMIF('Как будет'!$A:$A,Доп.расчеты!$A14,'Как будет'!DI:DI) -> 0 | DI14: =SUMIF('Как будет'!$A:$A,Доп.расчеты!$A14,'Как будет'!DJ:DJ) -> 0 | DJ14: =SUMIF('Как будет'!$A:$A,Доп.расчеты!$A14,'Как будет'!DK:DK) -> 0 | DK14: =SUMIF('Как будет'!$A:$A,Доп.расчеты!$A14,'Как будет'!DL:DL) -> 0 | DL14: =SUMIF('Как будет'!$A:$A,Доп.расчеты!$A14,'Как будет'!DM:DM) -> 0 | DM14: =SUMIF('Как будет'!$A:$A,Доп.расчеты!$A14,'Как будет'!DN:DN) -> 0 | DN14: =SUMIF('Как будет'!$A:$A,Доп.расчеты!$A14,'Как будет'!DO:DO) -> 0 | DO14: =SUMIF('Как будет'!$A:$A,Доп.расчеты!$A14,'Как будет'!DP:DP) -> 0 | DP14: =SUMIF('Как будет'!$A:$A,Доп.расчеты!$A14,'Как будет'!DQ:DQ) -> 0 | DQ14: =SUMIF('Как будет'!$A:$A,Доп.расчеты!$A14,'Как будет'!DR:DR) -> 0 | DR14: =SUMIF('Как будет'!$A:$A,Доп.расчеты!$A14,'Как будет'!DS:DS) -> 0 | DS14: =SUMIF('Как будет'!$A:$A,Доп.расчеты!$A14,'Как будет'!DT:DT) -> 0 | DT14: =SUMIF('Как будет'!$A:$A,Доп.расчеты!$A14,'Как будет'!DU:DU) -> 0 | DU14: =SUMIF('Как будет'!$A:$A,Доп.расчеты!$A14,'Как будет'!DV:DV) -> 0 | DV14: =SUMIF('Как будет'!$A:$A,Доп.расчеты!$A14,'Как будет'!DW:DW) -> 0 | DW14: =SUMIF('Как будет'!$A:$A,Доп.расчеты!$A14,'Как будет'!DX:DX) -> 0 | DX14: =SUMIF('Как будет'!$A:$A,Доп.расчеты!$A14,'Как будет'!DY:DY) -> 0 | DY14: =SUMIF('Как будет'!$A:$A,Доп.расчеты!$A14,'Как будет'!DZ:DZ) -> 0 | DZ14: =SUMIF('Как будет'!$A:$A,Доп.расчеты!$A14,'Как будет'!EA:EA) -> 0 | EA14: =SUMIF('Как будет'!$A:$A,Доп.расчеты!$A14,'Как будет'!EB:EB) -> 0 | EB14: =SUMIF('Как будет'!$A:$A,Доп.расчеты!$A14,'Как будет'!EC:EC) -> 0 | EC14: =SUMIF('Как будет'!$A:$A,Доп.расчеты!$A14,'Как будет'!ED:ED) -> 0 | ED14: =SUMIF('Как будет'!$A:$A,Доп.расчеты!$A14,'Как будет'!EE:EE) -> 0 | EE14: =SUMIF('Как будет'!$A:$A,Доп.расчеты!$A14,'Как будет'!EF:EF) -> 0 | EF14: =SUMIF('Как будет'!$A:$A,Доп.расчеты!$A14,'Как будет'!EG:EG) -> 0 | EG14: =SUMIF('Как будет'!$A:$A,Доп.расчеты!$A14,'Как будет'!EH:EH) -> 0 | EH14: =SUMIF('Как будет'!$A:$A,Доп.расчеты!$A14,'Как будет'!EI:EI) -> 0 | EI14: =SUMIF('Как будет'!$A:$A,Доп.расчеты!$A14,'Как будет'!EJ:EJ) -> 0 | EJ14: =SUMIF('Как будет'!$A:$A,Доп.расчеты!$A14,'Как будет'!EK:EK) -> 0 | EK14: =SUMIF('Как будет'!$A:$A,Доп.расчеты!$A14,'Как будет'!EL:EL) -> 0 | EL14: =SUMIF('Как будет'!$A:$A,Доп.расчеты!$A14,'Как будет'!EM:EM) -> 0 | EM14: =SUMIF('Как будет'!$A:$A,Доп.расчеты!$A14,'Как будет'!EN:EN) -> 0 | EN14: =SUMIF('Как будет'!$A:$A,Доп.расчеты!$A14,'Как будет'!EO:EO) -> 0 | EO14: =SUMIF('Как будет'!$A:$A,Доп.расчеты!$A14,'Как будет'!EP:EP) -> 0 | EP14: =SUMIF('Как будет'!$A:$A,Доп.расчеты!$A14,'Как будет'!EQ:EQ) -> 0 | EQ14: =SUMIF('Как будет'!$A:$A,Доп.расчеты!$A14,'Как будет'!ER:ER) -> 0 | ER14: =SUMIF('Как будет'!$A:$A,Доп.расчеты!$A14,'Как будет'!ES:ES) -> 0 | ES14: =SUMIF('Как будет'!$A:$A,Доп.расчеты!$A14,'Как будет'!ET:ET) -> 0 | ET14: =SUMIF('Как будет'!$A:$A,Доп.расчеты!$A14,'Как будет'!EU:EU) -> 0 | EU14: =SUMIF('Как будет'!$A:$A,Доп.расчеты!$A14,'Как будет'!EV:EV) -> 0 | EV14: =SUMIF('Как будет'!$A:$A,Доп.расчеты!$A14,'Как будет'!EW:EW) -> 0 | EW14: =SUMIF('Как будет'!$A:$A,Доп.расчеты!$A14,'Как будет'!EX:EX) -> 0 | EX14: =SUMIF('Как будет'!$A:$A,Доп.расчеты!$A14,'Как будет'!EY:EY) -> 0 | EY14: =SUMIF('Как будет'!$A:$A,Доп.расчеты!$A14,'Как будет'!EZ:EZ) -> 0 | EZ14: =SUMIF('Как будет'!$A:$A,Доп.расчеты!$A14,'Как будет'!FA:FA) -> 0 | FA14: =SUMIF('Как будет'!$A:$A,Доп.расчеты!$A14,'Как будет'!FB:FB) -> 0 | FB14: =SUMIF('Как будет'!$A:$A,Доп.расчеты!$A14,'Как будет'!FC:FC) -> 0 | FC14: =SUMIF('Как будет'!$A:$A,Доп.расчеты!$A14,'Как будет'!FD:FD) -> 0 | FD14: =SUMIF('Как будет'!$A:$A,Доп.расчеты!$A14,'Как будет'!FE:FE) -> 0 | FE14: =SUMIF('Как будет'!$A:$A,Доп.расчеты!$A14,'Как будет'!FF:FF) -> 0 | FF14: =SUMIF('Как будет'!$A:$A,Доп.расчеты!$A14,'Как будет'!FG:FG) -> 0 | FG14: =SUMIF('Как будет'!$A:$A,Доп.расчеты!$A14,'Как будет'!FH:FH) -> 0 | FH14: =SUMIF('Как будет'!$A:$A,Доп.расчеты!$A14,'Как будет'!FI:FI) -> 0 | FI14: =SUMIF('Как будет'!$A:$A,Доп.расчеты!$A14,'Как будет'!FJ:FJ) -> 0 | FJ14: =SUMIF('Как будет'!$A:$A,Доп.расчеты!$A14,'Как будет'!FK:FK) -> 0 | FK14: =SUMIF('Как будет'!$A:$A,Доп.расчеты!$A14,'Как будет'!FL:FL) -> 0 | FL14: =SUMIF('Как будет'!$A:$A,Доп.расчеты!$A14,'Как будет'!FM:FM) -> 0 | FM14: =SUMIF('Как будет'!$A:$A,Доп.расчеты!$A14,'Как будет'!FN:FN) -> 0 | FN14: =SUMIF('Как будет'!$A:$A,Доп.расчеты!$A14,'Как будет'!FO:FO) -> 0 | FO14: =SUMIF('Как будет'!$A:$A,Доп.расчеты!$A14,'Как будет'!FP:FP) -> 0 | FP14: =SUMIF('Как будет'!$A:$A,Доп.расчеты!$A14,'Как будет'!FQ:FQ) -> 0 | FQ14: =SUMIF('Как будет'!$A:$A,Доп.расчеты!$A14,'Как будет'!FR:FR) -> 0 | FR14: =SUMIF('Как будет'!$A:$A,Доп.расчеты!$A14,'Как будет'!FS:FS) -> 0 | FS14: =SUMIF('Как будет'!$A:$A,Доп.расчеты!$A14,'Как будет'!FT:FT) -> 0 | FT14: =SUMIF('Как будет'!$A:$A,Доп.расчеты!$A14,'Как будет'!FU:FU) -> 0 | FU14: =SUMIF('Как будет'!$A:$A,Доп.расчеты!$A14,'Как будет'!FV:FV) -> 0 | FV14: =SUMIF('Как будет'!$A:$A,Доп.расчеты!$A14,'Как будет'!FW:FW) -> 0 | FW14: =SUMIF('Как будет'!$A:$A,Доп.расчеты!$A14,'Как будет'!FX:FX) -> 0 | FX14: =SUMIF('Как будет'!$A:$A,Доп.расчеты!$A14,'Как будет'!FY:FY) -> 0 | FY14: =SUMIF('Как будет'!$A:$A,Доп.расчеты!$A14,'Как будет'!FZ:FZ) -> 0 | FZ14: =SUMIF('Как будет'!$A:$A,Доп.расчеты!$A14,'Как будет'!GA:GA) -> 0 | GA14: =SUMIF('Как будет'!$A:$A,Доп.расчеты!$A14,'Как будет'!GB:GB) -> 0 | GB14: =SUMIF('Как будет'!$A:$A,Доп.расчеты!$A14,'Как будет'!GC:GC) -> 0 | GC14: =SUMIF('Как будет'!$A:$A,Доп.расчеты!$A14,'Как будет'!GD:GD) -> 0 | GD14: =SUMIF('Как будет'!$A:$A,Доп.расчеты!$A14,'Как будет'!GE:GE) -> 0 | GE14: =SUMIF('Как будет'!$A:$A,Доп.расчеты!$A14,'Как будет'!GF:GF) -> 0 | GF14: =SUMIF('Как будет'!$A:$A,Доп.расчеты!$A14,'Как будет'!GG:GG) -> 0 | GG14: =SUMIF('Как будет'!$A:$A,Доп.расчеты!$A14,'Как будет'!GH:GH) -> 0 | GH14: =SUMIF('Как будет'!$A:$A,Доп.расчеты!$A14,'Как будет'!GI:GI) -> 0 | GI14: =SUMIF('Как будет'!$A:$A,Доп.расчеты!$A14,'Как будет'!GJ:GJ) -> 0 | GJ14: =SUMIF('Как будет'!$A:$A,Доп.расчеты!$A14,'Как будет'!GK:GK) -> 0 | GK14: =SUMIF('Как будет'!$A:$A,Доп.расчеты!$A14,'Как будет'!GL:GL) -> 0 | GL14: =SUMIF('Как будет'!$A:$A,Доп.расчеты!$A14,'Как будет'!GM:GM) -> 0 | GM14: =SUMIF('Как будет'!$A:$A,Доп.расчеты!$A14,'Как будет'!GN:GN) -> 0 | GN14: =SUMIF('Как будет'!$A:$A,Доп.расчеты!$A14,'Как будет'!GO:GO) -> 0 | GO14: =SUMIF('Как будет'!$A:$A,Доп.расчеты!$A14,'Как будет'!GP:GP) -> 0 | GP14: =SUMIF('Как будет'!$A:$A,Доп.расчеты!$A14,'Как будет'!GQ:GQ) -> 0 | GQ14: =SUMIF('Как будет'!$A:$A,Доп.расчеты!$A14,'Как будет'!GR:GR) -> 0 | GR14: =SUMIF('Как будет'!$A:$A,Доп.расчеты!$A14,'Как будет'!GS:GS) -> 0 | GS14: =SUMIF('Как будет'!$A:$A,Доп.расчеты!$A14,'Как будет'!GT:GT) -> 0 | GT14: =SUMIF('Как будет'!$A:$A,Доп.расчеты!$A14,'Как будет'!GU:GU) -> 0
